Workbook

Sheet Moggio
B1: Dati generali
B2: Asset | D2: Moggio
B3: Acquisto | C3: Valore immobile | D3: -65000 | E3: 46148 | F3: =EDATE(E3,($E$5)*12)-1 -> 55278
B4: Data acquisto | E4: 46148 | F4: =EDATE(E4,($E$5)*12)-1 -> 55278 | I4: IRR | J4: =$L$302 -> 0.93417179
B5: Anni investimento | E5: 25 | I5: NPV | J5: =MAX(300:300) -> 10671.016
B6: Acquisto da? | E6: Privato/Imprese
B7: Prima casa? | E7: NO
B8: Rendita catastale | C8: - | D8: 619.75 | E8: =$E$4 -> 46148 | F8: =EDATE(E8,$E$5*12)-1 -> 55278
B9: Rivalutazione | C9: - | D9: 0.005 | E9: =$E$4 -> 46148 | F9: =F4 -> 55278
B12: Ricavi
B13: Affitto | C13: Alloggio | D13: 3000 | E13: =$E$4 -> 46148 | F13: =EDATE(E13,$E$5*12)-1 -> 55278
B15: Vendita | C15: Alloggio | D15: =-$D$3*(1+D9)^E5 -> 73631.712 | E15: =EDATE($E$4,$E$5*12)-1 -> 55278 | F15: =EDATE($E$4,$E$5*12) -> 55279
B17: Costi
B18: Condominio | C18: Ordinario | D18: =1200 -> 1200 | E18: =$E$4 -> 46148 | F18: =EDATE(E18,$E$5*12)-1 -> 55278
B19: Assicurazione | C19: - | D19: 0 | E19: =$E$4 -> 46148 | F19: 46053
B20: Utenze | C20: Gas | D20: 0 | E20: =$E$4 -> 46148 | F20: =EDATE(E20,$E$5*12)-1 -> 55278
B21: Utenze | C21: Luce | D21: =-50*12 -> -600 | E21: =$E$4 -> 46148 | F21: =EDATE(E21,$E$5*12)-1 -> 55278
B22: Utenze | C22: Internet | D22: =-38.83*6 -> -232.98 | E22: =$E$4 -> 46148 | F22: =EDATE(E22,$E$5*12)-1 -> 55278
B23: Manutenzione ordinaria | C23: - | D23: -100 | E23: =$E$4 -> 46148 | F23: =EDATE(E23,$E$5*12)-1 -> 55278
B24: Manutenzione straordinaria | C24: - | D24: -200 | E24: =$E$4 -> 46148 | F24: =EDATE(E24,$E$5*12)-1 -> 55278
B27: Ammortamenti
B28: Anni | D28: =SUMIFS(#REF!,#REF!,$B28) -> #REF!
B30: Oneri finanziari
B35: Avviamento
B36: Avviamento | C36: Notaio | D36: -2000 | E36: =$E$4 -> 46148 | F36: =EDATE(E36,$E$5*12)-1 -> 55278
B37: Avviamento | C37: Intermediazione | D37: =-3000*1.22 -> -3660 | E37: =$E$4 -> 46148 | F37: =EDATE(E37,$E$5*12)-1 -> 55278
B38: Avviamento | C38: - | D38: -1000 | E38: =$E$4 -> 46148 | F38: =EDATE(E38,$E$5*12)-1 -> 55278
B39: Arredamento | C39: - | D39: -3000 | E39: =$E$4 -> 46148 | F39: =EDATE(E39,$E$5*12)-1 -> 55278
B40: Ristrutturazione | C40: - | D40: -5000 | E40: =$E$4 -> 46148 | F40: =EDATE(E40,$E$5*12)-1 -> 55278
B42: Tasse
B43: Imposte | C43: Registro | D43: =-IF($E$7="SI",MAX(2%*$D$8*105%*120,1000),MAX(9%*$D$8*105%*120,1000)) -> -7027.965 | E43: =$E$4 -> 46148 | F43: =EDATE(E43,$E$5*12)-1 -> 55278
B44: Imposte | C44: Ipotecaria | D44: =-IF($E$6="Privato/Imprese",50,200) -> -50 | E44: =$E$4 -> 46148 | F44: =EDATE(E44,$E$5*12)-1 -> 55278
B45: Imposte | C45: Catastale | D45: =-IF($E$6="Privato/Imprese",50,200) -> -50 | E45: =$E$4 -> 46148 | F45: =EDATE(E45,$E$5*12)-1 -> 55278
B47: Imposte | C47: IMU | D47: =IF($E$7="SI",0,$D$8*1.05*160*1.06%) -> 1103.6508 | E47: =$E$4 -> 46148 | F47: =EDATE(E47,$E$5*12)-1 -> 55278
B48: Imposte | C48: TARI | D48: -176 | E48: =$E$4 -> 46148 | F48: =EDATE(E48,$E$5*12)-1 -> 55278
B51: Detrazioni
B52: Mutuo | C52: Cap detrazione | D52: =4000*$D$31/294000 -> 0 | E52: Ripartizione mutuo
B53: Mutuo | C53: % detrazione | D53: 0.19
B54: Intermediazione | C54: Cap detrazione | D54: 1000
B55: Intermediazione | C55: % detrazione | D55: 0.19
B56: Ristrutturazione | C56: Cap detrazione | D56: 96000
B57: Ristrutturazione | C57: % detrazione | D57: 0.5
B58: Arredamento | C58: Cap detrazione | D58: 10000 | E58: 44562 | F58: 44592
B59: Arredamento | C59: Cap detrazione | D59: 8000 | E59: 44927 | F59: 44957
B60: Arredamento | C60: Cap detrazione | D60: 5000 | E60: 45292 | F60: 45322
B61: Arredamento | C61: % detrazione | D61: 0.5
B62: Offset detrazioni | D62: 1
I65: Profit & Loss
I67: Tipo | J67: Servizio | K67: Voce | L67: =YEAR($E$4) -> 2026 | M67: =IF(L67<>"",IF(L67+1<=YEAR($E$4)+$E$5+$D$62,L67+1,""),"") -> 2027 | N67: =IF(M67<>"",IF(M67+1<=YEAR($E$4)+$E$5+$D$62,M67+1,""),"") -> 2028 | O67: =IF(N67<>"",IF(N67+1<=YEAR($E$4)+$E$5+$D$62,N67+1,""),"") -> 2029 | P67: =IF(O67<>"",IF(O67+1<=YEAR($E$4)+$E$5+$D$62,O67+1,""),"") -> 2030 | Q67: =IF(P67<>"",IF(P67+1<=YEAR($E$4)+$E$5+$D$62,P67+1,""),"") -> 2031 | R67: =IF(Q67<>"",IF(Q67+1<=YEAR($E$4)+$E$5+$D$62,Q67+1,""),"") -> 2032 | S67: =IF(R67<>"",IF(R67+1<=YEAR($E$4)+$E$5+$D$62,R67+1,""),"") -> 2033 | T67: =IF(S67<>"",IF(S67+1<=YEAR($E$4)+$E$5+$D$62,S67+1,""),"") -> 2034 | ... AO67: =IF(AN67<>"",IF(AN67+1<=YEAR($E$4)+$E$5+$D$62,AN67+1,""),"")
J69: Affitto | K69: Alloggio | L69: =IF(AND(TRUE,L$67<>""),SUMIFS(Flussi!$F:$F,Flussi!$B:$B,L$67,Flussi!$D:$D,$J69,Flussi!$E:$E,$K69,Flussi!$A:$A,$D$2),"") -> 3000 | M69: =IF(AND(TRUE,M$67<>""),SUMIFS(Flussi!$F:$F,Flussi!$B:$B,M$67,Flussi!$D:$D,$J69,Flussi!$E:$E,$K69,Flussi!$A:$A,$D$2),"") -> 3000 | N69: =IF(AND(TRUE,N$67<>""),SUMIFS(Flussi!$F:$F,Flussi!$B:$B,N$67,Flussi!$D:$D,$J69,Flussi!$E:$E,$K69,Flussi!$A:$A,$D$2),"") -> 3000 | O69: =IF(AND(TRUE,O$67<>""),SUMIFS(Flussi!$F:$F,Flussi!$B:$B,O$67,Flussi!$D:$D,$J69,Flussi!$E:$E,$K69,Flussi!$A:$A,$D$2),"") -> 3000 | P69: =IF(AND(TRUE,P$67<>""),SUMIFS(Flussi!$F:$F,Flussi!$B:$B,P$67,Flussi!$D:$D,$J69,Flussi!$E:$E,$K69,Flussi!$A:$A,$D$2),"") -> 3000 | Q69: =IF(AND(TRUE,Q$67<>""),SUMIFS(Flussi!$F:$F,Flussi!$B:$B,Q$67,Flussi!$D:$D,$J69,Flussi!$E:$E,$K69,Flussi!$A:$A,$D$2),"") -> 3000 | R69: =IF(AND(TRUE,R$67<>""),SUMIFS(Flussi!$F:$F,Flussi!$B:$B,R$67,Flussi!$D:$D,$J69,Flussi!$E:$E,$K69,Flussi!$A:$A,$D$2),"") -> 3000 | S69: =IF(AND(TRUE,S$67<>""),SUMIFS(Flussi!$F:$F,Flussi!$B:$B,S$67,Flussi!$D:$D,$J69,Flussi!$E:$E,$K69,Flussi!$A:$A,$D$2),"") -> 3000 | ... AO69: =IF(AND(TRUE,AO$67<>""),SUMIFS(Flussi!$F:$F,Flussi!$B:$B,AO$67,Flussi!$D:$D,$J69,Flussi!$E:$E,$K69,Flussi!$A:$A,$D$2),"")
J70: Affitto | K70: Box | L70: =IF(AND(TRUE,L$67<>""),SUMIFS(Flussi!$F:$F,Flussi!$B:$B,L$67,Flussi!$D:$D,$J70,Flussi!$E:$E,$K70,Flussi!$A:$A,$D$2),"") -> 0 | M70: =IF(AND(TRUE,M$67<>""),SUMIFS(Flussi!$F:$F,Flussi!$B:$B,M$67,Flussi!$D:$D,$J70,Flussi!$E:$E,$K70,Flussi!$A:$A,$D$2),"") -> 0 | N70: =IF(AND(TRUE,N$67<>""),SUMIFS(Flussi!$F:$F,Flussi!$B:$B,N$67,Flussi!$D:$D,$J70,Flussi!$E:$E,$K70,Flussi!$A:$A,$D$2),"") -> 0 | O70: =IF(AND(TRUE,O$67<>""),SUMIFS(Flussi!$F:$F,Flussi!$B:$B,O$67,Flussi!$D:$D,$J70,Flussi!$E:$E,$K70,Flussi!$A:$A,$D$2),"") -> 0 | P70: =IF(AND(TRUE,P$67<>""),SUMIFS(Flussi!$F:$F,Flussi!$B:$B,P$67,Flussi!$D:$D,$J70,Flussi!$E:$E,$K70,Flussi!$A:$A,$D$2),"") -> 0 | Q70: =IF(AND(TRUE,Q$67<>""),SUMIFS(Flussi!$F:$F,Flussi!$B:$B,Q$67,Flussi!$D:$D,$J70,Flussi!$E:$E,$K70,Flussi!$A:$A,$D$2),"") -> 0 | R70: =IF(AND(TRUE,R$67<>""),SUMIFS(Flussi!$F:$F,Flussi!$B:$B,R$67,Flussi!$D:$D,$J70,Flussi!$E:$E,$K70,Flussi!$A:$A,$D$2),"") -> 0 | S70: =IF(AND(TRUE,S$67<>""),SUMIFS(Flussi!$F:$F,Flussi!$B:$B,S$67,Flussi!$D:$D,$J70,Flussi!$E:$E,$K70,Flussi!$A:$A,$D$2),"") -> 0 | ... AO70: =IF(AND(TRUE,AO$67<>""),SUMIFS(Flussi!$F:$F,Flussi!$B:$B,AO$67,Flussi!$D:$D,$J70,Flussi!$E:$E,$K70,Flussi!$A:$A,$D$2),"")
J71: Vendita | K71: Alloggio | L71: =IF(AND(TRUE,L$67<>""),SUMIFS(Flussi!$F:$F,Flussi!$B:$B,L$67,Flussi!$D:$D,$J71,Flussi!$E:$E,$K71,Flussi!$A:$A,$D$2),"") -> 0 | M71: =IF(AND(TRUE,M$67<>""),SUMIFS(Flussi!$F:$F,Flussi!$B:$B,M$67,Flussi!$D:$D,$J71,Flussi!$E:$E,$K71,Flussi!$A:$A,$D$2),"") -> 0 | N71: =IF(AND(TRUE,N$67<>""),SUMIFS(Flussi!$F:$F,Flussi!$B:$B,N$67,Flussi!$D:$D,$J71,Flussi!$E:$E,$K71,Flussi!$A:$A,$D$2),"") -> 0 | O71: =IF(AND(TRUE,O$67<>""),SUMIFS(Flussi!$F:$F,Flussi!$B:$B,O$67,Flussi!$D:$D,$J71,Flussi!$E:$E,$K71,Flussi!$A:$A,$D$2),"") -> 0 | P71: =IF(AND(TRUE,P$67<>""),SUMIFS(Flussi!$F:$F,Flussi!$B:$B,P$67,Flussi!$D:$D,$J71,Flussi!$E:$E,$K71,Flussi!$A:$A,$D$2),"") -> 0 | Q71: =IF(AND(TRUE,Q$67<>""),SUMIFS(Flussi!$F:$F,Flussi!$B:$B,Q$67,Flussi!$D:$D,$J71,Flussi!$E:$E,$K71,Flussi!$A:$A,$D$2),"") -> 0 | R71: =IF(AND(TRUE,R$67<>""),SUMIFS(Flussi!$F:$F,Flussi!$B:$B,R$67,Flussi!$D:$D,$J71,Flussi!$E:$E,$K71,Flussi!$A:$A,$D$2),"") -> 0 | S71: =IF(AND(TRUE,S$67<>""),SUMIFS(Flussi!$F:$F,Flussi!$B:$B,S$67,Flussi!$D:$D,$J71,Flussi!$E:$E,$K71,Flussi!$A:$A,$D$2),"") -> 0 | ... AO71: =IF(AND(TRUE,AO$67<>""),SUMIFS(Flussi!$F:$F,Flussi!$B:$B,AO$67,Flussi!$D:$D,$J71,Flussi!$E:$E,$K71,Flussi!$A:$A,$D$2),"")
J72: Vendita | K72: Box | L72: =IF(AND(TRUE,L$67<>""),SUMIFS(Flussi!$F:$F,Flussi!$B:$B,L$67,Flussi!$D:$D,$J72,Flussi!$E:$E,$K72,Flussi!$A:$A,$D$2),"") -> 0 | M72: =IF(AND(TRUE,M$67<>""),SUMIFS(Flussi!$F:$F,Flussi!$B:$B,M$67,Flussi!$D:$D,$J72,Flussi!$E:$E,$K72,Flussi!$A:$A,$D$2),"") -> 0 | N72: =IF(AND(TRUE,N$67<>""),SUMIFS(Flussi!$F:$F,Flussi!$B:$B,N$67,Flussi!$D:$D,$J72,Flussi!$E:$E,$K72,Flussi!$A:$A,$D$2),"") -> 0 | O72: =IF(AND(TRUE,O$67<>""),SUMIFS(Flussi!$F:$F,Flussi!$B:$B,O$67,Flussi!$D:$D,$J72,Flussi!$E:$E,$K72,Flussi!$A:$A,$D$2),"") -> 0 | P72: =IF(AND(TRUE,P$67<>""),SUMIFS(Flussi!$F:$F,Flussi!$B:$B,P$67,Flussi!$D:$D,$J72,Flussi!$E:$E,$K72,Flussi!$A:$A,$D$2),"") -> 0 | Q72: =IF(AND(TRUE,Q$67<>""),SUMIFS(Flussi!$F:$F,Flussi!$B:$B,Q$67,Flussi!$D:$D,$J72,Flussi!$E:$E,$K72,Flussi!$A:$A,$D$2),"") -> 0 | R72: =IF(AND(TRUE,R$67<>""),SUMIFS(Flussi!$F:$F,Flussi!$B:$B,R$67,Flussi!$D:$D,$J72,Flussi!$E:$E,$K72,Flussi!$A:$A,$D$2),"") -> 0 | S72: =IF(AND(TRUE,S$67<>""),SUMIFS(Flussi!$F:$F,Flussi!$B:$B,S$67,Flussi!$D:$D,$J72,Flussi!$E:$E,$K72,Flussi!$A:$A,$D$2),"") -> 0 | ... AO72: =IF(AND(TRUE,AO$67<>""),SUMIFS(Flussi!$F:$F,Flussi!$B:$B,AO$67,Flussi!$D:$D,$J72,Flussi!$E:$E,$K72,Flussi!$A:$A,$D$2),"")
I73: Ricavi | K73: P&L | L73: =IF(AND(TRUE,L$67<>""),SUM(L69:L72),"") -> 3000 | M73: =IF(AND(TRUE,M$67<>""),SUM(M69:M72),"") -> 3000 | N73: =IF(AND(TRUE,N$67<>""),SUM(N69:N72),"") -> 3000 | O73: =IF(AND(TRUE,O$67<>""),SUM(O69:O72),"") -> 3000 | P73: =IF(AND(TRUE,P$67<>""),SUM(P69:P72),"") -> 3000 | Q73: =IF(AND(TRUE,Q$67<>""),SUM(Q69:Q72),"") -> 3000 | R73: =IF(AND(TRUE,R$67<>""),SUM(R69:R72),"") -> 3000 | S73: =IF(AND(TRUE,S$67<>""),SUM(S69:S72),"") -> 3000 | ... AO73: =IF(AND(TRUE,AO$67<>""),SUM(AO69:AO72),"")
J74: Utenze | K74: Gas | L74: =IF(AND(TRUE,L$67<>""),SUMIFS(Flussi!$F:$F,Flussi!$B:$B,L$67,Flussi!$D:$D,$J74,Flussi!$E:$E,$K74,Flussi!$A:$A,$D$2),"") -> 0 | M74: =IF(AND(TRUE,M$67<>""),SUMIFS(Flussi!$F:$F,Flussi!$B:$B,M$67,Flussi!$D:$D,$J74,Flussi!$E:$E,$K74,Flussi!$A:$A,$D$2),"") -> 0 | N74: =IF(AND(TRUE,N$67<>""),SUMIFS(Flussi!$F:$F,Flussi!$B:$B,N$67,Flussi!$D:$D,$J74,Flussi!$E:$E,$K74,Flussi!$A:$A,$D$2),"") -> 0 | O74: =IF(AND(TRUE,O$67<>""),SUMIFS(Flussi!$F:$F,Flussi!$B:$B,O$67,Flussi!$D:$D,$J74,Flussi!$E:$E,$K74,Flussi!$A:$A,$D$2),"") -> 0 | P74: =IF(AND(TRUE,P$67<>""),SUMIFS(Flussi!$F:$F,Flussi!$B:$B,P$67,Flussi!$D:$D,$J74,Flussi!$E:$E,$K74,Flussi!$A:$A,$D$2),"") -> 0 | Q74: =IF(AND(TRUE,Q$67<>""),SUMIFS(Flussi!$F:$F,Flussi!$B:$B,Q$67,Flussi!$D:$D,$J74,Flussi!$E:$E,$K74,Flussi!$A:$A,$D$2),"") -> 0 | R74: =IF(AND(TRUE,R$67<>""),SUMIFS(Flussi!$F:$F,Flussi!$B:$B,R$67,Flussi!$D:$D,$J74,Flussi!$E:$E,$K74,Flussi!$A:$A,$D$2),"") -> 0 | S74: =IF(AND(TRUE,S$67<>""),SUMIFS(Flussi!$F:$F,Flussi!$B:$B,S$67,Flussi!$D:$D,$J74,Flussi!$E:$E,$K74,Flussi!$A:$A,$D$2),"") -> 0 | ... AO74: =IF(AND(TRUE,AO$67<>""),SUMIFS(Flussi!$F:$F,Flussi!$B:$B,AO$67,Flussi!$D:$D,$J74,Flussi!$E:$E,$K74,Flussi!$A:$A,$D$2),"")
J75: Utenze | K75: Luce | L75: =IF(AND(TRUE,L$67<>""),SUMIFS(Flussi!$F:$F,Flussi!$B:$B,L$67,Flussi!$D:$D,$J75,Flussi!$E:$E,$K75,Flussi!$A:$A,$D$2),"") -> -843 | M75: =IF(AND(TRUE,M$67<>""),SUMIFS(Flussi!$F:$F,Flussi!$B:$B,M$67,Flussi!$D:$D,$J75,Flussi!$E:$E,$K75,Flussi!$A:$A,$D$2),"") -> -600 | N75: =IF(AND(TRUE,N$67<>""),SUMIFS(Flussi!$F:$F,Flussi!$B:$B,N$67,Flussi!$D:$D,$J75,Flussi!$E:$E,$K75,Flussi!$A:$A,$D$2),"") -> -600 | O75: =IF(AND(TRUE,O$67<>""),SUMIFS(Flussi!$F:$F,Flussi!$B:$B,O$67,Flussi!$D:$D,$J75,Flussi!$E:$E,$K75,Flussi!$A:$A,$D$2),"") -> -600 | P75: =IF(AND(TRUE,P$67<>""),SUMIFS(Flussi!$F:$F,Flussi!$B:$B,P$67,Flussi!$D:$D,$J75,Flussi!$E:$E,$K75,Flussi!$A:$A,$D$2),"") -> -600 | Q75: =IF(AND(TRUE,Q$67<>""),SUMIFS(Flussi!$F:$F,Flussi!$B:$B,Q$67,Flussi!$D:$D,$J75,Flussi!$E:$E,$K75,Flussi!$A:$A,$D$2),"") -> -600 | R75: =IF(AND(TRUE,R$67<>""),SUMIFS(Flussi!$F:$F,Flussi!$B:$B,R$67,Flussi!$D:$D,$J75,Flussi!$E:$E,$K75,Flussi!$A:$A,$D$2),"") -> -600 | S75: =IF(AND(TRUE,S$67<>""),SUMIFS(Flussi!$F:$F,Flussi!$B:$B,S$67,Flussi!$D:$D,$J75,Flussi!$E:$E,$K75,Flussi!$A:$A,$D$2),"") -> -600 | ... AO75: =IF(AND(TRUE,AO$67<>""),SUMIFS(Flussi!$F:$F,Flussi!$B:$B,AO$67,Flussi!$D:$D,$J75,Flussi!$E:$E,$K75,Flussi!$A:$A,$D$2),"")
J76: Utenze | K76: Internet | L76: =IF(AND(TRUE,L$67<>""),SUMIFS(Flussi!$F:$F,Flussi!$B:$B,L$67,Flussi!$D:$D,$J76,Flussi!$E:$E,$K76,Flussi!$A:$A,$D$2),"") -> -232.98 | M76: =IF(AND(TRUE,M$67<>""),SUMIFS(Flussi!$F:$F,Flussi!$B:$B,M$67,Flussi!$D:$D,$J76,Flussi!$E:$E,$K76,Flussi!$A:$A,$D$2),"") -> -232.98 | N76: =IF(AND(TRUE,N$67<>""),SUMIFS(Flussi!$F:$F,Flussi!$B:$B,N$67,Flussi!$D:$D,$J76,Flussi!$E:$E,$K76,Flussi!$A:$A,$D$2),"") -> -232.98 | O76: =IF(AND(TRUE,O$67<>""),SUMIFS(Flussi!$F:$F,Flussi!$B:$B,O$67,Flussi!$D:$D,$J76,Flussi!$E:$E,$K76,Flussi!$A:$A,$D$2),"") -> -232.98 | P76: =IF(AND(TRUE,P$67<>""),SUMIFS(Flussi!$F:$F,Flussi!$B:$B,P$67,Flussi!$D:$D,$J76,Flussi!$E:$E,$K76,Flussi!$A:$A,$D$2),"") -> -232.98 | Q76: =IF(AND(TRUE,Q$67<>""),SUMIFS(Flussi!$F:$F,Flussi!$B:$B,Q$67,Flussi!$D:$D,$J76,Flussi!$E:$E,$K76,Flussi!$A:$A,$D$2),"") -> -232.98 | R76: =IF(AND(TRUE,R$67<>""),SUMIFS(Flussi!$F:$F,Flussi!$B:$B,R$67,Flussi!$D:$D,$J76,Flussi!$E:$E,$K76,Flussi!$A:$A,$D$2),"") -> -232.98 | S76: =IF(AND(TRUE,S$67<>""),SUMIFS(Flussi!$F:$F,Flussi!$B:$B,S$67,Flussi!$D:$D,$J76,Flussi!$E:$E,$K76,Flussi!$A:$A,$D$2),"") -> -232.98 | ... AO76: =IF(AND(TRUE,AO$67<>""),SUMIFS(Flussi!$F:$F,Flussi!$B:$B,AO$67,Flussi!$D:$D,$J76,Flussi!$E:$E,$K76,Flussi!$A:$A,$D$2),"")
J77: Avviamento | K77: Intermediazione | L77: =IF(AND(TRUE,L$67<>""),SUMIFS(Flussi!$F:$F,Flussi!$B:$B,L$67,Flussi!$D:$D,$J77,Flussi!$E:$E,$K77,Flussi!$A:$A,$D$2),"") -> -3660 | M77: =IF(AND(TRUE,M$67<>""),SUMIFS(Flussi!$F:$F,Flussi!$B:$B,M$67,Flussi!$D:$D,$J77,Flussi!$E:$E,$K77,Flussi!$A:$A,$D$2),"") -> 0 | N77: =IF(AND(TRUE,N$67<>""),SUMIFS(Flussi!$F:$F,Flussi!$B:$B,N$67,Flussi!$D:$D,$J77,Flussi!$E:$E,$K77,Flussi!$A:$A,$D$2),"") -> 0 | O77: =IF(AND(TRUE,O$67<>""),SUMIFS(Flussi!$F:$F,Flussi!$B:$B,O$67,Flussi!$D:$D,$J77,Flussi!$E:$E,$K77,Flussi!$A:$A,$D$2),"") -> 0 | P77: =IF(AND(TRUE,P$67<>""),SUMIFS(Flussi!$F:$F,Flussi!$B:$B,P$67,Flussi!$D:$D,$J77,Flussi!$E:$E,$K77,Flussi!$A:$A,$D$2),"") -> 0 | Q77: =IF(AND(TRUE,Q$67<>""),SUMIFS(Flussi!$F:$F,Flussi!$B:$B,Q$67,Flussi!$D:$D,$J77,Flussi!$E:$E,$K77,Flussi!$A:$A,$D$2),"") -> 0 | R77: =IF(AND(TRUE,R$67<>""),SUMIFS(Flussi!$F:$F,Flussi!$B:$B,R$67,Flussi!$D:$D,$J77,Flussi!$E:$E,$K77,Flussi!$A:$A,$D$2),"") -> 0 | S77: =IF(AND(TRUE,S$67<>""),SUMIFS(Flussi!$F:$F,Flussi!$B:$B,S$67,Flussi!$D:$D,$J77,Flussi!$E:$E,$K77,Flussi!$A:$A,$D$2),"") -> 0 | ... AO77: =IF(AND(TRUE,AO$67<>""),SUMIFS(Flussi!$F:$F,Flussi!$B:$B,AO$67,Flussi!$D:$D,$J77,Flussi!$E:$E,$K77,Flussi!$A:$A,$D$2),"")
J78: Avviamento | K78: Notaio | L78: =IF(AND(TRUE,L$67<>""),SUMIFS(Flussi!$F:$F,Flussi!$B:$B,L$67,Flussi!$D:$D,$J78,Flussi!$E:$E,$K78,Flussi!$A:$A,$D$2),"") -> 1425.2 | M78: =IF(AND(TRUE,M$67<>""),SUMIFS(Flussi!$F:$F,Flussi!$B:$B,M$67,Flussi!$D:$D,$J78,Flussi!$E:$E,$K78,Flussi!$A:$A,$D$2),"") -> 0 | N78: =IF(AND(TRUE,N$67<>""),SUMIFS(Flussi!$F:$F,Flussi!$B:$B,N$67,Flussi!$D:$D,$J78,Flussi!$E:$E,$K78,Flussi!$A:$A,$D$2),"") -> 0 | O78: =IF(AND(TRUE,O$67<>""),SUMIFS(Flussi!$F:$F,Flussi!$B:$B,O$67,Flussi!$D:$D,$J78,Flussi!$E:$E,$K78,Flussi!$A:$A,$D$2),"") -> 0 | P78: =IF(AND(TRUE,P$67<>""),SUMIFS(Flussi!$F:$F,Flussi!$B:$B,P$67,Flussi!$D:$D,$J78,Flussi!$E:$E,$K78,Flussi!$A:$A,$D$2),"") -> 0 | Q78: =IF(AND(TRUE,Q$67<>""),SUMIFS(Flussi!$F:$F,Flussi!$B:$B,Q$67,Flussi!$D:$D,$J78,Flussi!$E:$E,$K78,Flussi!$A:$A,$D$2),"") -> 0 | R78: =IF(AND(TRUE,R$67<>""),SUMIFS(Flussi!$F:$F,Flussi!$B:$B,R$67,Flussi!$D:$D,$J78,Flussi!$E:$E,$K78,Flussi!$A:$A,$D$2),"") -> 0 | S78: =IF(AND(TRUE,S$67<>""),SUMIFS(Flussi!$F:$F,Flussi!$B:$B,S$67,Flussi!$D:$D,$J78,Flussi!$E:$E,$K78,Flussi!$A:$A,$D$2),"") -> 0 | ... AO78: =IF(AND(TRUE,AO$67<>""),SUMIFS(Flussi!$F:$F,Flussi!$B:$B,AO$67,Flussi!$D:$D,$J78,Flussi!$E:$E,$K78,Flussi!$A:$A,$D$2),"")
J79: Condominio | K79: Ordinario | L79: =IF(AND(TRUE,L$67<>""),SUMIFS(Flussi!$F:$F,Flussi!$B:$B,L$67,Flussi!$D:$D,$J79,Flussi!$E:$E,$K79,Flussi!$A:$A,$D$2),"") -> -1115.86 | M79: =IF(AND(TRUE,M$67<>""),SUMIFS(Flussi!$F:$F,Flussi!$B:$B,M$67,Flussi!$D:$D,$J79,Flussi!$E:$E,$K79,Flussi!$A:$A,$D$2),"") -> 385.14 | N79: =IF(AND(TRUE,N$67<>""),SUMIFS(Flussi!$F:$F,Flussi!$B:$B,N$67,Flussi!$D:$D,$J79,Flussi!$E:$E,$K79,Flussi!$A:$A,$D$2),"") -> 1200 | O79: =IF(AND(TRUE,O$67<>""),SUMIFS(Flussi!$F:$F,Flussi!$B:$B,O$67,Flussi!$D:$D,$J79,Flussi!$E:$E,$K79,Flussi!$A:$A,$D$2),"") -> 1200 | P79: =IF(AND(TRUE,P$67<>""),SUMIFS(Flussi!$F:$F,Flussi!$B:$B,P$67,Flussi!$D:$D,$J79,Flussi!$E:$E,$K79,Flussi!$A:$A,$D$2),"") -> 1200 | Q79: =IF(AND(TRUE,Q$67<>""),SUMIFS(Flussi!$F:$F,Flussi!$B:$B,Q$67,Flussi!$D:$D,$J79,Flussi!$E:$E,$K79,Flussi!$A:$A,$D$2),"") -> 1200 | R79: =IF(AND(TRUE,R$67<>""),SUMIFS(Flussi!$F:$F,Flussi!$B:$B,R$67,Flussi!$D:$D,$J79,Flussi!$E:$E,$K79,Flussi!$A:$A,$D$2),"") -> 1200 | S79: =IF(AND(TRUE,S$67<>""),SUMIFS(Flussi!$F:$F,Flussi!$B:$B,S$67,Flussi!$D:$D,$J79,Flussi!$E:$E,$K79,Flussi!$A:$A,$D$2),"") -> 1200 | ... AO79: =IF(AND(TRUE,AO$67<>""),SUMIFS(Flussi!$F:$F,Flussi!$B:$B,AO$67,Flussi!$D:$D,$J79,Flussi!$E:$E,$K79,Flussi!$A:$A,$D$2),"")
J80: Condominio | K80: Straordinario | L80: =IF(AND(TRUE,L$67<>""),SUMIFS(Flussi!$F:$F,Flussi!$B:$B,L$67,Flussi!$D:$D,$J80,Flussi!$E:$E,$K80,Flussi!$A:$A,$D$2),"") -> -972.58 | M80: =IF(AND(TRUE,M$67<>""),SUMIFS(Flussi!$F:$F,Flussi!$B:$B,M$67,Flussi!$D:$D,$J80,Flussi!$E:$E,$K80,Flussi!$A:$A,$D$2),"") -> 0 | N80: =IF(AND(TRUE,N$67<>""),SUMIFS(Flussi!$F:$F,Flussi!$B:$B,N$67,Flussi!$D:$D,$J80,Flussi!$E:$E,$K80,Flussi!$A:$A,$D$2),"") -> 0 | O80: =IF(AND(TRUE,O$67<>""),SUMIFS(Flussi!$F:$F,Flussi!$B:$B,O$67,Flussi!$D:$D,$J80,Flussi!$E:$E,$K80,Flussi!$A:$A,$D$2),"") -> 0 | P80: =IF(AND(TRUE,P$67<>""),SUMIFS(Flussi!$F:$F,Flussi!$B:$B,P$67,Flussi!$D:$D,$J80,Flussi!$E:$E,$K80,Flussi!$A:$A,$D$2),"") -> 0 | Q80: =IF(AND(TRUE,Q$67<>""),SUMIFS(Flussi!$F:$F,Flussi!$B:$B,Q$67,Flussi!$D:$D,$J80,Flussi!$E:$E,$K80,Flussi!$A:$A,$D$2),"") -> 0 | R80: =IF(AND(TRUE,R$67<>""),SUMIFS(Flussi!$F:$F,Flussi!$B:$B,R$67,Flussi!$D:$D,$J80,Flussi!$E:$E,$K80,Flussi!$A:$A,$D$2),"") -> 0 | S80: =IF(AND(TRUE,S$67<>""),SUMIFS(Flussi!$F:$F,Flussi!$B:$B,S$67,Flussi!$D:$D,$J80,Flussi!$E:$E,$K80,Flussi!$A:$A,$D$2),"") -> 0 | ... AO80: =IF(AND(TRUE,AO$67<>""),SUMIFS(Flussi!$F:$F,Flussi!$B:$B,AO$67,Flussi!$D:$D,$J80,Flussi!$E:$E,$K80,Flussi!$A:$A,$D$2),"")
J81: Assicurazione | K81: - | L81: =IF(AND(TRUE,L$67<>""),SUMIFS(Flussi!$F:$F,Flussi!$B:$B,L$67,Flussi!$D:$D,$J81,Flussi!$E:$E,$K81,Flussi!$A:$A,$D$2),"") -> 0 | M81: =IF(AND(TRUE,M$67<>""),SUMIFS(Flussi!$F:$F,Flussi!$B:$B,M$67,Flussi!$D:$D,$J81,Flussi!$E:$E,$K81,Flussi!$A:$A,$D$2),"") -> 0 | N81: =IF(AND(TRUE,N$67<>""),SUMIFS(Flussi!$F:$F,Flussi!$B:$B,N$67,Flussi!$D:$D,$J81,Flussi!$E:$E,$K81,Flussi!$A:$A,$D$2),"") -> 0 | O81: =IF(AND(TRUE,O$67<>""),SUMIFS(Flussi!$F:$F,Flussi!$B:$B,O$67,Flussi!$D:$D,$J81,Flussi!$E:$E,$K81,Flussi!$A:$A,$D$2),"") -> 0 | P81: =IF(AND(TRUE,P$67<>""),SUMIFS(Flussi!$F:$F,Flussi!$B:$B,P$67,Flussi!$D:$D,$J81,Flussi!$E:$E,$K81,Flussi!$A:$A,$D$2),"") -> 0 | Q81: =IF(AND(TRUE,Q$67<>""),SUMIFS(Flussi!$F:$F,Flussi!$B:$B,Q$67,Flussi!$D:$D,$J81,Flussi!$E:$E,$K81,Flussi!$A:$A,$D$2),"") -> 0 | R81: =IF(AND(TRUE,R$67<>""),SUMIFS(Flussi!$F:$F,Flussi!$B:$B,R$67,Flussi!$D:$D,$J81,Flussi!$E:$E,$K81,Flussi!$A:$A,$D$2),"") -> 0 | S81: =IF(AND(TRUE,S$67<>""),SUMIFS(Flussi!$F:$F,Flussi!$B:$B,S$67,Flussi!$D:$D,$J81,Flussi!$E:$E,$K81,Flussi!$A:$A,$D$2),"") -> 0 | ... AO81: =IF(AND(TRUE,AO$67<>""),SUMIFS(Flussi!$F:$F,Flussi!$B:$B,AO$67,Flussi!$D:$D,$J81,Flussi!$E:$E,$K81,Flussi!$A:$A,$D$2),"")
J82: Manutenzione ordinaria | K82: - | L82: =IF(AND(TRUE,L$67<>""),SUMIFS(Flussi!$F:$F,Flussi!$B:$B,L$67,Flussi!$D:$D,$J82,Flussi!$E:$E,$K82,Flussi!$A:$A,$D$2),"") -> -100 | M82: =IF(AND(TRUE,M$67<>""),SUMIFS(Flussi!$F:$F,Flussi!$B:$B,M$67,Flussi!$D:$D,$J82,Flussi!$E:$E,$K82,Flussi!$A:$A,$D$2),"") -> -100 | N82: =IF(AND(TRUE,N$67<>""),SUMIFS(Flussi!$F:$F,Flussi!$B:$B,N$67,Flussi!$D:$D,$J82,Flussi!$E:$E,$K82,Flussi!$A:$A,$D$2),"") -> -100 | O82: =IF(AND(TRUE,O$67<>""),SUMIFS(Flussi!$F:$F,Flussi!$B:$B,O$67,Flussi!$D:$D,$J82,Flussi!$E:$E,$K82,Flussi!$A:$A,$D$2),"") -> -100 | P82: =IF(AND(TRUE,P$67<>""),SUMIFS(Flussi!$F:$F,Flussi!$B:$B,P$67,Flussi!$D:$D,$J82,Flussi!$E:$E,$K82,Flussi!$A:$A,$D$2),"") -> -100 | Q82: =IF(AND(TRUE,Q$67<>""),SUMIFS(Flussi!$F:$F,Flussi!$B:$B,Q$67,Flussi!$D:$D,$J82,Flussi!$E:$E,$K82,Flussi!$A:$A,$D$2),"") -> -100 | R82: =IF(AND(TRUE,R$67<>""),SUMIFS(Flussi!$F:$F,Flussi!$B:$B,R$67,Flussi!$D:$D,$J82,Flussi!$E:$E,$K82,Flussi!$A:$A,$D$2),"") -> -100 | S82: =IF(AND(TRUE,S$67<>""),SUMIFS(Flussi!$F:$F,Flussi!$B:$B,S$67,Flussi!$D:$D,$J82,Flussi!$E:$E,$K82,Flussi!$A:$A,$D$2),"") -> -100 | ... AO82: =IF(AND(TRUE,AO$67<>""),SUMIFS(Flussi!$F:$F,Flussi!$B:$B,AO$67,Flussi!$D:$D,$J82,Flussi!$E:$E,$K82,Flussi!$A:$A,$D$2),"")
J83: Manutenzione straordinaria | K83: - | L83: =IF(AND(TRUE,L$67<>""),SUMIFS(Flussi!$F:$F,Flussi!$B:$B,L$67,Flussi!$D:$D,$J83,Flussi!$E:$E,$K83,Flussi!$A:$A,$D$2),"") -> -200 | M83: =IF(AND(TRUE,M$67<>""),SUMIFS(Flussi!$F:$F,Flussi!$B:$B,M$67,Flussi!$D:$D,$J83,Flussi!$E:$E,$K83,Flussi!$A:$A,$D$2),"") -> -200 | N83: =IF(AND(TRUE,N$67<>""),SUMIFS(Flussi!$F:$F,Flussi!$B:$B,N$67,Flussi!$D:$D,$J83,Flussi!$E:$E,$K83,Flussi!$A:$A,$D$2),"") -> -200 | O83: =IF(AND(TRUE,O$67<>""),SUMIFS(Flussi!$F:$F,Flussi!$B:$B,O$67,Flussi!$D:$D,$J83,Flussi!$E:$E,$K83,Flussi!$A:$A,$D$2),"") -> -200 | P83: =IF(AND(TRUE,P$67<>""),SUMIFS(Flussi!$F:$F,Flussi!$B:$B,P$67,Flussi!$D:$D,$J83,Flussi!$E:$E,$K83,Flussi!$A:$A,$D$2),"") -> -200 | Q83: =IF(AND(TRUE,Q$67<>""),SUMIFS(Flussi!$F:$F,Flussi!$B:$B,Q$67,Flussi!$D:$D,$J83,Flussi!$E:$E,$K83,Flussi!$A:$A,$D$2),"") -> -200 | R83: =IF(AND(TRUE,R$67<>""),SUMIFS(Flussi!$F:$F,Flussi!$B:$B,R$67,Flussi!$D:$D,$J83,Flussi!$E:$E,$K83,Flussi!$A:$A,$D$2),"") -> -200 | S83: =IF(AND(TRUE,S$67<>""),SUMIFS(Flussi!$F:$F,Flussi!$B:$B,S$67,Flussi!$D:$D,$J83,Flussi!$E:$E,$K83,Flussi!$A:$A,$D$2),"") -> -200 | ... AO83: =IF(AND(TRUE,AO$67<>""),SUMIFS(Flussi!$F:$F,Flussi!$B:$B,AO$67,Flussi!$D:$D,$J83,Flussi!$E:$E,$K83,Flussi!$A:$A,$D$2),"")
J84: Storno | K84: - | L84: =IF(AND(TRUE,L$67<>""),SUMIFS(Flussi!$F:$F,Flussi!$B:$B,L$67,Flussi!$D:$D,$J84,Flussi!$E:$E,$K84,Flussi!$A:$A,$D$2),"") -> 0 | M84: =IF(AND(TRUE,M$67<>""),SUMIFS(Flussi!$F:$F,Flussi!$B:$B,M$67,Flussi!$D:$D,$J84,Flussi!$E:$E,$K84,Flussi!$A:$A,$D$2),"") -> 0 | N84: =IF(AND(TRUE,N$67<>""),SUMIFS(Flussi!$F:$F,Flussi!$B:$B,N$67,Flussi!$D:$D,$J84,Flussi!$E:$E,$K84,Flussi!$A:$A,$D$2),"") -> 0 | O84: =IF(AND(TRUE,O$67<>""),SUMIFS(Flussi!$F:$F,Flussi!$B:$B,O$67,Flussi!$D:$D,$J84,Flussi!$E:$E,$K84,Flussi!$A:$A,$D$2),"") -> 0 | P84: =IF(AND(TRUE,P$67<>""),SUMIFS(Flussi!$F:$F,Flussi!$B:$B,P$67,Flussi!$D:$D,$J84,Flussi!$E:$E,$K84,Flussi!$A:$A,$D$2),"") -> 0 | Q84: =IF(AND(TRUE,Q$67<>""),SUMIFS(Flussi!$F:$F,Flussi!$B:$B,Q$67,Flussi!$D:$D,$J84,Flussi!$E:$E,$K84,Flussi!$A:$A,$D$2),"") -> 0 | R84: =IF(AND(TRUE,R$67<>""),SUMIFS(Flussi!$F:$F,Flussi!$B:$B,R$67,Flussi!$D:$D,$J84,Flussi!$E:$E,$K84,Flussi!$A:$A,$D$2),"") -> 0 | S84: =IF(AND(TRUE,S$67<>""),SUMIFS(Flussi!$F:$F,Flussi!$B:$B,S$67,Flussi!$D:$D,$J84,Flussi!$E:$E,$K84,Flussi!$A:$A,$D$2),"") -> 0 | ... AO84: =IF(AND(TRUE,AO$67<>""),SUMIFS(Flussi!$F:$F,Flussi!$B:$B,AO$67,Flussi!$D:$D,$J84,Flussi!$E:$E,$K84,Flussi!$A:$A,$D$2),"")
I85: Costi | K85: P&L | L85: =IF(AND(TRUE,L$67<>""),SUM(L74:L84),"") -> -5699.22 | M85: =IF(AND(TRUE,M$67<>""),SUM(M74:M84),"") -> -747.84 | N85: =IF(AND(TRUE,N$67<>""),SUM(N74:N84),"") -> 67.02 | O85: =IF(AND(TRUE,O$67<>""),SUM(O74:O84),"") -> 67.02 | P85: =IF(AND(TRUE,P$67<>""),SUM(P74:P84),"") -> 67.02 | Q85: =IF(AND(TRUE,Q$67<>""),SUM(Q74:Q84),"") -> 67.02 | R85: =IF(AND(TRUE,R$67<>""),SUM(R74:R84),"") -> 67.02 | S85: =IF(AND(TRUE,S$67<>""),SUM(S74:S84),"") -> 67.02 | ... AO85: =IF(AND(TRUE,AO$67<>""),SUM(AO74:AO84),"")
I86: EBIDTA | K86: P&L | L86: =IF(AND(TRUE,L$67<>""),L73+L85,"") -> -2699.22 | M86: =IF(AND(TRUE,M$67<>""),M73+M85,"") -> 2252.16 | N86: =IF(AND(TRUE,N$67<>""),N73+N85,"") -> 3067.02 | O86: =IF(AND(TRUE,O$67<>""),O73+O85,"") -> 3067.02 | P86: =IF(AND(TRUE,P$67<>""),P73+P85,"") -> 3067.02 | Q86: =IF(AND(TRUE,Q$67<>""),Q73+Q85,"") -> 3067.02 | R86: =IF(AND(TRUE,R$67<>""),R73+R85,"") -> 3067.02 | S86: =IF(AND(TRUE,S$67<>""),S73+S85,"") -> 3067.02 | ... AO86: =IF(AND(TRUE,AO$67<>""),AO73+AO85,"")
J88: Acquisto | K88: Valore immobile | L88: =IF(AND(TRUE,L$67<>""),SUMIFS(Flussi!$F:$F,Flussi!$B:$B,L$67,Flussi!$D:$D,$J88,Flussi!$E:$E,$K88,Flussi!$A:$A,$D$2),"") -> 35000 | M88: =IF(AND(TRUE,M$67<>""),SUMIFS(Flussi!$F:$F,Flussi!$B:$B,M$67,Flussi!$D:$D,$J88,Flussi!$E:$E,$K88,Flussi!$A:$A,$D$2),"") -> 0 | N88: =IF(AND(TRUE,N$67<>""),SUMIFS(Flussi!$F:$F,Flussi!$B:$B,N$67,Flussi!$D:$D,$J88,Flussi!$E:$E,$K88,Flussi!$A:$A,$D$2),"") -> 0 | O88: =IF(AND(TRUE,O$67<>""),SUMIFS(Flussi!$F:$F,Flussi!$B:$B,O$67,Flussi!$D:$D,$J88,Flussi!$E:$E,$K88,Flussi!$A:$A,$D$2),"") -> 0 | P88: =IF(AND(TRUE,P$67<>""),SUMIFS(Flussi!$F:$F,Flussi!$B:$B,P$67,Flussi!$D:$D,$J88,Flussi!$E:$E,$K88,Flussi!$A:$A,$D$2),"") -> 0 | Q88: =IF(AND(TRUE,Q$67<>""),SUMIFS(Flussi!$F:$F,Flussi!$B:$B,Q$67,Flussi!$D:$D,$J88,Flussi!$E:$E,$K88,Flussi!$A:$A,$D$2),"") -> 0 | R88: =IF(AND(TRUE,R$67<>""),SUMIFS(Flussi!$F:$F,Flussi!$B:$B,R$67,Flussi!$D:$D,$J88,Flussi!$E:$E,$K88,Flussi!$A:$A,$D$2),"") -> 0 | S88: =IF(AND(TRUE,S$67<>""),SUMIFS(Flussi!$F:$F,Flussi!$B:$B,S$67,Flussi!$D:$D,$J88,Flussi!$E:$E,$K88,Flussi!$A:$A,$D$2),"") -> 0 | ... AO88: =IF(AND(TRUE,AO$67<>""),SUMIFS(Flussi!$F:$F,Flussi!$B:$B,AO$67,Flussi!$D:$D,$J88,Flussi!$E:$E,$K88,Flussi!$A:$A,$D$2),"")
J89: Mutuo0 | K89: Importo | L89: =IF(AND(TRUE,L$67<>""),SUMIFS(Flussi!$F:$F,Flussi!$B:$B,L$67,Flussi!$D:$D,$J89,Flussi!$E:$E,$K89,Flussi!$A:$A,$D$2),"") -> 0 | M89: =IF(AND(TRUE,M$67<>""),SUMIFS(Flussi!$F:$F,Flussi!$B:$B,M$67,Flussi!$D:$D,$J89,Flussi!$E:$E,$K89,Flussi!$A:$A,$D$2),"") -> 0 | N89: =IF(AND(TRUE,N$67<>""),SUMIFS(Flussi!$F:$F,Flussi!$B:$B,N$67,Flussi!$D:$D,$J89,Flussi!$E:$E,$K89,Flussi!$A:$A,$D$2),"") -> 0 | O89: =IF(AND(TRUE,O$67<>""),SUMIFS(Flussi!$F:$F,Flussi!$B:$B,O$67,Flussi!$D:$D,$J89,Flussi!$E:$E,$K89,Flussi!$A:$A,$D$2),"") -> 0 | P89: =IF(AND(TRUE,P$67<>""),SUMIFS(Flussi!$F:$F,Flussi!$B:$B,P$67,Flussi!$D:$D,$J89,Flussi!$E:$E,$K89,Flussi!$A:$A,$D$2),"") -> 0 | Q89: =IF(AND(TRUE,Q$67<>""),SUMIFS(Flussi!$F:$F,Flussi!$B:$B,Q$67,Flussi!$D:$D,$J89,Flussi!$E:$E,$K89,Flussi!$A:$A,$D$2),"") -> 0 | R89: =IF(AND(TRUE,R$67<>""),SUMIFS(Flussi!$F:$F,Flussi!$B:$B,R$67,Flussi!$D:$D,$J89,Flussi!$E:$E,$K89,Flussi!$A:$A,$D$2),"") -> 0 | S89: =IF(AND(TRUE,S$67<>""),SUMIFS(Flussi!$F:$F,Flussi!$B:$B,S$67,Flussi!$D:$D,$J89,Flussi!$E:$E,$K89,Flussi!$A:$A,$D$2),"") -> 0 | ... AO89: =IF(AND(TRUE,AO$67<>""),SUMIFS(Flussi!$F:$F,Flussi!$B:$B,AO$67,Flussi!$D:$D,$J89,Flussi!$E:$E,$K89,Flussi!$A:$A,$D$2),"")
J90: Mutuo0 | K90: Quota capitale | L90: =IF(AND(TRUE,L$67<>""),-SUMIFS(StrambioMutuo0!$H:$H,StrambioMutuo0!$A:$A,L$67),"") -> 0 | M90: =IF(AND(TRUE,M$67<>""),-SUMIFS(StrambioMutuo0!$H:$H,StrambioMutuo0!$A:$A,M$67),"") -> 0 | N90: =IF(AND(TRUE,N$67<>""),-SUMIFS(StrambioMutuo0!$H:$H,StrambioMutuo0!$A:$A,N$67),"") -> 0 | O90: =IF(AND(TRUE,O$67<>""),-SUMIFS(StrambioMutuo0!$H:$H,StrambioMutuo0!$A:$A,O$67),"") -> 0 | P90: =IF(AND(TRUE,P$67<>""),-SUMIFS(StrambioMutuo0!$H:$H,StrambioMutuo0!$A:$A,P$67),"") -> 0 | Q90: =IF(AND(TRUE,Q$67<>""),-SUMIFS(StrambioMutuo0!$H:$H,StrambioMutuo0!$A:$A,Q$67),"") -> 0 | R90: =IF(AND(TRUE,R$67<>""),-SUMIFS(StrambioMutuo0!$H:$H,StrambioMutuo0!$A:$A,R$67),"") -> 0 | S90: =IF(AND(TRUE,S$67<>""),-SUMIFS(StrambioMutuo0!$H:$H,StrambioMutuo0!$A:$A,S$67),"") -> 0 | ... AO90: =IF(AND(TRUE,AO$67<>""),-SUMIFS(StrambioMutuo0!$H:$H,StrambioMutuo0!$A:$A,AO$67),"")
J91: Mutuo0 | K91: Rimborso anticipato | L91: =IF(AND(TRUE,L$67<>""),-SUMIFS(StrambioMutuo0!$I:$I,StrambioMutuo0!$A:$A,L$67),"") -> 0 | M91: =IF(AND(TRUE,M$67<>""),-SUMIFS(StrambioMutuo0!$I:$I,StrambioMutuo0!$A:$A,M$67),"") -> 0 | N91: =IF(AND(TRUE,N$67<>""),-SUMIFS(StrambioMutuo0!$I:$I,StrambioMutuo0!$A:$A,N$67),"") -> 0 | O91: =IF(AND(TRUE,O$67<>""),-SUMIFS(StrambioMutuo0!$I:$I,StrambioMutuo0!$A:$A,O$67),"") -> 0 | P91: =IF(AND(TRUE,P$67<>""),-SUMIFS(StrambioMutuo0!$I:$I,StrambioMutuo0!$A:$A,P$67),"") -> 0 | Q91: =IF(AND(TRUE,Q$67<>""),-SUMIFS(StrambioMutuo0!$I:$I,StrambioMutuo0!$A:$A,Q$67),"") -> 0 | R91: =IF(AND(TRUE,R$67<>""),-SUMIFS(StrambioMutuo0!$I:$I,StrambioMutuo0!$A:$A,R$67),"") -> 0 | S91: =IF(AND(TRUE,S$67<>""),-SUMIFS(StrambioMutuo0!$I:$I,StrambioMutuo0!$A:$A,S$67),"") -> 0 | ... AO91: =IF(AND(TRUE,AO$67<>""),-SUMIFS(StrambioMutuo0!$I:$I,StrambioMutuo0!$A:$A,AO$67),"")
J92: Mutuo1 | K92: Importo | L92: =IF(AND(TRUE,L$67<>""),SUMIFS(Flussi!$F:$F,Flussi!$B:$B,L$67,Flussi!$D:$D,$J92,Flussi!$E:$E,$K92),"") -> 0 | M92: =IF(AND(TRUE,M$67<>""),SUMIFS(Flussi!$F:$F,Flussi!$B:$B,M$67,Flussi!$D:$D,$J92,Flussi!$E:$E,$K92),"") -> 0 | N92: =IF(AND(TRUE,N$67<>""),SUMIFS(Flussi!$F:$F,Flussi!$B:$B,N$67,Flussi!$D:$D,$J92,Flussi!$E:$E,$K92),"") -> 0 | O92: =IF(AND(TRUE,O$67<>""),SUMIFS(Flussi!$F:$F,Flussi!$B:$B,O$67,Flussi!$D:$D,$J92,Flussi!$E:$E,$K92),"") -> 0 | P92: =IF(AND(TRUE,P$67<>""),SUMIFS(Flussi!$F:$F,Flussi!$B:$B,P$67,Flussi!$D:$D,$J92,Flussi!$E:$E,$K92),"") -> 0 | Q92: =IF(AND(TRUE,Q$67<>""),SUMIFS(Flussi!$F:$F,Flussi!$B:$B,Q$67,Flussi!$D:$D,$J92,Flussi!$E:$E,$K92),"") -> 0 | R92: =IF(AND(TRUE,R$67<>""),SUMIFS(Flussi!$F:$F,Flussi!$B:$B,R$67,Flussi!$D:$D,$J92,Flussi!$E:$E,$K92),"") -> 0 | S92: =IF(AND(TRUE,S$67<>""),SUMIFS(Flussi!$F:$F,Flussi!$B:$B,S$67,Flussi!$D:$D,$J92,Flussi!$E:$E,$K92),"") -> 0 | ... AO92: =IF(AND(TRUE,AO$67<>""),SUMIFS(Flussi!$F:$F,Flussi!$B:$B,AO$67,Flussi!$D:$D,$J92,Flussi!$E:$E,$K92),"")
J93: Mutuo1 | K93: Quota capitale | L93: =IF(AND(TRUE,L$67<>""),-SUMIFS(StrambioMutuo1!$H:$H,StrambioMutuo1!$A:$A,L$67),"") -> -8161.3785 | M93: =IF(AND(TRUE,M$67<>""),-SUMIFS(StrambioMutuo1!$H:$H,StrambioMutuo1!$A:$A,M$67),"") -> -8386.1565 | N93: =IF(AND(TRUE,N$67<>""),-SUMIFS(StrambioMutuo1!$H:$H,StrambioMutuo1!$A:$A,N$67),"") -> -8617.1252 | O93: =IF(AND(TRUE,O$67<>""),-SUMIFS(StrambioMutuo1!$H:$H,StrambioMutuo1!$A:$A,O$67),"") -> -8854.4552 | P93: =IF(AND(TRUE,P$67<>""),-SUMIFS(StrambioMutuo1!$H:$H,StrambioMutuo1!$A:$A,P$67),"") -> -9098.3217 | Q93: =IF(AND(TRUE,Q$67<>""),-SUMIFS(StrambioMutuo1!$H:$H,StrambioMutuo1!$A:$A,Q$67),"") -> -9348.9046 | R93: =IF(AND(TRUE,R$67<>""),-SUMIFS(StrambioMutuo1!$H:$H,StrambioMutuo1!$A:$A,R$67),"") -> -9606.3891 | S93: =IF(AND(TRUE,S$67<>""),-SUMIFS(StrambioMutuo1!$H:$H,StrambioMutuo1!$A:$A,S$67),"") -> -9870.965 | ... AO93: =IF(AND(TRUE,AO$67<>""),-SUMIFS(StrambioMutuo1!$H:$H,StrambioMutuo1!$A:$A,AO$67),"")
J94: Mutuo1 | K94: Rimborso anticipato | L94: =IF(AND(TRUE,L$67<>""),-SUMIFS(StrambioMutuo1!$I:$I,StrambioMutuo1!$A:$A,L$67),"") -> 0 | M94: =IF(AND(TRUE,M$67<>""),-SUMIFS(StrambioMutuo1!$I:$I,StrambioMutuo1!$A:$A,M$67),"") -> 0 | N94: =IF(AND(TRUE,N$67<>""),-SUMIFS(StrambioMutuo1!$I:$I,StrambioMutuo1!$A:$A,N$67),"") -> 0 | O94: =IF(AND(TRUE,O$67<>""),-SUMIFS(StrambioMutuo1!$I:$I,StrambioMutuo1!$A:$A,O$67),"") -> 0 | P94: =IF(AND(TRUE,P$67<>""),-SUMIFS(StrambioMutuo1!$I:$I,StrambioMutuo1!$A:$A,P$67),"") -> 0 | Q94: =IF(AND(TRUE,Q$67<>""),-SUMIFS(StrambioMutuo1!$I:$I,StrambioMutuo1!$A:$A,Q$67),"") -> 0 | R94: =IF(AND(TRUE,R$67<>""),-SUMIFS(StrambioMutuo1!$I:$I,StrambioMutuo1!$A:$A,R$67),"") -> 0 | S94: =IF(AND(TRUE,S$67<>""),-SUMIFS(StrambioMutuo1!$I:$I,StrambioMutuo1!$A:$A,S$67),"") -> 0 | ... AO94: =IF(AND(TRUE,AO$67<>""),-SUMIFS(StrambioMutuo1!$I:$I,StrambioMutuo1!$A:$A,AO$67),"")
I95: Equity | J95: Equity | K95: P&L | L95: =IF(AND(TRUE,L$67<>""),SUM(L88:L94),"") -> 26838.622 | M95: =IF(AND(TRUE,M$67<>""),SUM(M88:M94),"") -> -8386.1565 | N95: =IF(AND(TRUE,N$67<>""),SUM(N88:N94),"") -> -8617.1252 | O95: =IF(AND(TRUE,O$67<>""),SUM(O88:O94),"") -> -8854.4552 | P95: =IF(AND(TRUE,P$67<>""),SUM(P88:P94),"") -> -9098.3217 | Q95: =IF(AND(TRUE,Q$67<>""),SUM(Q88:Q94),"") -> -9348.9046 | R95: =IF(AND(TRUE,R$67<>""),SUM(R88:R94),"") -> -9606.3891 | S95: =IF(AND(TRUE,S$67<>""),SUM(S88:S94),"") -> -9870.965 | ... AO95: =IF(AND(TRUE,AO$67<>""),SUM(AO88:AO94),"")
H96: =YEAR($E$4) -> 2026 | L96: =IF(AND($H96<>"",L$67<>""),IF(AND(L$67>=$H96,L$67<$H96+$D$28),SUMIFS($L$95:$AO$95,$L$67:$AO$67,$H96)/$D$28,0),"") -> #REF! | M96: =IF(AND($H96<>"",M$67<>""),IF(AND(M$67>=$H96,M$67<$H96+$D$28),SUMIFS($L$95:$AO$95,$L$67:$AO$67,$H96)/$D$28,0),"") -> #REF! | N96: =IF(AND($H96<>"",N$67<>""),IF(AND(N$67>=$H96,N$67<$H96+$D$28),SUMIFS($L$95:$AO$95,$L$67:$AO$67,$H96)/$D$28,0),"") -> #REF! | O96: =IF(AND($H96<>"",O$67<>""),IF(AND(O$67>=$H96,O$67<$H96+$D$28),SUMIFS($L$95:$AO$95,$L$67:$AO$67,$H96)/$D$28,0),"") -> #REF! | P96: =IF(AND($H96<>"",P$67<>""),IF(AND(P$67>=$H96,P$67<$H96+$D$28),SUMIFS($L$95:$AO$95,$L$67:$AO$67,$H96)/$D$28,0),"") -> #REF! | Q96: =IF(AND($H96<>"",Q$67<>""),IF(AND(Q$67>=$H96,Q$67<$H96+$D$28),SUMIFS($L$95:$AO$95,$L$67:$AO$67,$H96)/$D$28,0),"") -> #REF! | R96: =IF(AND($H96<>"",R$67<>""),IF(AND(R$67>=$H96,R$67<$H96+$D$28),SUMIFS($L$95:$AO$95,$L$67:$AO$67,$H96)/$D$28,0),"") -> #REF! | S96: =IF(AND($H96<>"",S$67<>""),IF(AND(S$67>=$H96,S$67<$H96+$D$28),SUMIFS($L$95:$AO$95,$L$67:$AO$67,$H96)/$D$28,0),"") -> #REF! | ... AO96: =IF(AND($H96<>"",AO$67<>""),IF(AND(AO$67>=$H96,AO$67<$H96+$D$28),SUMIFS($L$95:$AO$95,$L$67:$AO$67,$H96)/$D$28,0),"")
H97: =IF(H96<>"",IF(H96+1<YEAR($E$4)+$E$5,H96+1,""),"") -> 2027 | L97: =IF(AND($H97<>"",L$67<>""),IF(AND(L$67>=$H97,L$67<$H97+$D$28),SUMIFS($L$95:$AO$95,$L$67:$AO$67,$H97)/$D$28,0),"") -> #REF! | M97: =IF(AND($H97<>"",M$67<>""),IF(AND(M$67>=$H97,M$67<$H97+$D$28),SUMIFS($L$95:$AO$95,$L$67:$AO$67,$H97)/$D$28,0),"") -> #REF! | N97: =IF(AND($H97<>"",N$67<>""),IF(AND(N$67>=$H97,N$67<$H97+$D$28),SUMIFS($L$95:$AO$95,$L$67:$AO$67,$H97)/$D$28,0),"") -> #REF! | O97: =IF(AND($H97<>"",O$67<>""),IF(AND(O$67>=$H97,O$67<$H97+$D$28),SUMIFS($L$95:$AO$95,$L$67:$AO$67,$H97)/$D$28,0),"") -> #REF! | P97: =IF(AND($H97<>"",P$67<>""),IF(AND(P$67>=$H97,P$67<$H97+$D$28),SUMIFS($L$95:$AO$95,$L$67:$AO$67,$H97)/$D$28,0),"") -> #REF! | Q97: =IF(AND($H97<>"",Q$67<>""),IF(AND(Q$67>=$H97,Q$67<$H97+$D$28),SUMIFS($L$95:$AO$95,$L$67:$AO$67,$H97)/$D$28,0),"") -> #REF! | R97: =IF(AND($H97<>"",R$67<>""),IF(AND(R$67>=$H97,R$67<$H97+$D$28),SUMIFS($L$95:$AO$95,$L$67:$AO$67,$H97)/$D$28,0),"") -> #REF! | S97: =IF(AND($H97<>"",S$67<>""),IF(AND(S$67>=$H97,S$67<$H97+$D$28),SUMIFS($L$95:$AO$95,$L$67:$AO$67,$H97)/$D$28,0),"") -> #REF! | ... AO97: =IF(AND($H97<>"",AO$67<>""),IF(AND(AO$67>=$H97,AO$67<$H97+$D$28),SUMIFS($L$95:$AO$95,$L$67:$AO$67,$H97)/$D$28,0),"")
H98: =IF(H97<>"",IF(H97+1<YEAR($E$4)+$E$5,H97+1,""),"") -> 2028 | L98: =IF(AND($H98<>"",L$67<>""),IF(AND(L$67>=$H98,L$67<$H98+$D$28),SUMIFS($L$95:$AO$95,$L$67:$AO$67,$H98)/$D$28,0),"") -> #REF! | M98: =IF(AND($H98<>"",M$67<>""),IF(AND(M$67>=$H98,M$67<$H98+$D$28),SUMIFS($L$95:$AO$95,$L$67:$AO$67,$H98)/$D$28,0),"") -> #REF! | N98: =IF(AND($H98<>"",N$67<>""),IF(AND(N$67>=$H98,N$67<$H98+$D$28),SUMIFS($L$95:$AO$95,$L$67:$AO$67,$H98)/$D$28,0),"") -> #REF! | O98: =IF(AND($H98<>"",O$67<>""),IF(AND(O$67>=$H98,O$67<$H98+$D$28),SUMIFS($L$95:$AO$95,$L$67:$AO$67,$H98)/$D$28,0),"") -> #REF! | P98: =IF(AND($H98<>"",P$67<>""),IF(AND(P$67>=$H98,P$67<$H98+$D$28),SUMIFS($L$95:$AO$95,$L$67:$AO$67,$H98)/$D$28,0),"") -> #REF! | Q98: =IF(AND($H98<>"",Q$67<>""),IF(AND(Q$67>=$H98,Q$67<$H98+$D$28),SUMIFS($L$95:$AO$95,$L$67:$AO$67,$H98)/$D$28,0),"") -> #REF! | R98: =IF(AND($H98<>"",R$67<>""),IF(AND(R$67>=$H98,R$67<$H98+$D$28),SUMIFS($L$95:$AO$95,$L$67:$AO$67,$H98)/$D$28,0),"") -> #REF! | S98: =IF(AND($H98<>"",S$67<>""),IF(AND(S$67>=$H98,S$67<$H98+$D$28),SUMIFS($L$95:$AO$95,$L$67:$AO$67,$H98)/$D$28,0),"") -> #REF! | ... AO98: =IF(AND($H98<>"",AO$67<>""),IF(AND(AO$67>=$H98,AO$67<$H98+$D$28),SUMIFS($L$95:$AO$95,$L$67:$AO$67,$H98)/$D$28,0),"")
H99: =IF(H98<>"",IF(H98+1<YEAR($E$4)+$E$5,H98+1,""),"") -> 2029 | L99: =IF(AND($H99<>"",L$67<>""),IF(AND(L$67>=$H99,L$67<$H99+$D$28),SUMIFS($L$95:$AO$95,$L$67:$AO$67,$H99)/$D$28,0),"") -> #REF! | M99: =IF(AND($H99<>"",M$67<>""),IF(AND(M$67>=$H99,M$67<$H99+$D$28),SUMIFS($L$95:$AO$95,$L$67:$AO$67,$H99)/$D$28,0),"") -> #REF! | N99: =IF(AND($H99<>"",N$67<>""),IF(AND(N$67>=$H99,N$67<$H99+$D$28),SUMIFS($L$95:$AO$95,$L$67:$AO$67,$H99)/$D$28,0),"") -> #REF! | O99: =IF(AND($H99<>"",O$67<>""),IF(AND(O$67>=$H99,O$67<$H99+$D$28),SUMIFS($L$95:$AO$95,$L$67:$AO$67,$H99)/$D$28,0),"") -> #REF! | P99: =IF(AND($H99<>"",P$67<>""),IF(AND(P$67>=$H99,P$67<$H99+$D$28),SUMIFS($L$95:$AO$95,$L$67:$AO$67,$H99)/$D$28,0),"") -> #REF! | Q99: =IF(AND($H99<>"",Q$67<>""),IF(AND(Q$67>=$H99,Q$67<$H99+$D$28),SUMIFS($L$95:$AO$95,$L$67:$AO$67,$H99)/$D$28,0),"") -> #REF! | R99: =IF(AND($H99<>"",R$67<>""),IF(AND(R$67>=$H99,R$67<$H99+$D$28),SUMIFS($L$95:$AO$95,$L$67:$AO$67,$H99)/$D$28,0),"") -> #REF! | S99: =IF(AND($H99<>"",S$67<>""),IF(AND(S$67>=$H99,S$67<$H99+$D$28),SUMIFS($L$95:$AO$95,$L$67:$AO$67,$H99)/$D$28,0),"") -> #REF! | ... AO99: =IF(AND($H99<>"",AO$67<>""),IF(AND(AO$67>=$H99,AO$67<$H99+$D$28),SUMIFS($L$95:$AO$95,$L$67:$AO$67,$H99)/$D$28,0),"")
H100: =IF(H99<>"",IF(H99+1<YEAR($E$4)+$E$5,H99+1,""),"") -> 2030 | L100: =IF(AND($H100<>"",L$67<>""),IF(AND(L$67>=$H100,L$67<$H100+$D$28),SUMIFS($L$95:$AO$95,$L$67:$AO$67,$H100)/$D$28,0),"") -> #REF! | M100: =IF(AND($H100<>"",M$67<>""),IF(AND(M$67>=$H100,M$67<$H100+$D$28),SUMIFS($L$95:$AO$95,$L$67:$AO$67,$H100)/$D$28,0),"") -> #REF! | N100: =IF(AND($H100<>"",N$67<>""),IF(AND(N$67>=$H100,N$67<$H100+$D$28),SUMIFS($L$95:$AO$95,$L$67:$AO$67,$H100)/$D$28,0),"") -> #REF! | O100: =IF(AND($H100<>"",O$67<>""),IF(AND(O$67>=$H100,O$67<$H100+$D$28),SUMIFS($L$95:$AO$95,$L$67:$AO$67,$H100)/$D$28,0),"") -> #REF! | P100: =IF(AND($H100<>"",P$67<>""),IF(AND(P$67>=$H100,P$67<$H100+$D$28),SUMIFS($L$95:$AO$95,$L$67:$AO$67,$H100)/$D$28,0),"") -> #REF! | Q100: =IF(AND($H100<>"",Q$67<>""),IF(AND(Q$67>=$H100,Q$67<$H100+$D$28),SUMIFS($L$95:$AO$95,$L$67:$AO$67,$H100)/$D$28,0),"") -> #REF! | R100: =IF(AND($H100<>"",R$67<>""),IF(AND(R$67>=$H100,R$67<$H100+$D$28),SUMIFS($L$95:$AO$95,$L$67:$AO$67,$H100)/$D$28,0),"") -> #REF! | S100: =IF(AND($H100<>"",S$67<>""),IF(AND(S$67>=$H100,S$67<$H100+$D$28),SUMIFS($L$95:$AO$95,$L$67:$AO$67,$H100)/$D$28,0),"") -> #REF! | ... AO100: =IF(AND($H100<>"",AO$67<>""),IF(AND(AO$67>=$H100,AO$67<$H100+$D$28),SUMIFS($L$95:$AO$95,$L$67:$AO$67,$H100)/$D$28,0),"")
H101: =IF(H100<>"",IF(H100+1<YEAR($E$4)+$E$5,H100+1,""),"") -> 2031 | L101: =IF(AND($H101<>"",L$67<>""),IF(AND(L$67>=$H101,L$67<$H101+$D$28),SUMIFS($L$95:$AO$95,$L$67:$AO$67,$H101)/$D$28,0),"") -> #REF! | M101: =IF(AND($H101<>"",M$67<>""),IF(AND(M$67>=$H101,M$67<$H101+$D$28),SUMIFS($L$95:$AO$95,$L$67:$AO$67,$H101)/$D$28,0),"") -> #REF! | N101: =IF(AND($H101<>"",N$67<>""),IF(AND(N$67>=$H101,N$67<$H101+$D$28),SUMIFS($L$95:$AO$95,$L$67:$AO$67,$H101)/$D$28,0),"") -> #REF! | O101: =IF(AND($H101<>"",O$67<>""),IF(AND(O$67>=$H101,O$67<$H101+$D$28),SUMIFS($L$95:$AO$95,$L$67:$AO$67,$H101)/$D$28,0),"") -> #REF! | P101: =IF(AND($H101<>"",P$67<>""),IF(AND(P$67>=$H101,P$67<$H101+$D$28),SUMIFS($L$95:$AO$95,$L$67:$AO$67,$H101)/$D$28,0),"") -> #REF! | Q101: =IF(AND($H101<>"",Q$67<>""),IF(AND(Q$67>=$H101,Q$67<$H101+$D$28),SUMIFS($L$95:$AO$95,$L$67:$AO$67,$H101)/$D$28,0),"") -> #REF! | R101: =IF(AND($H101<>"",R$67<>""),IF(AND(R$67>=$H101,R$67<$H101+$D$28),SUMIFS($L$95:$AO$95,$L$67:$AO$67,$H101)/$D$28,0),"") -> #REF! | S101: =IF(AND($H101<>"",S$67<>""),IF(AND(S$67>=$H101,S$67<$H101+$D$28),SUMIFS($L$95:$AO$95,$L$67:$AO$67,$H101)/$D$28,0),"") -> #REF! | ... AO101: =IF(AND($H101<>"",AO$67<>""),IF(AND(AO$67>=$H101,AO$67<$H101+$D$28),SUMIFS($L$95:$AO$95,$L$67:$AO$67,$H101)/$D$28,0),"")
H102: =IF(H101<>"",IF(H101+1<YEAR($E$4)+$E$5,H101+1,""),"") -> 2032 | L102: =IF(AND($H102<>"",L$67<>""),IF(AND(L$67>=$H102,L$67<$H102+$D$28),SUMIFS($L$95:$AO$95,$L$67:$AO$67,$H102)/$D$28,0),"") -> #REF! | M102: =IF(AND($H102<>"",M$67<>""),IF(AND(M$67>=$H102,M$67<$H102+$D$28),SUMIFS($L$95:$AO$95,$L$67:$AO$67,$H102)/$D$28,0),"") -> #REF! | N102: =IF(AND($H102<>"",N$67<>""),IF(AND(N$67>=$H102,N$67<$H102+$D$28),SUMIFS($L$95:$AO$95,$L$67:$AO$67,$H102)/$D$28,0),"") -> #REF! | O102: =IF(AND($H102<>"",O$67<>""),IF(AND(O$67>=$H102,O$67<$H102+$D$28),SUMIFS($L$95:$AO$95,$L$67:$AO$67,$H102)/$D$28,0),"") -> #REF! | P102: =IF(AND($H102<>"",P$67<>""),IF(AND(P$67>=$H102,P$67<$H102+$D$28),SUMIFS($L$95:$AO$95,$L$67:$AO$67,$H102)/$D$28,0),"") -> #REF! | Q102: =IF(AND($H102<>"",Q$67<>""),IF(AND(Q$67>=$H102,Q$67<$H102+$D$28),SUMIFS($L$95:$AO$95,$L$67:$AO$67,$H102)/$D$28,0),"") -> #REF! | R102: =IF(AND($H102<>"",R$67<>""),IF(AND(R$67>=$H102,R$67<$H102+$D$28),SUMIFS($L$95:$AO$95,$L$67:$AO$67,$H102)/$D$28,0),"") -> #REF! | S102: =IF(AND($H102<>"",S$67<>""),IF(AND(S$67>=$H102,S$67<$H102+$D$28),SUMIFS($L$95:$AO$95,$L$67:$AO$67,$H102)/$D$28,0),"") -> #REF! | ... AO102: =IF(AND($H102<>"",AO$67<>""),IF(AND(AO$67>=$H102,AO$67<$H102+$D$28),SUMIFS($L$95:$AO$95,$L$67:$AO$67,$H102)/$D$28,0),"")
H103: =IF(H102<>"",IF(H102+1<YEAR($E$4)+$E$5,H102+1,""),"") -> 2033 | L103: =IF(AND($H103<>"",L$67<>""),IF(AND(L$67>=$H103,L$67<$H103+$D$28),SUMIFS($L$95:$AO$95,$L$67:$AO$67,$H103)/$D$28,0),"") -> #REF! | M103: =IF(AND($H103<>"",M$67<>""),IF(AND(M$67>=$H103,M$67<$H103+$D$28),SUMIFS($L$95:$AO$95,$L$67:$AO$67,$H103)/$D$28,0),"") -> #REF! | N103: =IF(AND($H103<>"",N$67<>""),IF(AND(N$67>=$H103,N$67<$H103+$D$28),SUMIFS($L$95:$AO$95,$L$67:$AO$67,$H103)/$D$28,0),"") -> #REF! | O103: =IF(AND($H103<>"",O$67<>""),IF(AND(O$67>=$H103,O$67<$H103+$D$28),SUMIFS($L$95:$AO$95,$L$67:$AO$67,$H103)/$D$28,0),"") -> #REF! | P103: =IF(AND($H103<>"",P$67<>""),IF(AND(P$67>=$H103,P$67<$H103+$D$28),SUMIFS($L$95:$AO$95,$L$67:$AO$67,$H103)/$D$28,0),"") -> #REF! | Q103: =IF(AND($H103<>"",Q$67<>""),IF(AND(Q$67>=$H103,Q$67<$H103+$D$28),SUMIFS($L$95:$AO$95,$L$67:$AO$67,$H103)/$D$28,0),"") -> #REF! | R103: =IF(AND($H103<>"",R$67<>""),IF(AND(R$67>=$H103,R$67<$H103+$D$28),SUMIFS($L$95:$AO$95,$L$67:$AO$67,$H103)/$D$28,0),"") -> #REF! | S103: =IF(AND($H103<>"",S$67<>""),IF(AND(S$67>=$H103,S$67<$H103+$D$28),SUMIFS($L$95:$AO$95,$L$67:$AO$67,$H103)/$D$28,0),"") -> #REF! | ... AO103: =IF(AND($H103<>"",AO$67<>""),IF(AND(AO$67>=$H103,AO$67<$H103+$D$28),SUMIFS($L$95:$AO$95,$L$67:$AO$67,$H103)/$D$28,0),"")
H104: =IF(H103<>"",IF(H103+1<YEAR($E$4)+$E$5,H103+1,""),"") -> 2034 | L104: =IF(AND($H104<>"",L$67<>""),IF(AND(L$67>=$H104,L$67<$H104+$D$28),SUMIFS($L$95:$AO$95,$L$67:$AO$67,$H104)/$D$28,0),"") -> #REF! | M104: =IF(AND($H104<>"",M$67<>""),IF(AND(M$67>=$H104,M$67<$H104+$D$28),SUMIFS($L$95:$AO$95,$L$67:$AO$67,$H104)/$D$28,0),"") -> #REF! | N104: =IF(AND($H104<>"",N$67<>""),IF(AND(N$67>=$H104,N$67<$H104+$D$28),SUMIFS($L$95:$AO$95,$L$67:$AO$67,$H104)/$D$28,0),"") -> #REF! | O104: =IF(AND($H104<>"",O$67<>""),IF(AND(O$67>=$H104,O$67<$H104+$D$28),SUMIFS($L$95:$AO$95,$L$67:$AO$67,$H104)/$D$28,0),"") -> #REF! | P104: =IF(AND($H104<>"",P$67<>""),IF(AND(P$67>=$H104,P$67<$H104+$D$28),SUMIFS($L$95:$AO$95,$L$67:$AO$67,$H104)/$D$28,0),"") -> #REF! | Q104: =IF(AND($H104<>"",Q$67<>""),IF(AND(Q$67>=$H104,Q$67<$H104+$D$28),SUMIFS($L$95:$AO$95,$L$67:$AO$67,$H104)/$D$28,0),"") -> #REF! | R104: =IF(AND($H104<>"",R$67<>""),IF(AND(R$67>=$H104,R$67<$H104+$D$28),SUMIFS($L$95:$AO$95,$L$67:$AO$67,$H104)/$D$28,0),"") -> #REF! | S104: =IF(AND($H104<>"",S$67<>""),IF(AND(S$67>=$H104,S$67<$H104+$D$28),SUMIFS($L$95:$AO$95,$L$67:$AO$67,$H104)/$D$28,0),"") -> #REF! | ... AO104: =IF(AND($H104<>"",AO$67<>""),IF(AND(AO$67>=$H104,AO$67<$H104+$D$28),SUMIFS($L$95:$AO$95,$L$67:$AO$67,$H104)/$D$28,0),"")
H105: =IF(H104<>"",IF(H104+1<YEAR($E$4)+$E$5,H104+1,""),"") -> 2035 | L105: =IF(AND($H105<>"",L$67<>""),IF(AND(L$67>=$H105,L$67<$H105+$D$28),SUMIFS($L$95:$AO$95,$L$67:$AO$67,$H105)/$D$28,0),"") -> #REF! | M105: =IF(AND($H105<>"",M$67<>""),IF(AND(M$67>=$H105,M$67<$H105+$D$28),SUMIFS($L$95:$AO$95,$L$67:$AO$67,$H105)/$D$28,0),"") -> #REF! | N105: =IF(AND($H105<>"",N$67<>""),IF(AND(N$67>=$H105,N$67<$H105+$D$28),SUMIFS($L$95:$AO$95,$L$67:$AO$67,$H105)/$D$28,0),"") -> #REF! | O105: =IF(AND($H105<>"",O$67<>""),IF(AND(O$67>=$H105,O$67<$H105+$D$28),SUMIFS($L$95:$AO$95,$L$67:$AO$67,$H105)/$D$28,0),"") -> #REF! | P105: =IF(AND($H105<>"",P$67<>""),IF(AND(P$67>=$H105,P$67<$H105+$D$28),SUMIFS($L$95:$AO$95,$L$67:$AO$67,$H105)/$D$28,0),"") -> #REF! | Q105: =IF(AND($H105<>"",Q$67<>""),IF(AND(Q$67>=$H105,Q$67<$H105+$D$28),SUMIFS($L$95:$AO$95,$L$67:$AO$67,$H105)/$D$28,0),"") -> #REF! | R105: =IF(AND($H105<>"",R$67<>""),IF(AND(R$67>=$H105,R$67<$H105+$D$28),SUMIFS($L$95:$AO$95,$L$67:$AO$67,$H105)/$D$28,0),"") -> #REF! | S105: =IF(AND($H105<>"",S$67<>""),IF(AND(S$67>=$H105,S$67<$H105+$D$28),SUMIFS($L$95:$AO$95,$L$67:$AO$67,$H105)/$D$28,0),"") -> #REF! | ... AO105: =IF(AND($H105<>"",AO$67<>""),IF(AND(AO$67>=$H105,AO$67<$H105+$D$28),SUMIFS($L$95:$AO$95,$L$67:$AO$67,$H105)/$D$28,0),"")
H106: =IF(H105<>"",IF(H105+1<YEAR($E$4)+$E$5,H105+1,""),"") -> 2036 | L106: =IF(AND($H106<>"",L$67<>""),IF(AND(L$67>=$H106,L$67<$H106+$D$28),SUMIFS($L$95:$AO$95,$L$67:$AO$67,$H106)/$D$28,0),"") -> #REF! | M106: =IF(AND($H106<>"",M$67<>""),IF(AND(M$67>=$H106,M$67<$H106+$D$28),SUMIFS($L$95:$AO$95,$L$67:$AO$67,$H106)/$D$28,0),"") -> #REF! | N106: =IF(AND($H106<>"",N$67<>""),IF(AND(N$67>=$H106,N$67<$H106+$D$28),SUMIFS($L$95:$AO$95,$L$67:$AO$67,$H106)/$D$28,0),"") -> #REF! | O106: =IF(AND($H106<>"",O$67<>""),IF(AND(O$67>=$H106,O$67<$H106+$D$28),SUMIFS($L$95:$AO$95,$L$67:$AO$67,$H106)/$D$28,0),"") -> #REF! | P106: =IF(AND($H106<>"",P$67<>""),IF(AND(P$67>=$H106,P$67<$H106+$D$28),SUMIFS($L$95:$AO$95,$L$67:$AO$67,$H106)/$D$28,0),"") -> #REF! | Q106: =IF(AND($H106<>"",Q$67<>""),IF(AND(Q$67>=$H106,Q$67<$H106+$D$28),SUMIFS($L$95:$AO$95,$L$67:$AO$67,$H106)/$D$28,0),"") -> #REF! | R106: =IF(AND($H106<>"",R$67<>""),IF(AND(R$67>=$H106,R$67<$H106+$D$28),SUMIFS($L$95:$AO$95,$L$67:$AO$67,$H106)/$D$28,0),"") -> #REF! | S106: =IF(AND($H106<>"",S$67<>""),IF(AND(S$67>=$H106,S$67<$H106+$D$28),SUMIFS($L$95:$AO$95,$L$67:$AO$67,$H106)/$D$28,0),"") -> #REF! | ... AO106: =IF(AND($H106<>"",AO$67<>""),IF(AND(AO$67>=$H106,AO$67<$H106+$D$28),SUMIFS($L$95:$AO$95,$L$67:$AO$67,$H106)/$D$28,0),"")
H107: =IF(H106<>"",IF(H106+1<YEAR($E$4)+$E$5,H106+1,""),"") -> 2037 | L107: =IF(AND($H107<>"",L$67<>""),IF(AND(L$67>=$H107,L$67<$H107+$D$28),SUMIFS($L$95:$AO$95,$L$67:$AO$67,$H107)/$D$28,0),"") -> #REF! | M107: =IF(AND($H107<>"",M$67<>""),IF(AND(M$67>=$H107,M$67<$H107+$D$28),SUMIFS($L$95:$AO$95,$L$67:$AO$67,$H107)/$D$28,0),"") -> #REF! | N107: =IF(AND($H107<>"",N$67<>""),IF(AND(N$67>=$H107,N$67<$H107+$D$28),SUMIFS($L$95:$AO$95,$L$67:$AO$67,$H107)/$D$28,0),"") -> #REF! | O107: =IF(AND($H107<>"",O$67<>""),IF(AND(O$67>=$H107,O$67<$H107+$D$28),SUMIFS($L$95:$AO$95,$L$67:$AO$67,$H107)/$D$28,0),"") -> #REF! | P107: =IF(AND($H107<>"",P$67<>""),IF(AND(P$67>=$H107,P$67<$H107+$D$28),SUMIFS($L$95:$AO$95,$L$67:$AO$67,$H107)/$D$28,0),"") -> #REF! | Q107: =IF(AND($H107<>"",Q$67<>""),IF(AND(Q$67>=$H107,Q$67<$H107+$D$28),SUMIFS($L$95:$AO$95,$L$67:$AO$67,$H107)/$D$28,0),"") -> #REF! | R107: =IF(AND($H107<>"",R$67<>""),IF(AND(R$67>=$H107,R$67<$H107+$D$28),SUMIFS($L$95:$AO$95,$L$67:$AO$67,$H107)/$D$28,0),"") -> #REF! | S107: =IF(AND($H107<>"",S$67<>""),IF(AND(S$67>=$H107,S$67<$H107+$D$28),SUMIFS($L$95:$AO$95,$L$67:$AO$67,$H107)/$D$28,0),"") -> #REF! | ... AO107: =IF(AND($H107<>"",AO$67<>""),IF(AND(AO$67>=$H107,AO$67<$H107+$D$28),SUMIFS($L$95:$AO$95,$L$67:$AO$67,$H107)/$D$28,0),"")
H108: =IF(H107<>"",IF(H107+1<YEAR($E$4)+$E$5,H107+1,""),"") -> 2038 | L108: =IF(AND($H108<>"",L$67<>""),IF(AND(L$67>=$H108,L$67<$H108+$D$28),SUMIFS($L$95:$AO$95,$L$67:$AO$67,$H108)/$D$28,0),"") -> #REF! | M108: =IF(AND($H108<>"",M$67<>""),IF(AND(M$67>=$H108,M$67<$H108+$D$28),SUMIFS($L$95:$AO$95,$L$67:$AO$67,$H108)/$D$28,0),"") -> #REF! | N108: =IF(AND($H108<>"",N$67<>""),IF(AND(N$67>=$H108,N$67<$H108+$D$28),SUMIFS($L$95:$AO$95,$L$67:$AO$67,$H108)/$D$28,0),"") -> #REF! | O108: =IF(AND($H108<>"",O$67<>""),IF(AND(O$67>=$H108,O$67<$H108+$D$28),SUMIFS($L$95:$AO$95,$L$67:$AO$67,$H108)/$D$28,0),"") -> #REF! | P108: =IF(AND($H108<>"",P$67<>""),IF(AND(P$67>=$H108,P$67<$H108+$D$28),SUMIFS($L$95:$AO$95,$L$67:$AO$67,$H108)/$D$28,0),"") -> #REF! | Q108: =IF(AND($H108<>"",Q$67<>""),IF(AND(Q$67>=$H108,Q$67<$H108+$D$28),SUMIFS($L$95:$AO$95,$L$67:$AO$67,$H108)/$D$28,0),"") -> #REF! | R108: =IF(AND($H108<>"",R$67<>""),IF(AND(R$67>=$H108,R$67<$H108+$D$28),SUMIFS($L$95:$AO$95,$L$67:$AO$67,$H108)/$D$28,0),"") -> #REF! | S108: =IF(AND($H108<>"",S$67<>""),IF(AND(S$67>=$H108,S$67<$H108+$D$28),SUMIFS($L$95:$AO$95,$L$67:$AO$67,$H108)/$D$28,0),"") -> #REF! | ... AO108: =IF(AND($H108<>"",AO$67<>""),IF(AND(AO$67>=$H108,AO$67<$H108+$D$28),SUMIFS($L$95:$AO$95,$L$67:$AO$67,$H108)/$D$28,0),"")
... H125: =IF(H124<>"",IF(H124+1<YEAR($E$4)+$E$5,H124+1,""),"") | L125: =IF(AND($H125<>"",L$67<>""),IF(AND(L$67>=$H125,L$67<$H125+$D$28),SUMIFS($L$95:$AO$95,$L$67:$AO$67,$H125)/$D$28,0),"") | M125: =IF(AND($H125<>"",M$67<>""),IF(AND(M$67>=$H125,M$67<$H125+$D$28),SUMIFS($L$95:$AO$95,$L$67:$AO$67,$H125)/$D$28,0),"") | N125: =IF(AND($H125<>"",N$67<>""),IF(AND(N$67>=$H125,N$67<$H125+$D$28),SUMIFS($L$95:$AO$95,$L$67:$AO$67,$H125)/$D$28,0),"") | O125: =IF(AND($H125<>"",O$67<>""),IF(AND(O$67>=$H125,O$67<$H125+$D$28),SUMIFS($L$95:$AO$95,$L$67:$AO$67,$H125)/$D$28,0),"") | P125: =IF(AND($H125<>"",P$67<>""),IF(AND(P$67>=$H125,P$67<$H125+$D$28),SUMIFS($L$95:$AO$95,$L$67:$AO$67,$H125)/$D$28,0),"") | Q125: =IF(AND($H125<>"",Q$67<>""),IF(AND(Q$67>=$H125,Q$67<$H125+$D$28),SUMIFS($L$95:$AO$95,$L$67:$AO$67,$H125)/$D$28,0),"") | R125: =IF(AND($H125<>"",R$67<>""),IF(AND(R$67>=$H125,R$67<$H125+$D$28),SUMIFS($L$95:$AO$95,$L$67:$AO$67,$H125)/$D$28,0),"") | S125: =IF(AND($H125<>"",S$67<>""),IF(AND(S$67>=$H125,S$67<$H125+$D$28),SUMIFS($L$95:$AO$95,$L$67:$AO$67,$H125)/$D$28,0),"") | ... AO125: =IF(AND($H125<>"",AO$67<>""),IF(AND(AO$67>=$H125,AO$67<$H125+$D$28),SUMIFS($L$95:$AO$95,$L$67:$AO$67,$H125)/$D$28,0),"")
J126: Ristrutturazione | K126: - | L126: =IF(AND(TRUE,L$67<>""),SUMIFS(Flussi!$F:$F,Flussi!$B:$B,L$67,Flussi!$D:$D,$J126,Flussi!$E:$E,$K126,Flussi!$A:$A,$D$2),"") -> -5000 | M126: =IF(AND(TRUE,M$67<>""),SUMIFS(Flussi!$F:$F,Flussi!$B:$B,M$67,Flussi!$D:$D,$J126,Flussi!$E:$E,$K126,Flussi!$A:$A,$D$2),"") -> 0 | N126: =IF(AND(TRUE,N$67<>""),SUMIFS(Flussi!$F:$F,Flussi!$B:$B,N$67,Flussi!$D:$D,$J126,Flussi!$E:$E,$K126,Flussi!$A:$A,$D$2),"") -> 0 | O126: =IF(AND(TRUE,O$67<>""),SUMIFS(Flussi!$F:$F,Flussi!$B:$B,O$67,Flussi!$D:$D,$J126,Flussi!$E:$E,$K126,Flussi!$A:$A,$D$2),"") -> 0 | P126: =IF(AND(TRUE,P$67<>""),SUMIFS(Flussi!$F:$F,Flussi!$B:$B,P$67,Flussi!$D:$D,$J126,Flussi!$E:$E,$K126,Flussi!$A:$A,$D$2),"") -> 0 | Q126: =IF(AND(TRUE,Q$67<>""),SUMIFS(Flussi!$F:$F,Flussi!$B:$B,Q$67,Flussi!$D:$D,$J126,Flussi!$E:$E,$K126,Flussi!$A:$A,$D$2),"") -> 0 | R126: =IF(AND(TRUE,R$67<>""),SUMIFS(Flussi!$F:$F,Flussi!$B:$B,R$67,Flussi!$D:$D,$J126,Flussi!$E:$E,$K126,Flussi!$A:$A,$D$2),"") -> 0 | S126: =IF(AND(TRUE,S$67<>""),SUMIFS(Flussi!$F:$F,Flussi!$B:$B,S$67,Flussi!$D:$D,$J126,Flussi!$E:$E,$K126,Flussi!$A:$A,$D$2),"") -> 0 | ... AO126: =IF(AND(TRUE,AO$67<>""),SUMIFS(Flussi!$F:$F,Flussi!$B:$B,AO$67,Flussi!$D:$D,$J126,Flussi!$E:$E,$K126,Flussi!$A:$A,$D$2),"")
H127: =YEAR($E$4) -> 2026 | L127: =IF(AND($H127<>"",L$67<>""),IF(AND(L$67>=$H127,L$67<$H127+$D$28),SUMIFS($L$126:$AO$126,$L$67:$AO$67,$H127)/$D$28,0),"") -> #REF! | M127: =IF(AND($H127<>"",M$67<>""),IF(AND(M$67>=$H127,M$67<$H127+$D$28),SUMIFS($L$126:$AO$126,$L$67:$AO$67,$H127)/$D$28,0),"") -> #REF! | N127: =IF(AND($H127<>"",N$67<>""),IF(AND(N$67>=$H127,N$67<$H127+$D$28),SUMIFS($L$126:$AO$126,$L$67:$AO$67,$H127)/$D$28,0),"") -> #REF! | O127: =IF(AND($H127<>"",O$67<>""),IF(AND(O$67>=$H127,O$67<$H127+$D$28),SUMIFS($L$126:$AO$126,$L$67:$AO$67,$H127)/$D$28,0),"") -> #REF! | P127: =IF(AND($H127<>"",P$67<>""),IF(AND(P$67>=$H127,P$67<$H127+$D$28),SUMIFS($L$126:$AO$126,$L$67:$AO$67,$H127)/$D$28,0),"") -> #REF! | Q127: =IF(AND($H127<>"",Q$67<>""),IF(AND(Q$67>=$H127,Q$67<$H127+$D$28),SUMIFS($L$126:$AO$126,$L$67:$AO$67,$H127)/$D$28,0),"") -> #REF! | R127: =IF(AND($H127<>"",R$67<>""),IF(AND(R$67>=$H127,R$67<$H127+$D$28),SUMIFS($L$126:$AO$126,$L$67:$AO$67,$H127)/$D$28,0),"") -> #REF! | S127: =IF(AND($H127<>"",S$67<>""),IF(AND(S$67>=$H127,S$67<$H127+$D$28),SUMIFS($L$126:$AO$126,$L$67:$AO$67,$H127)/$D$28,0),"") -> #REF! | ... AO127: =IF(AND($H127<>"",AO$67<>""),IF(AND(AO$67>=$H127,AO$67<$H127+$D$28),SUMIFS($L$126:$AO$126,$L$67:$AO$67,$H127)/$D$28,0),"")
H128: =IF(H127<>"",IF(H127+1<YEAR($E$4)+$E$5,H127+1,""),"") -> 2027 | L128: =IF(AND($H128<>"",L$67<>""),IF(AND(L$67>=$H128,L$67<$H128+$D$28),SUMIFS($L$126:$AO$126,$L$67:$AO$67,$H128)/$D$28,0),"") -> #REF! | M128: =IF(AND($H128<>"",M$67<>""),IF(AND(M$67>=$H128,M$67<$H128+$D$28),SUMIFS($L$126:$AO$126,$L$67:$AO$67,$H128)/$D$28,0),"") -> #REF! | N128: =IF(AND($H128<>"",N$67<>""),IF(AND(N$67>=$H128,N$67<$H128+$D$28),SUMIFS($L$126:$AO$126,$L$67:$AO$67,$H128)/$D$28,0),"") -> #REF! | O128: =IF(AND($H128<>"",O$67<>""),IF(AND(O$67>=$H128,O$67<$H128+$D$28),SUMIFS($L$126:$AO$126,$L$67:$AO$67,$H128)/$D$28,0),"") -> #REF! | P128: =IF(AND($H128<>"",P$67<>""),IF(AND(P$67>=$H128,P$67<$H128+$D$28),SUMIFS($L$126:$AO$126,$L$67:$AO$67,$H128)/$D$28,0),"") -> #REF! | Q128: =IF(AND($H128<>"",Q$67<>""),IF(AND(Q$67>=$H128,Q$67<$H128+$D$28),SUMIFS($L$126:$AO$126,$L$67:$AO$67,$H128)/$D$28,0),"") -> #REF! | R128: =IF(AND($H128<>"",R$67<>""),IF(AND(R$67>=$H128,R$67<$H128+$D$28),SUMIFS($L$126:$AO$126,$L$67:$AO$67,$H128)/$D$28,0),"") -> #REF! | S128: =IF(AND($H128<>"",S$67<>""),IF(AND(S$67>=$H128,S$67<$H128+$D$28),SUMIFS($L$126:$AO$126,$L$67:$AO$67,$H128)/$D$28,0),"") -> #REF! | ... AO128: =IF(AND($H128<>"",AO$67<>""),IF(AND(AO$67>=$H128,AO$67<$H128+$D$28),SUMIFS($L$126:$AO$126,$L$67:$AO$67,$H128)/$D$28,0),"")
H129: =IF(H128<>"",IF(H128+1<YEAR($E$4)+$E$5,H128+1,""),"") -> 2028 | L129: =IF(AND($H129<>"",L$67<>""),IF(AND(L$67>=$H129,L$67<$H129+$D$28),SUMIFS($L$126:$AO$126,$L$67:$AO$67,$H129)/$D$28,0),"") -> #REF! | M129: =IF(AND($H129<>"",M$67<>""),IF(AND(M$67>=$H129,M$67<$H129+$D$28),SUMIFS($L$126:$AO$126,$L$67:$AO$67,$H129)/$D$28,0),"") -> #REF! | N129: =IF(AND($H129<>"",N$67<>""),IF(AND(N$67>=$H129,N$67<$H129+$D$28),SUMIFS($L$126:$AO$126,$L$67:$AO$67,$H129)/$D$28,0),"") -> #REF! | O129: =IF(AND($H129<>"",O$67<>""),IF(AND(O$67>=$H129,O$67<$H129+$D$28),SUMIFS($L$126:$AO$126,$L$67:$AO$67,$H129)/$D$28,0),"") -> #REF! | P129: =IF(AND($H129<>"",P$67<>""),IF(AND(P$67>=$H129,P$67<$H129+$D$28),SUMIFS($L$126:$AO$126,$L$67:$AO$67,$H129)/$D$28,0),"") -> #REF! | Q129: =IF(AND($H129<>"",Q$67<>""),IF(AND(Q$67>=$H129,Q$67<$H129+$D$28),SUMIFS($L$126:$AO$126,$L$67:$AO$67,$H129)/$D$28,0),"") -> #REF! | R129: =IF(AND($H129<>"",R$67<>""),IF(AND(R$67>=$H129,R$67<$H129+$D$28),SUMIFS($L$126:$AO$126,$L$67:$AO$67,$H129)/$D$28,0),"") -> #REF! | S129: =IF(AND($H129<>"",S$67<>""),IF(AND(S$67>=$H129,S$67<$H129+$D$28),SUMIFS($L$126:$AO$126,$L$67:$AO$67,$H129)/$D$28,0),"") -> #REF! | ... AO129: =IF(AND($H129<>"",AO$67<>""),IF(AND(AO$67>=$H129,AO$67<$H129+$D$28),SUMIFS($L$126:$AO$126,$L$67:$AO$67,$H129)/$D$28,0),"")
H130: =IF(H129<>"",IF(H129+1<YEAR($E$4)+$E$5,H129+1,""),"") -> 2029 | L130: =IF(AND($H130<>"",L$67<>""),IF(AND(L$67>=$H130,L$67<$H130+$D$28),SUMIFS($L$126:$AO$126,$L$67:$AO$67,$H130)/$D$28,0),"") -> #REF! | M130: =IF(AND($H130<>"",M$67<>""),IF(AND(M$67>=$H130,M$67<$H130+$D$28),SUMIFS($L$126:$AO$126,$L$67:$AO$67,$H130)/$D$28,0),"") -> #REF! | N130: =IF(AND($H130<>"",N$67<>""),IF(AND(N$67>=$H130,N$67<$H130+$D$28),SUMIFS($L$126:$AO$126,$L$67:$AO$67,$H130)/$D$28,0),"") -> #REF! | O130: =IF(AND($H130<>"",O$67<>""),IF(AND(O$67>=$H130,O$67<$H130+$D$28),SUMIFS($L$126:$AO$126,$L$67:$AO$67,$H130)/$D$28,0),"") -> #REF! | P130: =IF(AND($H130<>"",P$67<>""),IF(AND(P$67>=$H130,P$67<$H130+$D$28),SUMIFS($L$126:$AO$126,$L$67:$AO$67,$H130)/$D$28,0),"") -> #REF! | Q130: =IF(AND($H130<>"",Q$67<>""),IF(AND(Q$67>=$H130,Q$67<$H130+$D$28),SUMIFS($L$126:$AO$126,$L$67:$AO$67,$H130)/$D$28,0),"") -> #REF! | R130: =IF(AND($H130<>"",R$67<>""),IF(AND(R$67>=$H130,R$67<$H130+$D$28),SUMIFS($L$126:$AO$126,$L$67:$AO$67,$H130)/$D$28,0),"") -> #REF! | S130: =IF(AND($H130<>"",S$67<>""),IF(AND(S$67>=$H130,S$67<$H130+$D$28),SUMIFS($L$126:$AO$126,$L$67:$AO$67,$H130)/$D$28,0),"") -> #REF! | ... AO130: =IF(AND($H130<>"",AO$67<>""),IF(AND(AO$67>=$H130,AO$67<$H130+$D$28),SUMIFS($L$126:$AO$126,$L$67:$AO$67,$H130)/$D$28,0),"")
H131: =IF(H130<>"",IF(H130+1<YEAR($E$4)+$E$5,H130+1,""),"") -> 2030 | L131: =IF(AND($H131<>"",L$67<>""),IF(AND(L$67>=$H131,L$67<$H131+$D$28),SUMIFS($L$126:$AO$126,$L$67:$AO$67,$H131)/$D$28,0),"") -> #REF! | M131: =IF(AND($H131<>"",M$67<>""),IF(AND(M$67>=$H131,M$67<$H131+$D$28),SUMIFS($L$126:$AO$126,$L$67:$AO$67,$H131)/$D$28,0),"") -> #REF! | N131: =IF(AND($H131<>"",N$67<>""),IF(AND(N$67>=$H131,N$67<$H131+$D$28),SUMIFS($L$126:$AO$126,$L$67:$AO$67,$H131)/$D$28,0),"") -> #REF! | O131: =IF(AND($H131<>"",O$67<>""),IF(AND(O$67>=$H131,O$67<$H131+$D$28),SUMIFS($L$126:$AO$126,$L$67:$AO$67,$H131)/$D$28,0),"") -> #REF! | P131: =IF(AND($H131<>"",P$67<>""),IF(AND(P$67>=$H131,P$67<$H131+$D$28),SUMIFS($L$126:$AO$126,$L$67:$AO$67,$H131)/$D$28,0),"") -> #REF! | Q131: =IF(AND($H131<>"",Q$67<>""),IF(AND(Q$67>=$H131,Q$67<$H131+$D$28),SUMIFS($L$126:$AO$126,$L$67:$AO$67,$H131)/$D$28,0),"") -> #REF! | R131: =IF(AND($H131<>"",R$67<>""),IF(AND(R$67>=$H131,R$67<$H131+$D$28),SUMIFS($L$126:$AO$126,$L$67:$AO$67,$H131)/$D$28,0),"") -> #REF! | S131: =IF(AND($H131<>"",S$67<>""),IF(AND(S$67>=$H131,S$67<$H131+$D$28),SUMIFS($L$126:$AO$126,$L$67:$AO$67,$H131)/$D$28,0),"") -> #REF! | ... AO131: =IF(AND($H131<>"",AO$67<>""),IF(AND(AO$67>=$H131,AO$67<$H131+$D$28),SUMIFS($L$126:$AO$126,$L$67:$AO$67,$H131)/$D$28,0),"")
H132: =IF(H131<>"",IF(H131+1<YEAR($E$4)+$E$5,H131+1,""),"") -> 2031 | L132: =IF(AND($H132<>"",L$67<>""),IF(AND(L$67>=$H132,L$67<$H132+$D$28),SUMIFS($L$126:$AO$126,$L$67:$AO$67,$H132)/$D$28,0),"") -> #REF! | M132: =IF(AND($H132<>"",M$67<>""),IF(AND(M$67>=$H132,M$67<$H132+$D$28),SUMIFS($L$126:$AO$126,$L$67:$AO$67,$H132)/$D$28,0),"") -> #REF! | N132: =IF(AND($H132<>"",N$67<>""),IF(AND(N$67>=$H132,N$67<$H132+$D$28),SUMIFS($L$126:$AO$126,$L$67:$AO$67,$H132)/$D$28,0),"") -> #REF! | O132: =IF(AND($H132<>"",O$67<>""),IF(AND(O$67>=$H132,O$67<$H132+$D$28),SUMIFS($L$126:$AO$126,$L$67:$AO$67,$H132)/$D$28,0),"") -> #REF! | P132: =IF(AND($H132<>"",P$67<>""),IF(AND(P$67>=$H132,P$67<$H132+$D$28),SUMIFS($L$126:$AO$126,$L$67:$AO$67,$H132)/$D$28,0),"") -> #REF! | Q132: =IF(AND($H132<>"",Q$67<>""),IF(AND(Q$67>=$H132,Q$67<$H132+$D$28),SUMIFS($L$126:$AO$126,$L$67:$AO$67,$H132)/$D$28,0),"") -> #REF! | R132: =IF(AND($H132<>"",R$67<>""),IF(AND(R$67>=$H132,R$67<$H132+$D$28),SUMIFS($L$126:$AO$126,$L$67:$AO$67,$H132)/$D$28,0),"") -> #REF! | S132: =IF(AND($H132<>"",S$67<>""),IF(AND(S$67>=$H132,S$67<$H132+$D$28),SUMIFS($L$126:$AO$126,$L$67:$AO$67,$H132)/$D$28,0),"") -> #REF! | ... AO132: =IF(AND($H132<>"",AO$67<>""),IF(AND(AO$67>=$H132,AO$67<$H132+$D$28),SUMIFS($L$126:$AO$126,$L$67:$AO$67,$H132)/$D$28,0),"")
H133: =IF(H132<>"",IF(H132+1<YEAR($E$4)+$E$5,H132+1,""),"") -> 2032 | L133: =IF(AND($H133<>"",L$67<>""),IF(AND(L$67>=$H133,L$67<$H133+$D$28),SUMIFS($L$126:$AO$126,$L$67:$AO$67,$H133)/$D$28,0),"") -> #REF! | M133: =IF(AND($H133<>"",M$67<>""),IF(AND(M$67>=$H133,M$67<$H133+$D$28),SUMIFS($L$126:$AO$126,$L$67:$AO$67,$H133)/$D$28,0),"") -> #REF! | N133: =IF(AND($H133<>"",N$67<>""),IF(AND(N$67>=$H133,N$67<$H133+$D$28),SUMIFS($L$126:$AO$126,$L$67:$AO$67,$H133)/$D$28,0),"") -> #REF! | O133: =IF(AND($H133<>"",O$67<>""),IF(AND(O$67>=$H133,O$67<$H133+$D$28),SUMIFS($L$126:$AO$126,$L$67:$AO$67,$H133)/$D$28,0),"") -> #REF! | P133: =IF(AND($H133<>"",P$67<>""),IF(AND(P$67>=$H133,P$67<$H133+$D$28),SUMIFS($L$126:$AO$126,$L$67:$AO$67,$H133)/$D$28,0),"") -> #REF! | Q133: =IF(AND($H133<>"",Q$67<>""),IF(AND(Q$67>=$H133,Q$67<$H133+$D$28),SUMIFS($L$126:$AO$126,$L$67:$AO$67,$H133)/$D$28,0),"") -> #REF! | R133: =IF(AND($H133<>"",R$67<>""),IF(AND(R$67>=$H133,R$67<$H133+$D$28),SUMIFS($L$126:$AO$126,$L$67:$AO$67,$H133)/$D$28,0),"") -> #REF! | S133: =IF(AND($H133<>"",S$67<>""),IF(AND(S$67>=$H133,S$67<$H133+$D$28),SUMIFS($L$126:$AO$126,$L$67:$AO$67,$H133)/$D$28,0),"") -> #REF! | ... AO133: =IF(AND($H133<>"",AO$67<>""),IF(AND(AO$67>=$H133,AO$67<$H133+$D$28),SUMIFS($L$126:$AO$126,$L$67:$AO$67,$H133)/$D$28,0),"")
H134: =IF(H133<>"",IF(H133+1<YEAR($E$4)+$E$5,H133+1,""),"") -> 2033 | L134: =IF(AND($H134<>"",L$67<>""),IF(AND(L$67>=$H134,L$67<$H134+$D$28),SUMIFS($L$126:$AO$126,$L$67:$AO$67,$H134)/$D$28,0),"") -> #REF! | M134: =IF(AND($H134<>"",M$67<>""),IF(AND(M$67>=$H134,M$67<$H134+$D$28),SUMIFS($L$126:$AO$126,$L$67:$AO$67,$H134)/$D$28,0),"") -> #REF! | N134: =IF(AND($H134<>"",N$67<>""),IF(AND(N$67>=$H134,N$67<$H134+$D$28),SUMIFS($L$126:$AO$126,$L$67:$AO$67,$H134)/$D$28,0),"") -> #REF! | O134: =IF(AND($H134<>"",O$67<>""),IF(AND(O$67>=$H134,O$67<$H134+$D$28),SUMIFS($L$126:$AO$126,$L$67:$AO$67,$H134)/$D$28,0),"") -> #REF! | P134: =IF(AND($H134<>"",P$67<>""),IF(AND(P$67>=$H134,P$67<$H134+$D$28),SUMIFS($L$126:$AO$126,$L$67:$AO$67,$H134)/$D$28,0),"") -> #REF! | Q134: =IF(AND($H134<>"",Q$67<>""),IF(AND(Q$67>=$H134,Q$67<$H134+$D$28),SUMIFS($L$126:$AO$126,$L$67:$AO$67,$H134)/$D$28,0),"") -> #REF! | R134: =IF(AND($H134<>"",R$67<>""),IF(AND(R$67>=$H134,R$67<$H134+$D$28),SUMIFS($L$126:$AO$126,$L$67:$AO$67,$H134)/$D$28,0),"") -> #REF! | S134: =IF(AND($H134<>"",S$67<>""),IF(AND(S$67>=$H134,S$67<$H134+$D$28),SUMIFS($L$126:$AO$126,$L$67:$AO$67,$H134)/$D$28,0),"") -> #REF! | ... AO134: =IF(AND($H134<>"",AO$67<>""),IF(AND(AO$67>=$H134,AO$67<$H134+$D$28),SUMIFS($L$126:$AO$126,$L$67:$AO$67,$H134)/$D$28,0),"")
H135: =IF(H134<>"",IF(H134+1<YEAR($E$4)+$E$5,H134+1,""),"") -> 2034 | L135: =IF(AND($H135<>"",L$67<>""),IF(AND(L$67>=$H135,L$67<$H135+$D$28),SUMIFS($L$126:$AO$126,$L$67:$AO$67,$H135)/$D$28,0),"") -> #REF! | M135: =IF(AND($H135<>"",M$67<>""),IF(AND(M$67>=$H135,M$67<$H135+$D$28),SUMIFS($L$126:$AO$126,$L$67:$AO$67,$H135)/$D$28,0),"") -> #REF! | N135: =IF(AND($H135<>"",N$67<>""),IF(AND(N$67>=$H135,N$67<$H135+$D$28),SUMIFS($L$126:$AO$126,$L$67:$AO$67,$H135)/$D$28,0),"") -> #REF! | O135: =IF(AND($H135<>"",O$67<>""),IF(AND(O$67>=$H135,O$67<$H135+$D$28),SUMIFS($L$126:$AO$126,$L$67:$AO$67,$H135)/$D$28,0),"") -> #REF! | P135: =IF(AND($H135<>"",P$67<>""),IF(AND(P$67>=$H135,P$67<$H135+$D$28),SUMIFS($L$126:$AO$126,$L$67:$AO$67,$H135)/$D$28,0),"") -> #REF! | Q135: =IF(AND($H135<>"",Q$67<>""),IF(AND(Q$67>=$H135,Q$67<$H135+$D$28),SUMIFS($L$126:$AO$126,$L$67:$AO$67,$H135)/$D$28,0),"") -> #REF! | R135: =IF(AND($H135<>"",R$67<>""),IF(AND(R$67>=$H135,R$67<$H135+$D$28),SUMIFS($L$126:$AO$126,$L$67:$AO$67,$H135)/$D$28,0),"") -> #REF! | S135: =IF(AND($H135<>"",S$67<>""),IF(AND(S$67>=$H135,S$67<$H135+$D$28),SUMIFS($L$126:$AO$126,$L$67:$AO$67,$H135)/$D$28,0),"") -> #REF! | ... AO135: =IF(AND($H135<>"",AO$67<>""),IF(AND(AO$67>=$H135,AO$67<$H135+$D$28),SUMIFS($L$126:$AO$126,$L$67:$AO$67,$H135)/$D$28,0),"")
H136: =IF(H135<>"",IF(H135+1<YEAR($E$4)+$E$5,H135+1,""),"") -> 2035 | L136: =IF(AND($H136<>"",L$67<>""),IF(AND(L$67>=$H136,L$67<$H136+$D$28),SUMIFS($L$126:$AO$126,$L$67:$AO$67,$H136)/$D$28,0),"") -> #REF! | M136: =IF(AND($H136<>"",M$67<>""),IF(AND(M$67>=$H136,M$67<$H136+$D$28),SUMIFS($L$126:$AO$126,$L$67:$AO$67,$H136)/$D$28,0),"") -> #REF! | N136: =IF(AND($H136<>"",N$67<>""),IF(AND(N$67>=$H136,N$67<$H136+$D$28),SUMIFS($L$126:$AO$126,$L$67:$AO$67,$H136)/$D$28,0),"") -> #REF! | O136: =IF(AND($H136<>"",O$67<>""),IF(AND(O$67>=$H136,O$67<$H136+$D$28),SUMIFS($L$126:$AO$126,$L$67:$AO$67,$H136)/$D$28,0),"") -> #REF! | P136: =IF(AND($H136<>"",P$67<>""),IF(AND(P$67>=$H136,P$67<$H136+$D$28),SUMIFS($L$126:$AO$126,$L$67:$AO$67,$H136)/$D$28,0),"") -> #REF! | Q136: =IF(AND($H136<>"",Q$67<>""),IF(AND(Q$67>=$H136,Q$67<$H136+$D$28),SUMIFS($L$126:$AO$126,$L$67:$AO$67,$H136)/$D$28,0),"") -> #REF! | R136: =IF(AND($H136<>"",R$67<>""),IF(AND(R$67>=$H136,R$67<$H136+$D$28),SUMIFS($L$126:$AO$126,$L$67:$AO$67,$H136)/$D$28,0),"") -> #REF! | S136: =IF(AND($H136<>"",S$67<>""),IF(AND(S$67>=$H136,S$67<$H136+$D$28),SUMIFS($L$126:$AO$126,$L$67:$AO$67,$H136)/$D$28,0),"") -> #REF! | ... AO136: =IF(AND($H136<>"",AO$67<>""),IF(AND(AO$67>=$H136,AO$67<$H136+$D$28),SUMIFS($L$126:$AO$126,$L$67:$AO$67,$H136)/$D$28,0),"")
...

Sheet Strambio
B1: Dati generali
B2: Asset | D2: Strambio
B3: Acquisto | C3: Valore immobile | D3: -420000 | E3: 44895 | F3: =EDATE(E3,($E$5)*12)-1 -> 55486
B4: Data acquisto | E4: 44895 | F4: =EDATE(E4,($E$5)*12)-1 -> 55486 | I4: IRR | J4: =$L$302 -> 0.025546688
B5: Anni investimento | E5: 29 | I5: NPV | J5: =MAX(300:300) -> 104702.56
B6: Acquisto da? | E6: Privato/Imprese
B7: Prima casa? | E7: SI
B8: Rendita catastale | C8: - | D8: =522.91+15.18 -> 538.09 | E8: =$E$4 -> 44895 | F8: =EDATE(E8,$E$5*12)-1 -> 55486
B9: Rivalutazione | C9: - | D9: 0 | E9: =$E$4 -> 44895 | F9: 44926
B10: Rivalutazione | C10: - | D10: 0.016 | E10: =F9+1 -> 44927 | F10: =F4 -> 55486
B12: Ricavi
B13: Affitto | C13: Alloggio | D13: =D14/12*8 -> 7200 | E13: 44986 | F13: 45291
B14: Affitto | C14: Alloggio | D14: =900*12 -> 10800 | E14: =F13+1 -> 45292 | F14: =F4 -> 55486
B15: Vendita | C15: Alloggio | D15: =-$D$3*(1+D10)^E5 -> 665528.75 | E15: =EDATE($E$4,$E$5*12)-1 -> 55486 | F15: =EDATE($E$4,$E$5*12) -> 55487
B17: Costi
B18: Avviamento | C18: - | E18: =$E$4 -> 44895 | F18: =EDATE(E18,$E$5*12)-1 -> 55486
B19: Condominio | C19: Ordinario | D19: =-600*4 -> -2400 | E19: =$E$4 -> 44895 | F19: =EDATE(E19,$E$5*12)-1 -> 55486
B20: Assicurazione | C20: - | D20: =-23.7*12 -> -284.4 | E20: =$E$4 -> 44895 | F20: 46053
B21: Utenze | C21: Gas | D21: =-12*12 -> -144 | E21: =$E$4 -> 44895 | F21: =EDATE(E21,$E$5*12)-1 -> 55486
B22: Utenze | C22: Luce | D22: =-35*12 -> -420 | E22: =$E$4 -> 44895 | F22: =EDATE(E22,$E$5*12)-1 -> 55486
B23: Utenze | C23: Internet | D23: =-20.88*12 -> -250.56 | E23: =$E$4 -> 44895 | F23: =EDATE(E23,$E$5*12)-1 -> 55486
B24: Manutenzione ordinaria | C24: - | D24: -200 | E24: =$E$4 -> 44895 | F24: =EDATE(E24,$E$5*12)-1 -> 55486
B25: Manutenzione straordinaria | C25: - | D25: -300 | E25: =$E$4 -> 44895 | F25: =EDATE(E25,$E$5*12)-1 -> 55486
B27: Ammortamenti
B28: Anni | D28: 10
B30: Oneri finanziari
B31: Mutuo0 | C31: Importo | D31: 294000 | E31: 44895 | F31: 45657
B32: Mutuo0 | C32: Periodi | D32: 12
B33: Mutuo0 | C33: Anni | D33: 20
B34: Mutuo0 | C34: Decorrenza | D34: 44958
B35: Mutuo0 | C35: Commissioni | D35: 4
B36: Mutuo0 | C36: Tasso | D36: 0.032 | E36: 45536 | F36: 46539
B37: Mutuo1 | C37: Importo | D37: 208635.71 | E37: 45716 | F37: =EDATE(E37,$D$33*$D$32)-1 -> 53020
B38: Mutuo1 | C38: Periodi | D38: 12
B39: Mutuo1 | C39: Anni | D39: 20
B40: Mutuo1 | C40: Decorrenza | D40: 45716
B41: Mutuo1 | C41: Commissioni | D41: 2.75
B42: Mutuo1 | C42: Tasso | D42: 0.0272 | E42: =D40 -> 45716 | F42: =EDATE(E42,$D$33*12)-1 -> 53020
B44: Tasse
B45: Imposte | C45: Registro | D45: =-IF($E$7="SI",MAX(2%*$D$8*105%*120,1000),MAX(9%*$D$8*105%*120,1000)) -> -1355.9868 | E45: =$E$4 -> 44895 | F45: =EDATE(E45,$E$5*12)-1 -> 55486
B46: Imposte | C46: Ipotecaria | D46: =-IF($E$6="Privato/Imprese",50,200) -> -50 | E46: =$E$4 -> 44895 | F46: =EDATE(E46,$E$5*12)-1 -> 55486
B47: Imposte | C47: Catastale | D47: =-IF($E$6="Privato/Imprese",50,200) -> -50 | E47: =$E$4 -> 44895 | F47: =EDATE(E47,$E$5*12)-1 -> 55486
B48: Imposte | C48: IMU | D48: =IF($E$7="SI",0,$D$8*1.05*160*1.06%) -> 0 | E48: =$E$4 -> 44895 | F48: =EDATE(E48,$E$5*12)-1 -> 55486
B49: Imposte | C49: TARI | D49: -176 | E49: =$E$4 -> 44895 | F49: =EDATE(E49,$E$5*12)-1 -> 55486
B51: Detrazioni
B52: Mutuo | C52: Cap detrazione | D52: =4000*$D$31/294000 -> 4000 | E52: Ripartizione mutuo
B53: Mutuo | C53: % detrazione | D53: 0.19
B54: Intermediazione | C54: Cap detrazione | D54: 1000
B55: Intermediazione | C55: % detrazione | D55: 0.19
B56: Ristrutturazione | C56: Cap detrazione | D56: 96000
B57: Ristrutturazione | C57: % detrazione | D57: 0.5
B58: Arredamento | C58: Cap detrazione | D58: 10000 | E58: 44562 | F58: 44592
B59: Arredamento | C59: Cap detrazione | D59: 8000 | E59: 44927 | F59: 44957
B60: Arredamento | C60: Cap detrazione | D60: 5000 | E60: 45292 | F60: 45322
B61: Arredamento | C61: % detrazione | D61: 0.5
B62: Offset detrazioni | D62: 1
I65: Profit & Loss
I67: Tipo | J67: Servizio | K67: Voce | L67: =YEAR($E$4) -> 2022 | M67: =IF(L67<>"",IF(L67+1<=YEAR($E$4)+$E$5+$D$62,L67+1,""),"") -> 2023 | N67: =IF(M67<>"",IF(M67+1<=YEAR($E$4)+$E$5+$D$62,M67+1,""),"") -> 2024 | O67: =IF(N67<>"",IF(N67+1<=YEAR($E$4)+$E$5+$D$62,N67+1,""),"") -> 2025 | P67: =IF(O67<>"",IF(O67+1<=YEAR($E$4)+$E$5+$D$62,O67+1,""),"") -> 2026 | Q67: =IF(P67<>"",IF(P67+1<=YEAR($E$4)+$E$5+$D$62,P67+1,""),"") -> 2027 | R67: =IF(Q67<>"",IF(Q67+1<=YEAR($E$4)+$E$5+$D$62,Q67+1,""),"") -> 2028 | S67: =IF(R67<>"",IF(R67+1<=YEAR($E$4)+$E$5+$D$62,R67+1,""),"") -> 2029 | T67: =IF(S67<>"",IF(S67+1<=YEAR($E$4)+$E$5+$D$62,S67+1,""),"") -> 2030 | ... AO67: =IF(AN67<>"",IF(AN67+1<=YEAR($E$4)+$E$5+$D$62,AN67+1,""),"") -> 2051
J69: Affitto | K69: Alloggio | L69: =IF(AND(TRUE,L$67<>""),SUMIFS(Flussi!$F:$F,Flussi!$B:$B,L$67,Flussi!$D:$D,$J69,Flussi!$E:$E,$K69,Flussi!$A:$A,$D$2),"") -> 0 | M69: =IF(AND(TRUE,M$67<>""),SUMIFS(Flussi!$F:$F,Flussi!$B:$B,M$67,Flussi!$D:$D,$J69,Flussi!$E:$E,$K69,Flussi!$A:$A,$D$2),"") -> 7200 | N69: =IF(AND(TRUE,N$67<>""),SUMIFS(Flussi!$F:$F,Flussi!$B:$B,N$67,Flussi!$D:$D,$J69,Flussi!$E:$E,$K69,Flussi!$A:$A,$D$2),"") -> 10800 | O69: =IF(AND(TRUE,O$67<>""),SUMIFS(Flussi!$F:$F,Flussi!$B:$B,O$67,Flussi!$D:$D,$J69,Flussi!$E:$E,$K69,Flussi!$A:$A,$D$2),"") -> 10800 | P69: =IF(AND(TRUE,P$67<>""),SUMIFS(Flussi!$F:$F,Flussi!$B:$B,P$67,Flussi!$D:$D,$J69,Flussi!$E:$E,$K69,Flussi!$A:$A,$D$2),"") -> 10800 | Q69: =IF(AND(TRUE,Q$67<>""),SUMIFS(Flussi!$F:$F,Flussi!$B:$B,Q$67,Flussi!$D:$D,$J69,Flussi!$E:$E,$K69,Flussi!$A:$A,$D$2),"") -> 10800 | R69: =IF(AND(TRUE,R$67<>""),SUMIFS(Flussi!$F:$F,Flussi!$B:$B,R$67,Flussi!$D:$D,$J69,Flussi!$E:$E,$K69,Flussi!$A:$A,$D$2),"") -> 10800 | S69: =IF(AND(TRUE,S$67<>""),SUMIFS(Flussi!$F:$F,Flussi!$B:$B,S$67,Flussi!$D:$D,$J69,Flussi!$E:$E,$K69,Flussi!$A:$A,$D$2),"") -> 10800 | ... AO69: =IF(AND(TRUE,AO$67<>""),SUMIFS(Flussi!$F:$F,Flussi!$B:$B,AO$67,Flussi!$D:$D,$J69,Flussi!$E:$E,$K69,Flussi!$A:$A,$D$2),"") -> 0
J70: Affitto | K70: Box | L70: =IF(AND(TRUE,L$67<>""),SUMIFS(Flussi!$F:$F,Flussi!$B:$B,L$67,Flussi!$D:$D,$J70,Flussi!$E:$E,$K70,Flussi!$A:$A,$D$2),"") -> 0 | M70: =IF(AND(TRUE,M$67<>""),SUMIFS(Flussi!$F:$F,Flussi!$B:$B,M$67,Flussi!$D:$D,$J70,Flussi!$E:$E,$K70,Flussi!$A:$A,$D$2),"") -> 0 | N70: =IF(AND(TRUE,N$67<>""),SUMIFS(Flussi!$F:$F,Flussi!$B:$B,N$67,Flussi!$D:$D,$J70,Flussi!$E:$E,$K70,Flussi!$A:$A,$D$2),"") -> 0 | O70: =IF(AND(TRUE,O$67<>""),SUMIFS(Flussi!$F:$F,Flussi!$B:$B,O$67,Flussi!$D:$D,$J70,Flussi!$E:$E,$K70,Flussi!$A:$A,$D$2),"") -> 0 | P70: =IF(AND(TRUE,P$67<>""),SUMIFS(Flussi!$F:$F,Flussi!$B:$B,P$67,Flussi!$D:$D,$J70,Flussi!$E:$E,$K70,Flussi!$A:$A,$D$2),"") -> 0 | Q70: =IF(AND(TRUE,Q$67<>""),SUMIFS(Flussi!$F:$F,Flussi!$B:$B,Q$67,Flussi!$D:$D,$J70,Flussi!$E:$E,$K70,Flussi!$A:$A,$D$2),"") -> 0 | R70: =IF(AND(TRUE,R$67<>""),SUMIFS(Flussi!$F:$F,Flussi!$B:$B,R$67,Flussi!$D:$D,$J70,Flussi!$E:$E,$K70,Flussi!$A:$A,$D$2),"") -> 0 | S70: =IF(AND(TRUE,S$67<>""),SUMIFS(Flussi!$F:$F,Flussi!$B:$B,S$67,Flussi!$D:$D,$J70,Flussi!$E:$E,$K70,Flussi!$A:$A,$D$2),"") -> 0 | ... AO70: =IF(AND(TRUE,AO$67<>""),SUMIFS(Flussi!$F:$F,Flussi!$B:$B,AO$67,Flussi!$D:$D,$J70,Flussi!$E:$E,$K70,Flussi!$A:$A,$D$2),"") -> 0
J71: Vendita | K71: Alloggio | L71: =IF(AND(TRUE,L$67<>""),SUMIFS(Flussi!$F:$F,Flussi!$B:$B,L$67,Flussi!$D:$D,$J71,Flussi!$E:$E,$K71,Flussi!$A:$A,$D$2),"") -> 0 | M71: =IF(AND(TRUE,M$67<>""),SUMIFS(Flussi!$F:$F,Flussi!$B:$B,M$67,Flussi!$D:$D,$J71,Flussi!$E:$E,$K71,Flussi!$A:$A,$D$2),"") -> 0 | N71: =IF(AND(TRUE,N$67<>""),SUMIFS(Flussi!$F:$F,Flussi!$B:$B,N$67,Flussi!$D:$D,$J71,Flussi!$E:$E,$K71,Flussi!$A:$A,$D$2),"") -> 0 | O71: =IF(AND(TRUE,O$67<>""),SUMIFS(Flussi!$F:$F,Flussi!$B:$B,O$67,Flussi!$D:$D,$J71,Flussi!$E:$E,$K71,Flussi!$A:$A,$D$2),"") -> 0 | P71: =IF(AND(TRUE,P$67<>""),SUMIFS(Flussi!$F:$F,Flussi!$B:$B,P$67,Flussi!$D:$D,$J71,Flussi!$E:$E,$K71,Flussi!$A:$A,$D$2),"") -> 0 | Q71: =IF(AND(TRUE,Q$67<>""),SUMIFS(Flussi!$F:$F,Flussi!$B:$B,Q$67,Flussi!$D:$D,$J71,Flussi!$E:$E,$K71,Flussi!$A:$A,$D$2),"") -> 0 | R71: =IF(AND(TRUE,R$67<>""),SUMIFS(Flussi!$F:$F,Flussi!$B:$B,R$67,Flussi!$D:$D,$J71,Flussi!$E:$E,$K71,Flussi!$A:$A,$D$2),"") -> 0 | S71: =IF(AND(TRUE,S$67<>""),SUMIFS(Flussi!$F:$F,Flussi!$B:$B,S$67,Flussi!$D:$D,$J71,Flussi!$E:$E,$K71,Flussi!$A:$A,$D$2),"") -> 0 | ... AO71: =IF(AND(TRUE,AO$67<>""),SUMIFS(Flussi!$F:$F,Flussi!$B:$B,AO$67,Flussi!$D:$D,$J71,Flussi!$E:$E,$K71,Flussi!$A:$A,$D$2),"") -> 665528.75
J72: Vendita | K72: Box | L72: =IF(AND(TRUE,L$67<>""),SUMIFS(Flussi!$F:$F,Flussi!$B:$B,L$67,Flussi!$D:$D,$J72,Flussi!$E:$E,$K72,Flussi!$A:$A,$D$2),"") -> 0 | M72: =IF(AND(TRUE,M$67<>""),SUMIFS(Flussi!$F:$F,Flussi!$B:$B,M$67,Flussi!$D:$D,$J72,Flussi!$E:$E,$K72,Flussi!$A:$A,$D$2),"") -> 0 | N72: =IF(AND(TRUE,N$67<>""),SUMIFS(Flussi!$F:$F,Flussi!$B:$B,N$67,Flussi!$D:$D,$J72,Flussi!$E:$E,$K72,Flussi!$A:$A,$D$2),"") -> 0 | O72: =IF(AND(TRUE,O$67<>""),SUMIFS(Flussi!$F:$F,Flussi!$B:$B,O$67,Flussi!$D:$D,$J72,Flussi!$E:$E,$K72,Flussi!$A:$A,$D$2),"") -> 0 | P72: =IF(AND(TRUE,P$67<>""),SUMIFS(Flussi!$F:$F,Flussi!$B:$B,P$67,Flussi!$D:$D,$J72,Flussi!$E:$E,$K72,Flussi!$A:$A,$D$2),"") -> 0 | Q72: =IF(AND(TRUE,Q$67<>""),SUMIFS(Flussi!$F:$F,Flussi!$B:$B,Q$67,Flussi!$D:$D,$J72,Flussi!$E:$E,$K72,Flussi!$A:$A,$D$2),"") -> 0 | R72: =IF(AND(TRUE,R$67<>""),SUMIFS(Flussi!$F:$F,Flussi!$B:$B,R$67,Flussi!$D:$D,$J72,Flussi!$E:$E,$K72,Flussi!$A:$A,$D$2),"") -> 0 | S72: =IF(AND(TRUE,S$67<>""),SUMIFS(Flussi!$F:$F,Flussi!$B:$B,S$67,Flussi!$D:$D,$J72,Flussi!$E:$E,$K72,Flussi!$A:$A,$D$2),"") -> 0 | ... AO72: =IF(AND(TRUE,AO$67<>""),SUMIFS(Flussi!$F:$F,Flussi!$B:$B,AO$67,Flussi!$D:$D,$J72,Flussi!$E:$E,$K72,Flussi!$A:$A,$D$2),"") -> 0
I73: Ricavi | K73: P&L | L73: =IF(AND(TRUE,L$67<>""),SUM(L69:L72),"") -> 0 | M73: =IF(AND(TRUE,M$67<>""),SUM(M69:M72),"") -> 7200 | N73: =IF(AND(TRUE,N$67<>""),SUM(N69:N72),"") -> 10800 | O73: =IF(AND(TRUE,O$67<>""),SUM(O69:O72),"") -> 10800 | P73: =IF(AND(TRUE,P$67<>""),SUM(P69:P72),"") -> 10800 | Q73: =IF(AND(TRUE,Q$67<>""),SUM(Q69:Q72),"") -> 10800 | R73: =IF(AND(TRUE,R$67<>""),SUM(R69:R72),"") -> 10800 | S73: =IF(AND(TRUE,S$67<>""),SUM(S69:S72),"") -> 10800 | ... AO73: =IF(AND(TRUE,AO$67<>""),SUM(AO69:AO72),"") -> 665528.75
J74: Utenze | K74: Gas | L74: =IF(AND(TRUE,L$67<>""),SUMIFS(Flussi!$F:$F,Flussi!$B:$B,L$67,Flussi!$D:$D,$J74,Flussi!$E:$E,$K74,Flussi!$A:$A,$D$2),"") -> 0 | M74: =IF(AND(TRUE,M$67<>""),SUMIFS(Flussi!$F:$F,Flussi!$B:$B,M$67,Flussi!$D:$D,$J74,Flussi!$E:$E,$K74,Flussi!$A:$A,$D$2),"") -> -145 | N74: =IF(AND(TRUE,N$67<>""),SUMIFS(Flussi!$F:$F,Flussi!$B:$B,N$67,Flussi!$D:$D,$J74,Flussi!$E:$E,$K74,Flussi!$A:$A,$D$2),"") -> -179 | O74: =IF(AND(TRUE,O$67<>""),SUMIFS(Flussi!$F:$F,Flussi!$B:$B,O$67,Flussi!$D:$D,$J74,Flussi!$E:$E,$K74,Flussi!$A:$A,$D$2),"") -> -190 | P74: =IF(AND(TRUE,P$67<>""),SUMIFS(Flussi!$F:$F,Flussi!$B:$B,P$67,Flussi!$D:$D,$J74,Flussi!$E:$E,$K74,Flussi!$A:$A,$D$2),"") -> -204 | Q74: =IF(AND(TRUE,Q$67<>""),SUMIFS(Flussi!$F:$F,Flussi!$B:$B,Q$67,Flussi!$D:$D,$J74,Flussi!$E:$E,$K74,Flussi!$A:$A,$D$2),"") -> -144 | R74: =IF(AND(TRUE,R$67<>""),SUMIFS(Flussi!$F:$F,Flussi!$B:$B,R$67,Flussi!$D:$D,$J74,Flussi!$E:$E,$K74,Flussi!$A:$A,$D$2),"") -> -144 | S74: =IF(AND(TRUE,S$67<>""),SUMIFS(Flussi!$F:$F,Flussi!$B:$B,S$67,Flussi!$D:$D,$J74,Flussi!$E:$E,$K74,Flussi!$A:$A,$D$2),"") -> -144 | ... AO74: =IF(AND(TRUE,AO$67<>""),SUMIFS(Flussi!$F:$F,Flussi!$B:$B,AO$67,Flussi!$D:$D,$J74,Flussi!$E:$E,$K74,Flussi!$A:$A,$D$2),"") -> 0
J75: Utenze | K75: Luce | L75: =IF(AND(TRUE,L$67<>""),SUMIFS(Flussi!$F:$F,Flussi!$B:$B,L$67,Flussi!$D:$D,$J75,Flussi!$E:$E,$K75,Flussi!$A:$A,$D$2),"") -> -80 | M75: =IF(AND(TRUE,M$67<>""),SUMIFS(Flussi!$F:$F,Flussi!$B:$B,M$67,Flussi!$D:$D,$J75,Flussi!$E:$E,$K75,Flussi!$A:$A,$D$2),"") -> -390.802 | N75: =IF(AND(TRUE,N$67<>""),SUMIFS(Flussi!$F:$F,Flussi!$B:$B,N$67,Flussi!$D:$D,$J75,Flussi!$E:$E,$K75,Flussi!$A:$A,$D$2),"") -> -420 | O75: =IF(AND(TRUE,O$67<>""),SUMIFS(Flussi!$F:$F,Flussi!$B:$B,O$67,Flussi!$D:$D,$J75,Flussi!$E:$E,$K75,Flussi!$A:$A,$D$2),"") -> -464.6 | P75: =IF(AND(TRUE,P$67<>""),SUMIFS(Flussi!$F:$F,Flussi!$B:$B,P$67,Flussi!$D:$D,$J75,Flussi!$E:$E,$K75,Flussi!$A:$A,$D$2),"") -> -497 | Q75: =IF(AND(TRUE,Q$67<>""),SUMIFS(Flussi!$F:$F,Flussi!$B:$B,Q$67,Flussi!$D:$D,$J75,Flussi!$E:$E,$K75,Flussi!$A:$A,$D$2),"") -> -420 | R75: =IF(AND(TRUE,R$67<>""),SUMIFS(Flussi!$F:$F,Flussi!$B:$B,R$67,Flussi!$D:$D,$J75,Flussi!$E:$E,$K75,Flussi!$A:$A,$D$2),"") -> -420 | S75: =IF(AND(TRUE,S$67<>""),SUMIFS(Flussi!$F:$F,Flussi!$B:$B,S$67,Flussi!$D:$D,$J75,Flussi!$E:$E,$K75,Flussi!$A:$A,$D$2),"") -> -420 | ... AO75: =IF(AND(TRUE,AO$67<>""),SUMIFS(Flussi!$F:$F,Flussi!$B:$B,AO$67,Flussi!$D:$D,$J75,Flussi!$E:$E,$K75,Flussi!$A:$A,$D$2),"") -> 0
J76: Utenze | K76: Internet | L76: =IF(AND(TRUE,L$67<>""),SUMIFS(Flussi!$F:$F,Flussi!$B:$B,L$67,Flussi!$D:$D,$J76,Flussi!$E:$E,$K76,Flussi!$A:$A,$D$2),"") -> 0 | M76: =IF(AND(TRUE,M$67<>""),SUMIFS(Flussi!$F:$F,Flussi!$B:$B,M$67,Flussi!$D:$D,$J76,Flussi!$E:$E,$K76,Flussi!$A:$A,$D$2),"") -> -155.32 | N76: =IF(AND(TRUE,N$67<>""),SUMIFS(Flussi!$F:$F,Flussi!$B:$B,N$67,Flussi!$D:$D,$J76,Flussi!$E:$E,$K76,Flussi!$A:$A,$D$2),"") -> -232.98 | O76: =IF(AND(TRUE,O$67<>""),SUMIFS(Flussi!$F:$F,Flussi!$B:$B,O$67,Flussi!$D:$D,$J76,Flussi!$E:$E,$K76,Flussi!$A:$A,$D$2),"") -> -250.56 | P76: =IF(AND(TRUE,P$67<>""),SUMIFS(Flussi!$F:$F,Flussi!$B:$B,P$67,Flussi!$D:$D,$J76,Flussi!$E:$E,$K76,Flussi!$A:$A,$D$2),"") -> -250.92 | Q76: =IF(AND(TRUE,Q$67<>""),SUMIFS(Flussi!$F:$F,Flussi!$B:$B,Q$67,Flussi!$D:$D,$J76,Flussi!$E:$E,$K76,Flussi!$A:$A,$D$2),"") -> -250.56 | R76: =IF(AND(TRUE,R$67<>""),SUMIFS(Flussi!$F:$F,Flussi!$B:$B,R$67,Flussi!$D:$D,$J76,Flussi!$E:$E,$K76,Flussi!$A:$A,$D$2),"") -> -250.56 | S76: =IF(AND(TRUE,S$67<>""),SUMIFS(Flussi!$F:$F,Flussi!$B:$B,S$67,Flussi!$D:$D,$J76,Flussi!$E:$E,$K76,Flussi!$A:$A,$D$2),"") -> -250.56 | ... AO76: =IF(AND(TRUE,AO$67<>""),SUMIFS(Flussi!$F:$F,Flussi!$B:$B,AO$67,Flussi!$D:$D,$J76,Flussi!$E:$E,$K76,Flussi!$A:$A,$D$2),"") -> 0
J77: Avviamento | K77: Intermediazione | L77: =IF(AND(TRUE,L$67<>""),SUMIFS(Flussi!$F:$F,Flussi!$B:$B,L$67,Flussi!$D:$D,$J77,Flussi!$E:$E,$K77,Flussi!$A:$A,$D$2),"") -> -10004 | M77: =IF(AND(TRUE,M$67<>""),SUMIFS(Flussi!$F:$F,Flussi!$B:$B,M$67,Flussi!$D:$D,$J77,Flussi!$E:$E,$K77,Flussi!$A:$A,$D$2),"") -> 0 | N77: =IF(AND(TRUE,N$67<>""),SUMIFS(Flussi!$F:$F,Flussi!$B:$B,N$67,Flussi!$D:$D,$J77,Flussi!$E:$E,$K77,Flussi!$A:$A,$D$2),"") -> 0 | O77: =IF(AND(TRUE,O$67<>""),SUMIFS(Flussi!$F:$F,Flussi!$B:$B,O$67,Flussi!$D:$D,$J77,Flussi!$E:$E,$K77,Flussi!$A:$A,$D$2),"") -> 0 | P77: =IF(AND(TRUE,P$67<>""),SUMIFS(Flussi!$F:$F,Flussi!$B:$B,P$67,Flussi!$D:$D,$J77,Flussi!$E:$E,$K77,Flussi!$A:$A,$D$2),"") -> 0 | Q77: =IF(AND(TRUE,Q$67<>""),SUMIFS(Flussi!$F:$F,Flussi!$B:$B,Q$67,Flussi!$D:$D,$J77,Flussi!$E:$E,$K77,Flussi!$A:$A,$D$2),"") -> 0 | R77: =IF(AND(TRUE,R$67<>""),SUMIFS(Flussi!$F:$F,Flussi!$B:$B,R$67,Flussi!$D:$D,$J77,Flussi!$E:$E,$K77,Flussi!$A:$A,$D$2),"") -> 0 | S77: =IF(AND(TRUE,S$67<>""),SUMIFS(Flussi!$F:$F,Flussi!$B:$B,S$67,Flussi!$D:$D,$J77,Flussi!$E:$E,$K77,Flussi!$A:$A,$D$2),"") -> 0 | ... AO77: =IF(AND(TRUE,AO$67<>""),SUMIFS(Flussi!$F:$F,Flussi!$B:$B,AO$67,Flussi!$D:$D,$J77,Flussi!$E:$E,$K77,Flussi!$A:$A,$D$2),"") -> 0
J78: Avviamento | K78: Notaio | L78: =IF(AND(TRUE,L$67<>""),SUMIFS(Flussi!$F:$F,Flussi!$B:$B,L$67,Flussi!$D:$D,$J78,Flussi!$E:$E,$K78,Flussi!$A:$A,$D$2),"") -> -2950 | M78: =IF(AND(TRUE,M$67<>""),SUMIFS(Flussi!$F:$F,Flussi!$B:$B,M$67,Flussi!$D:$D,$J78,Flussi!$E:$E,$K78,Flussi!$A:$A,$D$2),"") -> 0 | N78: =IF(AND(TRUE,N$67<>""),SUMIFS(Flussi!$F:$F,Flussi!$B:$B,N$67,Flussi!$D:$D,$J78,Flussi!$E:$E,$K78,Flussi!$A:$A,$D$2),"") -> 0 | O78: =IF(AND(TRUE,O$67<>""),SUMIFS(Flussi!$F:$F,Flussi!$B:$B,O$67,Flussi!$D:$D,$J78,Flussi!$E:$E,$K78,Flussi!$A:$A,$D$2),"") -> 0 | P78: =IF(AND(TRUE,P$67<>""),SUMIFS(Flussi!$F:$F,Flussi!$B:$B,P$67,Flussi!$D:$D,$J78,Flussi!$E:$E,$K78,Flussi!$A:$A,$D$2),"") -> 0 | Q78: =IF(AND(TRUE,Q$67<>""),SUMIFS(Flussi!$F:$F,Flussi!$B:$B,Q$67,Flussi!$D:$D,$J78,Flussi!$E:$E,$K78,Flussi!$A:$A,$D$2),"") -> 0 | R78: =IF(AND(TRUE,R$67<>""),SUMIFS(Flussi!$F:$F,Flussi!$B:$B,R$67,Flussi!$D:$D,$J78,Flussi!$E:$E,$K78,Flussi!$A:$A,$D$2),"") -> 0 | S78: =IF(AND(TRUE,S$67<>""),SUMIFS(Flussi!$F:$F,Flussi!$B:$B,S$67,Flussi!$D:$D,$J78,Flussi!$E:$E,$K78,Flussi!$A:$A,$D$2),"") -> 0 | ... AO78: =IF(AND(TRUE,AO$67<>""),SUMIFS(Flussi!$F:$F,Flussi!$B:$B,AO$67,Flussi!$D:$D,$J78,Flussi!$E:$E,$K78,Flussi!$A:$A,$D$2),"") -> 0
J79: Condominio | K79: Ordinario | L79: =IF(AND(TRUE,L$67<>""),SUMIFS(Flussi!$F:$F,Flussi!$B:$B,L$67,Flussi!$D:$D,$J79,Flussi!$E:$E,$K79,Flussi!$A:$A,$D$2),"") -> -830 | M79: =IF(AND(TRUE,M$67<>""),SUMIFS(Flussi!$F:$F,Flussi!$B:$B,M$67,Flussi!$D:$D,$J79,Flussi!$E:$E,$K79,Flussi!$A:$A,$D$2),"") -> -2490.61 | N79: =IF(AND(TRUE,N$67<>""),SUMIFS(Flussi!$F:$F,Flussi!$B:$B,N$67,Flussi!$D:$D,$J79,Flussi!$E:$E,$K79,Flussi!$A:$A,$D$2),"") -> -1665.31 | O79: =IF(AND(TRUE,O$67<>""),SUMIFS(Flussi!$F:$F,Flussi!$B:$B,O$67,Flussi!$D:$D,$J79,Flussi!$E:$E,$K79,Flussi!$A:$A,$D$2),"") -> -2913 | P79: =IF(AND(TRUE,P$67<>""),SUMIFS(Flussi!$F:$F,Flussi!$B:$B,P$67,Flussi!$D:$D,$J79,Flussi!$E:$E,$K79,Flussi!$A:$A,$D$2),"") -> -2642.61 | Q79: =IF(AND(TRUE,Q$67<>""),SUMIFS(Flussi!$F:$F,Flussi!$B:$B,Q$67,Flussi!$D:$D,$J79,Flussi!$E:$E,$K79,Flussi!$A:$A,$D$2),"") -> -2400 | R79: =IF(AND(TRUE,R$67<>""),SUMIFS(Flussi!$F:$F,Flussi!$B:$B,R$67,Flussi!$D:$D,$J79,Flussi!$E:$E,$K79,Flussi!$A:$A,$D$2),"") -> -2400 | S79: =IF(AND(TRUE,S$67<>""),SUMIFS(Flussi!$F:$F,Flussi!$B:$B,S$67,Flussi!$D:$D,$J79,Flussi!$E:$E,$K79,Flussi!$A:$A,$D$2),"") -> -2400 | ... AO79: =IF(AND(TRUE,AO$67<>""),SUMIFS(Flussi!$F:$F,Flussi!$B:$B,AO$67,Flussi!$D:$D,$J79,Flussi!$E:$E,$K79,Flussi!$A:$A,$D$2),"") -> 0
J80: Condominio | K80: Straordinario | L80: =IF(AND(TRUE,L$67<>""),SUMIFS(Flussi!$F:$F,Flussi!$B:$B,L$67,Flussi!$D:$D,$J80,Flussi!$E:$E,$K80,Flussi!$A:$A,$D$2),"") -> 0 | M80: =IF(AND(TRUE,M$67<>""),SUMIFS(Flussi!$F:$F,Flussi!$B:$B,M$67,Flussi!$D:$D,$J80,Flussi!$E:$E,$K80,Flussi!$A:$A,$D$2),"") -> 0 | N80: =IF(AND(TRUE,N$67<>""),SUMIFS(Flussi!$F:$F,Flussi!$B:$B,N$67,Flussi!$D:$D,$J80,Flussi!$E:$E,$K80,Flussi!$A:$A,$D$2),"") -> 0 | O80: =IF(AND(TRUE,O$67<>""),SUMIFS(Flussi!$F:$F,Flussi!$B:$B,O$67,Flussi!$D:$D,$J80,Flussi!$E:$E,$K80,Flussi!$A:$A,$D$2),"") -> -3482.97 | P80: =IF(AND(TRUE,P$67<>""),SUMIFS(Flussi!$F:$F,Flussi!$B:$B,P$67,Flussi!$D:$D,$J80,Flussi!$E:$E,$K80,Flussi!$A:$A,$D$2),"") -> -568.05 | Q80: =IF(AND(TRUE,Q$67<>""),SUMIFS(Flussi!$F:$F,Flussi!$B:$B,Q$67,Flussi!$D:$D,$J80,Flussi!$E:$E,$K80,Flussi!$A:$A,$D$2),"") -> 0 | R80: =IF(AND(TRUE,R$67<>""),SUMIFS(Flussi!$F:$F,Flussi!$B:$B,R$67,Flussi!$D:$D,$J80,Flussi!$E:$E,$K80,Flussi!$A:$A,$D$2),"") -> 0 | S80: =IF(AND(TRUE,S$67<>""),SUMIFS(Flussi!$F:$F,Flussi!$B:$B,S$67,Flussi!$D:$D,$J80,Flussi!$E:$E,$K80,Flussi!$A:$A,$D$2),"") -> 0 | ... AO80: =IF(AND(TRUE,AO$67<>""),SUMIFS(Flussi!$F:$F,Flussi!$B:$B,AO$67,Flussi!$D:$D,$J80,Flussi!$E:$E,$K80,Flussi!$A:$A,$D$2),"") -> 0
J81: Assicurazione | K81: - | L81: =IF(AND(TRUE,L$67<>""),SUMIFS(Flussi!$F:$F,Flussi!$B:$B,L$67,Flussi!$D:$D,$J81,Flussi!$E:$E,$K81,Flussi!$A:$A,$D$2),"") -> -23.7 | M81: =IF(AND(TRUE,M$67<>""),SUMIFS(Flussi!$F:$F,Flussi!$B:$B,M$67,Flussi!$D:$D,$J81,Flussi!$E:$E,$K81,Flussi!$A:$A,$D$2),"") -> -284.4 | N81: =IF(AND(TRUE,N$67<>""),SUMIFS(Flussi!$F:$F,Flussi!$B:$B,N$67,Flussi!$D:$D,$J81,Flussi!$E:$E,$K81,Flussi!$A:$A,$D$2),"") -> -284.4 | O81: =IF(AND(TRUE,O$67<>""),SUMIFS(Flussi!$F:$F,Flussi!$B:$B,O$67,Flussi!$D:$D,$J81,Flussi!$E:$E,$K81,Flussi!$A:$A,$D$2),"") -> -284.4 | P81: =IF(AND(TRUE,P$67<>""),SUMIFS(Flussi!$F:$F,Flussi!$B:$B,P$67,Flussi!$D:$D,$J81,Flussi!$E:$E,$K81,Flussi!$A:$A,$D$2),"") -> 0 | Q81: =IF(AND(TRUE,Q$67<>""),SUMIFS(Flussi!$F:$F,Flussi!$B:$B,Q$67,Flussi!$D:$D,$J81,Flussi!$E:$E,$K81,Flussi!$A:$A,$D$2),"") -> 0 | R81: =IF(AND(TRUE,R$67<>""),SUMIFS(Flussi!$F:$F,Flussi!$B:$B,R$67,Flussi!$D:$D,$J81,Flussi!$E:$E,$K81,Flussi!$A:$A,$D$2),"") -> 0 | S81: =IF(AND(TRUE,S$67<>""),SUMIFS(Flussi!$F:$F,Flussi!$B:$B,S$67,Flussi!$D:$D,$J81,Flussi!$E:$E,$K81,Flussi!$A:$A,$D$2),"") -> 0 | ... AO81: =IF(AND(TRUE,AO$67<>""),SUMIFS(Flussi!$F:$F,Flussi!$B:$B,AO$67,Flussi!$D:$D,$J81,Flussi!$E:$E,$K81,Flussi!$A:$A,$D$2),"") -> 0
J82: Manutenzione ordinaria | K82: - | L82: =IF(AND(TRUE,L$67<>""),SUMIFS(Flussi!$F:$F,Flussi!$B:$B,L$67,Flussi!$D:$D,$J82,Flussi!$E:$E,$K82,Flussi!$A:$A,$D$2),"") -> 0 | M82: =IF(AND(TRUE,M$67<>""),SUMIFS(Flussi!$F:$F,Flussi!$B:$B,M$67,Flussi!$D:$D,$J82,Flussi!$E:$E,$K82,Flussi!$A:$A,$D$2),"") -> 253 | N82: =IF(AND(TRUE,N$67<>""),SUMIFS(Flussi!$F:$F,Flussi!$B:$B,N$67,Flussi!$D:$D,$J82,Flussi!$E:$E,$K82,Flussi!$A:$A,$D$2),"") -> 50 | O82: =IF(AND(TRUE,O$67<>""),SUMIFS(Flussi!$F:$F,Flussi!$B:$B,O$67,Flussi!$D:$D,$J82,Flussi!$E:$E,$K82,Flussi!$A:$A,$D$2),"") -> -248 | P82: =IF(AND(TRUE,P$67<>""),SUMIFS(Flussi!$F:$F,Flussi!$B:$B,P$67,Flussi!$D:$D,$J82,Flussi!$E:$E,$K82,Flussi!$A:$A,$D$2),"") -> -200 | Q82: =IF(AND(TRUE,Q$67<>""),SUMIFS(Flussi!$F:$F,Flussi!$B:$B,Q$67,Flussi!$D:$D,$J82,Flussi!$E:$E,$K82,Flussi!$A:$A,$D$2),"") -> -200 | R82: =IF(AND(TRUE,R$67<>""),SUMIFS(Flussi!$F:$F,Flussi!$B:$B,R$67,Flussi!$D:$D,$J82,Flussi!$E:$E,$K82,Flussi!$A:$A,$D$2),"") -> -200 | S82: =IF(AND(TRUE,S$67<>""),SUMIFS(Flussi!$F:$F,Flussi!$B:$B,S$67,Flussi!$D:$D,$J82,Flussi!$E:$E,$K82,Flussi!$A:$A,$D$2),"") -> -200 | ... AO82: =IF(AND(TRUE,AO$67<>""),SUMIFS(Flussi!$F:$F,Flussi!$B:$B,AO$67,Flussi!$D:$D,$J82,Flussi!$E:$E,$K82,Flussi!$A:$A,$D$2),"") -> 0
J83: Manutenzione straordinaria | K83: - | L83: =IF(AND(TRUE,L$67<>""),SUMIFS(Flussi!$F:$F,Flussi!$B:$B,L$67,Flussi!$D:$D,$J83,Flussi!$E:$E,$K83,Flussi!$A:$A,$D$2),"") -> 0 | M83: =IF(AND(TRUE,M$67<>""),SUMIFS(Flussi!$F:$F,Flussi!$B:$B,M$67,Flussi!$D:$D,$J83,Flussi!$E:$E,$K83,Flussi!$A:$A,$D$2),"") -> 0 | N83: =IF(AND(TRUE,N$67<>""),SUMIFS(Flussi!$F:$F,Flussi!$B:$B,N$67,Flussi!$D:$D,$J83,Flussi!$E:$E,$K83,Flussi!$A:$A,$D$2),"") -> 0 | O83: =IF(AND(TRUE,O$67<>""),SUMIFS(Flussi!$F:$F,Flussi!$B:$B,O$67,Flussi!$D:$D,$J83,Flussi!$E:$E,$K83,Flussi!$A:$A,$D$2),"") -> 0 | P83: =IF(AND(TRUE,P$67<>""),SUMIFS(Flussi!$F:$F,Flussi!$B:$B,P$67,Flussi!$D:$D,$J83,Flussi!$E:$E,$K83,Flussi!$A:$A,$D$2),"") -> -300 | Q83: =IF(AND(TRUE,Q$67<>""),SUMIFS(Flussi!$F:$F,Flussi!$B:$B,Q$67,Flussi!$D:$D,$J83,Flussi!$E:$E,$K83,Flussi!$A:$A,$D$2),"") -> -300 | R83: =IF(AND(TRUE,R$67<>""),SUMIFS(Flussi!$F:$F,Flussi!$B:$B,R$67,Flussi!$D:$D,$J83,Flussi!$E:$E,$K83,Flussi!$A:$A,$D$2),"") -> -300 | S83: =IF(AND(TRUE,S$67<>""),SUMIFS(Flussi!$F:$F,Flussi!$B:$B,S$67,Flussi!$D:$D,$J83,Flussi!$E:$E,$K83,Flussi!$A:$A,$D$2),"") -> -300 | ... AO83: =IF(AND(TRUE,AO$67<>""),SUMIFS(Flussi!$F:$F,Flussi!$B:$B,AO$67,Flussi!$D:$D,$J83,Flussi!$E:$E,$K83,Flussi!$A:$A,$D$2),"") -> 0
J84: Storno | K84: - | L84: =IF(AND(TRUE,L$67<>""),SUMIFS(Flussi!$F:$F,Flussi!$B:$B,L$67,Flussi!$D:$D,$J84,Flussi!$E:$E,$K84,Flussi!$A:$A,$D$2),"") -> 2000 | M84: =IF(AND(TRUE,M$67<>""),SUMIFS(Flussi!$F:$F,Flussi!$B:$B,M$67,Flussi!$D:$D,$J84,Flussi!$E:$E,$K84,Flussi!$A:$A,$D$2),"") -> 0 | N84: =IF(AND(TRUE,N$67<>""),SUMIFS(Flussi!$F:$F,Flussi!$B:$B,N$67,Flussi!$D:$D,$J84,Flussi!$E:$E,$K84,Flussi!$A:$A,$D$2),"") -> 1700 | O84: =IF(AND(TRUE,O$67<>""),SUMIFS(Flussi!$F:$F,Flussi!$B:$B,O$67,Flussi!$D:$D,$J84,Flussi!$E:$E,$K84,Flussi!$A:$A,$D$2),"") -> 3407 | P84: =IF(AND(TRUE,P$67<>""),SUMIFS(Flussi!$F:$F,Flussi!$B:$B,P$67,Flussi!$D:$D,$J84,Flussi!$E:$E,$K84,Flussi!$A:$A,$D$2),"") -> 1725 | Q84: =IF(AND(TRUE,Q$67<>""),SUMIFS(Flussi!$F:$F,Flussi!$B:$B,Q$67,Flussi!$D:$D,$J84,Flussi!$E:$E,$K84,Flussi!$A:$A,$D$2),"") -> 0 | R84: =IF(AND(TRUE,R$67<>""),SUMIFS(Flussi!$F:$F,Flussi!$B:$B,R$67,Flussi!$D:$D,$J84,Flussi!$E:$E,$K84,Flussi!$A:$A,$D$2),"") -> 0 | S84: =IF(AND(TRUE,S$67<>""),SUMIFS(Flussi!$F:$F,Flussi!$B:$B,S$67,Flussi!$D:$D,$J84,Flussi!$E:$E,$K84,Flussi!$A:$A,$D$2),"") -> 0 | ... AO84: =IF(AND(TRUE,AO$67<>""),SUMIFS(Flussi!$F:$F,Flussi!$B:$B,AO$67,Flussi!$D:$D,$J84,Flussi!$E:$E,$K84,Flussi!$A:$A,$D$2),"") -> 0
I85: Costi | K85: P&L | L85: =IF(AND(TRUE,L$67<>""),SUM(L74:L84),"") -> -11887.7 | M85: =IF(AND(TRUE,M$67<>""),SUM(M74:M84),"") -> -3213.132 | N85: =IF(AND(TRUE,N$67<>""),SUM(N74:N84),"") -> -1031.69 | O85: =IF(AND(TRUE,O$67<>""),SUM(O74:O84),"") -> -4426.53 | P85: =IF(AND(TRUE,P$67<>""),SUM(P74:P84),"") -> -2937.58 | Q85: =IF(AND(TRUE,Q$67<>""),SUM(Q74:Q84),"") -> -3714.56 | R85: =IF(AND(TRUE,R$67<>""),SUM(R74:R84),"") -> -3714.56 | S85: =IF(AND(TRUE,S$67<>""),SUM(S74:S84),"") -> -3714.56 | ... AO85: =IF(AND(TRUE,AO$67<>""),SUM(AO74:AO84),"") -> 0
I86: EBIDTA | K86: P&L | L86: =IF(AND(TRUE,L$67<>""),L73+L85,"") -> -11887.7 | M86: =IF(AND(TRUE,M$67<>""),M73+M85,"") -> 3986.868 | N86: =IF(AND(TRUE,N$67<>""),N73+N85,"") -> 9768.31 | O86: =IF(AND(TRUE,O$67<>""),O73+O85,"") -> 6373.47 | P86: =IF(AND(TRUE,P$67<>""),P73+P85,"") -> 7862.42 | Q86: =IF(AND(TRUE,Q$67<>""),Q73+Q85,"") -> 7085.44 | R86: =IF(AND(TRUE,R$67<>""),R73+R85,"") -> 7085.44 | S86: =IF(AND(TRUE,S$67<>""),S73+S85,"") -> 7085.44 | ... AO86: =IF(AND(TRUE,AO$67<>""),AO73+AO85,"") -> 665528.75
J88: Acquisto | K88: Valore immobile | L88: =IF(AND(TRUE,L$67<>""),SUMIFS(Flussi!$F:$F,Flussi!$B:$B,L$67,Flussi!$D:$D,$J88,Flussi!$E:$E,$K88,Flussi!$A:$A,$D$2),"") -> -420000 | M88: =IF(AND(TRUE,M$67<>""),SUMIFS(Flussi!$F:$F,Flussi!$B:$B,M$67,Flussi!$D:$D,$J88,Flussi!$E:$E,$K88,Flussi!$A:$A,$D$2),"") -> 0 | N88: =IF(AND(TRUE,N$67<>""),SUMIFS(Flussi!$F:$F,Flussi!$B:$B,N$67,Flussi!$D:$D,$J88,Flussi!$E:$E,$K88,Flussi!$A:$A,$D$2),"") -> 0 | O88: =IF(AND(TRUE,O$67<>""),SUMIFS(Flussi!$F:$F,Flussi!$B:$B,O$67,Flussi!$D:$D,$J88,Flussi!$E:$E,$K88,Flussi!$A:$A,$D$2),"") -> 0 | P88: =IF(AND(TRUE,P$67<>""),SUMIFS(Flussi!$F:$F,Flussi!$B:$B,P$67,Flussi!$D:$D,$J88,Flussi!$E:$E,$K88,Flussi!$A:$A,$D$2),"") -> 0 | Q88: =IF(AND(TRUE,Q$67<>""),SUMIFS(Flussi!$F:$F,Flussi!$B:$B,Q$67,Flussi!$D:$D,$J88,Flussi!$E:$E,$K88,Flussi!$A:$A,$D$2),"") -> 0 | R88: =IF(AND(TRUE,R$67<>""),SUMIFS(Flussi!$F:$F,Flussi!$B:$B,R$67,Flussi!$D:$D,$J88,Flussi!$E:$E,$K88,Flussi!$A:$A,$D$2),"") -> 0 | S88: =IF(AND(TRUE,S$67<>""),SUMIFS(Flussi!$F:$F,Flussi!$B:$B,S$67,Flussi!$D:$D,$J88,Flussi!$E:$E,$K88,Flussi!$A:$A,$D$2),"") -> 0 | ... AO88: =IF(AND(TRUE,AO$67<>""),SUMIFS(Flussi!$F:$F,Flussi!$B:$B,AO$67,Flussi!$D:$D,$J88,Flussi!$E:$E,$K88,Flussi!$A:$A,$D$2),"") -> 0
J89: Mutuo0 | K89: Importo | L89: =IF(AND(TRUE,L$67<>""),SUMIFS(Flussi!$F:$F,Flussi!$B:$B,L$67,Flussi!$D:$D,$J89,Flussi!$E:$E,$K89,Flussi!$A:$A,$D$2),"") -> 294000 | M89: =IF(AND(TRUE,M$67<>""),SUMIFS(Flussi!$F:$F,Flussi!$B:$B,M$67,Flussi!$D:$D,$J89,Flussi!$E:$E,$K89,Flussi!$A:$A,$D$2),"") -> 0 | N89: =IF(AND(TRUE,N$67<>""),SUMIFS(Flussi!$F:$F,Flussi!$B:$B,N$67,Flussi!$D:$D,$J89,Flussi!$E:$E,$K89,Flussi!$A:$A,$D$2),"") -> 0 | O89: =IF(AND(TRUE,O$67<>""),SUMIFS(Flussi!$F:$F,Flussi!$B:$B,O$67,Flussi!$D:$D,$J89,Flussi!$E:$E,$K89,Flussi!$A:$A,$D$2),"") -> 0 | P89: =IF(AND(TRUE,P$67<>""),SUMIFS(Flussi!$F:$F,Flussi!$B:$B,P$67,Flussi!$D:$D,$J89,Flussi!$E:$E,$K89,Flussi!$A:$A,$D$2),"") -> 0 | Q89: =IF(AND(TRUE,Q$67<>""),SUMIFS(Flussi!$F:$F,Flussi!$B:$B,Q$67,Flussi!$D:$D,$J89,Flussi!$E:$E,$K89,Flussi!$A:$A,$D$2),"") -> 0 | R89: =IF(AND(TRUE,R$67<>""),SUMIFS(Flussi!$F:$F,Flussi!$B:$B,R$67,Flussi!$D:$D,$J89,Flussi!$E:$E,$K89,Flussi!$A:$A,$D$2),"") -> 0 | S89: =IF(AND(TRUE,S$67<>""),SUMIFS(Flussi!$F:$F,Flussi!$B:$B,S$67,Flussi!$D:$D,$J89,Flussi!$E:$E,$K89,Flussi!$A:$A,$D$2),"") -> 0 | ... AO89: =IF(AND(TRUE,AO$67<>""),SUMIFS(Flussi!$F:$F,Flussi!$B:$B,AO$67,Flussi!$D:$D,$J89,Flussi!$E:$E,$K89,Flussi!$A:$A,$D$2),"") -> 0
J90: Mutuo0 | K90: Quota capitale | L90: =IF(AND(TRUE,L$67<>""),-SUMIFS(StrambioMutuo0!$H:$H,StrambioMutuo0!$A:$A,L$67),"") -> 0 | M90: =IF(AND(TRUE,M$67<>""),-SUMIFS(StrambioMutuo0!$H:$H,StrambioMutuo0!$A:$A,M$67),"") -> -8272.23 | N90: =IF(AND(TRUE,N$67<>""),-SUMIFS(StrambioMutuo0!$H:$H,StrambioMutuo0!$A:$A,N$67),"") -> -7185.99 | O90: =IF(AND(TRUE,O$67<>""),-SUMIFS(StrambioMutuo0!$H:$H,StrambioMutuo0!$A:$A,O$67),"") -> -696.75 | P90: =IF(AND(TRUE,P$67<>""),-SUMIFS(StrambioMutuo0!$H:$H,StrambioMutuo0!$A:$A,P$67),"") -> 0 | Q90: =IF(AND(TRUE,Q$67<>""),-SUMIFS(StrambioMutuo0!$H:$H,StrambioMutuo0!$A:$A,Q$67),"") -> 0 | R90: =IF(AND(TRUE,R$67<>""),-SUMIFS(StrambioMutuo0!$H:$H,StrambioMutuo0!$A:$A,R$67),"") -> 0 | S90: =IF(AND(TRUE,S$67<>""),-SUMIFS(StrambioMutuo0!$H:$H,StrambioMutuo0!$A:$A,S$67),"") -> 0 | ... AO90: =IF(AND(TRUE,AO$67<>""),-SUMIFS(StrambioMutuo0!$H:$H,StrambioMutuo0!$A:$A,AO$67),"") -> 0
J91: Mutuo0 | K91: Rimborso anticipato | L91: =IF(AND(TRUE,L$67<>""),-SUMIFS(StrambioMutuo0!$I:$I,StrambioMutuo0!$A:$A,L$67),"") -> 0 | M91: =IF(AND(TRUE,M$67<>""),-SUMIFS(StrambioMutuo0!$I:$I,StrambioMutuo0!$A:$A,M$67),"") -> -30000 | N91: =IF(AND(TRUE,N$67<>""),-SUMIFS(StrambioMutuo0!$I:$I,StrambioMutuo0!$A:$A,N$67),"") -> -40000 | O91: =IF(AND(TRUE,O$67<>""),-SUMIFS(StrambioMutuo0!$I:$I,StrambioMutuo0!$A:$A,O$67),"") -> -208635.71 | P91: =IF(AND(TRUE,P$67<>""),-SUMIFS(StrambioMutuo0!$I:$I,StrambioMutuo0!$A:$A,P$67),"") -> 0 | Q91: =IF(AND(TRUE,Q$67<>""),-SUMIFS(StrambioMutuo0!$I:$I,StrambioMutuo0!$A:$A,Q$67),"") -> 0 | R91: =IF(AND(TRUE,R$67<>""),-SUMIFS(StrambioMutuo0!$I:$I,StrambioMutuo0!$A:$A,R$67),"") -> 0 | S91: =IF(AND(TRUE,S$67<>""),-SUMIFS(StrambioMutuo0!$I:$I,StrambioMutuo0!$A:$A,S$67),"") -> 0 | ... AO91: =IF(AND(TRUE,AO$67<>""),-SUMIFS(StrambioMutuo0!$I:$I,StrambioMutuo0!$A:$A,AO$67),"") -> 0
J92: Mutuo1 | K92: Importo | L92: =IF(AND(TRUE,L$67<>""),SUMIFS(Flussi!$F:$F,Flussi!$B:$B,L$67,Flussi!$D:$D,$J92,Flussi!$E:$E,$K92),"") -> 0 | M92: =IF(AND(TRUE,M$67<>""),SUMIFS(Flussi!$F:$F,Flussi!$B:$B,M$67,Flussi!$D:$D,$J92,Flussi!$E:$E,$K92),"") -> 0 | N92: =IF(AND(TRUE,N$67<>""),SUMIFS(Flussi!$F:$F,Flussi!$B:$B,N$67,Flussi!$D:$D,$J92,Flussi!$E:$E,$K92),"") -> 0 | O92: =IF(AND(TRUE,O$67<>""),SUMIFS(Flussi!$F:$F,Flussi!$B:$B,O$67,Flussi!$D:$D,$J92,Flussi!$E:$E,$K92),"") -> 208635.71 | P92: =IF(AND(TRUE,P$67<>""),SUMIFS(Flussi!$F:$F,Flussi!$B:$B,P$67,Flussi!$D:$D,$J92,Flussi!$E:$E,$K92),"") -> 0 | Q92: =IF(AND(TRUE,Q$67<>""),SUMIFS(Flussi!$F:$F,Flussi!$B:$B,Q$67,Flussi!$D:$D,$J92,Flussi!$E:$E,$K92),"") -> 0 | R92: =IF(AND(TRUE,R$67<>""),SUMIFS(Flussi!$F:$F,Flussi!$B:$B,R$67,Flussi!$D:$D,$J92,Flussi!$E:$E,$K92),"") -> 0 | S92: =IF(AND(TRUE,S$67<>""),SUMIFS(Flussi!$F:$F,Flussi!$B:$B,S$67,Flussi!$D:$D,$J92,Flussi!$E:$E,$K92),"") -> 0 | ... AO92: =IF(AND(TRUE,AO$67<>""),SUMIFS(Flussi!$F:$F,Flussi!$B:$B,AO$67,Flussi!$D:$D,$J92,Flussi!$E:$E,$K92),"") -> 0
J93: Mutuo1 | K93: Quota capitale | L93: =IF(AND(TRUE,L$67<>""),-SUMIFS(StrambioMutuo1!$H:$H,StrambioMutuo1!$A:$A,L$67),"") -> 0 | M93: =IF(AND(TRUE,M$67<>""),-SUMIFS(StrambioMutuo1!$H:$H,StrambioMutuo1!$A:$A,M$67),"") -> 0 | N93: =IF(AND(TRUE,N$67<>""),-SUMIFS(StrambioMutuo1!$H:$H,StrambioMutuo1!$A:$A,N$67),"") -> 0 | O93: =IF(AND(TRUE,O$67<>""),-SUMIFS(StrambioMutuo1!$H:$H,StrambioMutuo1!$A:$A,O$67),"") -> -7288.9509 | P93: =IF(AND(TRUE,P$67<>""),-SUMIFS(StrambioMutuo1!$H:$H,StrambioMutuo1!$A:$A,P$67),"") -> -8161.3785 | Q93: =IF(AND(TRUE,Q$67<>""),-SUMIFS(StrambioMutuo1!$H:$H,StrambioMutuo1!$A:$A,Q$67),"") -> -8386.1565 | R93: =IF(AND(TRUE,R$67<>""),-SUMIFS(StrambioMutuo1!$H:$H,StrambioMutuo1!$A:$A,R$67),"") -> -8617.1252 | S93: =IF(AND(TRUE,S$67<>""),-SUMIFS(StrambioMutuo1!$H:$H,StrambioMutuo1!$A:$A,S$67),"") -> -8854.4552 | ... AO93: =IF(AND(TRUE,AO$67<>""),-SUMIFS(StrambioMutuo1!$H:$H,StrambioMutuo1!$A:$A,AO$67),"") -> 0
J94: Mutuo1 | K94: Rimborso anticipato | L94: =IF(AND(TRUE,L$67<>""),-SUMIFS(StrambioMutuo1!$I:$I,StrambioMutuo1!$A:$A,L$67),"") -> 0 | M94: =IF(AND(TRUE,M$67<>""),-SUMIFS(StrambioMutuo1!$I:$I,StrambioMutuo1!$A:$A,M$67),"") -> 0 | N94: =IF(AND(TRUE,N$67<>""),-SUMIFS(StrambioMutuo1!$I:$I,StrambioMutuo1!$A:$A,N$67),"") -> 0 | O94: =IF(AND(TRUE,O$67<>""),-SUMIFS(StrambioMutuo1!$I:$I,StrambioMutuo1!$A:$A,O$67),"") -> 0 | P94: =IF(AND(TRUE,P$67<>""),-SUMIFS(StrambioMutuo1!$I:$I,StrambioMutuo1!$A:$A,P$67),"") -> 0 | Q94: =IF(AND(TRUE,Q$67<>""),-SUMIFS(StrambioMutuo1!$I:$I,StrambioMutuo1!$A:$A,Q$67),"") -> 0 | R94: =IF(AND(TRUE,R$67<>""),-SUMIFS(StrambioMutuo1!$I:$I,StrambioMutuo1!$A:$A,R$67),"") -> 0 | S94: =IF(AND(TRUE,S$67<>""),-SUMIFS(StrambioMutuo1!$I:$I,StrambioMutuo1!$A:$A,S$67),"") -> 0 | ... AO94: =IF(AND(TRUE,AO$67<>""),-SUMIFS(StrambioMutuo1!$I:$I,StrambioMutuo1!$A:$A,AO$67),"") -> 0
I95: Equity | J95: Equity | K95: P&L | L95: =IF(AND(TRUE,L$67<>""),SUM(L88:L94),"") -> -126000 | M95: =IF(AND(TRUE,M$67<>""),SUM(M88:M94),"") -> -38272.23 | N95: =IF(AND(TRUE,N$67<>""),SUM(N88:N94),"") -> -47185.99 | O95: =IF(AND(TRUE,O$67<>""),SUM(O88:O94),"") -> -7985.7009 | P95: =IF(AND(TRUE,P$67<>""),SUM(P88:P94),"") -> -8161.3785 | Q95: =IF(AND(TRUE,Q$67<>""),SUM(Q88:Q94),"") -> -8386.1565 | R95: =IF(AND(TRUE,R$67<>""),SUM(R88:R94),"") -> -8617.1252 | S95: =IF(AND(TRUE,S$67<>""),SUM(S88:S94),"") -> -8854.4552 | ... AO95: =IF(AND(TRUE,AO$67<>""),SUM(AO88:AO94),"") -> 0
H96: =YEAR($E$4) -> 2022 | L96: =IF(AND($H96<>"",L$67<>""),IF(AND(L$67>=$H96,L$67<$H96+$D$28),SUMIFS($L$95:$AO$95,$L$67:$AO$67,$H96)/$D$28,0),"") -> -12600 | M96: =IF(AND($H96<>"",M$67<>""),IF(AND(M$67>=$H96,M$67<$H96+$D$28),SUMIFS($L$95:$AO$95,$L$67:$AO$67,$H96)/$D$28,0),"") -> -12600 | N96: =IF(AND($H96<>"",N$67<>""),IF(AND(N$67>=$H96,N$67<$H96+$D$28),SUMIFS($L$95:$AO$95,$L$67:$AO$67,$H96)/$D$28,0),"") -> -12600 | O96: =IF(AND($H96<>"",O$67<>""),IF(AND(O$67>=$H96,O$67<$H96+$D$28),SUMIFS($L$95:$AO$95,$L$67:$AO$67,$H96)/$D$28,0),"") -> -12600 | P96: =IF(AND($H96<>"",P$67<>""),IF(AND(P$67>=$H96,P$67<$H96+$D$28),SUMIFS($L$95:$AO$95,$L$67:$AO$67,$H96)/$D$28,0),"") -> -12600 | Q96: =IF(AND($H96<>"",Q$67<>""),IF(AND(Q$67>=$H96,Q$67<$H96+$D$28),SUMIFS($L$95:$AO$95,$L$67:$AO$67,$H96)/$D$28,0),"") -> -12600 | R96: =IF(AND($H96<>"",R$67<>""),IF(AND(R$67>=$H96,R$67<$H96+$D$28),SUMIFS($L$95:$AO$95,$L$67:$AO$67,$H96)/$D$28,0),"") -> -12600 | S96: =IF(AND($H96<>"",S$67<>""),IF(AND(S$67>=$H96,S$67<$H96+$D$28),SUMIFS($L$95:$AO$95,$L$67:$AO$67,$H96)/$D$28,0),"") -> -12600 | ... AO96: =IF(AND($H96<>"",AO$67<>""),IF(AND(AO$67>=$H96,AO$67<$H96+$D$28),SUMIFS($L$95:$AO$95,$L$67:$AO$67,$H96)/$D$28,0),"") -> 0
H97: =IF(H96<>"",IF(H96+1<YEAR($E$4)+$E$5,H96+1,""),"") -> 2023 | L97: =IF(AND($H97<>"",L$67<>""),IF(AND(L$67>=$H97,L$67<$H97+$D$28),SUMIFS($L$95:$AO$95,$L$67:$AO$67,$H97)/$D$28,0),"") -> 0 | M97: =IF(AND($H97<>"",M$67<>""),IF(AND(M$67>=$H97,M$67<$H97+$D$28),SUMIFS($L$95:$AO$95,$L$67:$AO$67,$H97)/$D$28,0),"") -> -3827.223 | N97: =IF(AND($H97<>"",N$67<>""),IF(AND(N$67>=$H97,N$67<$H97+$D$28),SUMIFS($L$95:$AO$95,$L$67:$AO$67,$H97)/$D$28,0),"") -> -3827.223 | O97: =IF(AND($H97<>"",O$67<>""),IF(AND(O$67>=$H97,O$67<$H97+$D$28),SUMIFS($L$95:$AO$95,$L$67:$AO$67,$H97)/$D$28,0),"") -> -3827.223 | P97: =IF(AND($H97<>"",P$67<>""),IF(AND(P$67>=$H97,P$67<$H97+$D$28),SUMIFS($L$95:$AO$95,$L$67:$AO$67,$H97)/$D$28,0),"") -> -3827.223 | Q97: =IF(AND($H97<>"",Q$67<>""),IF(AND(Q$67>=$H97,Q$67<$H97+$D$28),SUMIFS($L$95:$AO$95,$L$67:$AO$67,$H97)/$D$28,0),"") -> -3827.223 | R97: =IF(AND($H97<>"",R$67<>""),IF(AND(R$67>=$H97,R$67<$H97+$D$28),SUMIFS($L$95:$AO$95,$L$67:$AO$67,$H97)/$D$28,0),"") -> -3827.223 | S97: =IF(AND($H97<>"",S$67<>""),IF(AND(S$67>=$H97,S$67<$H97+$D$28),SUMIFS($L$95:$AO$95,$L$67:$AO$67,$H97)/$D$28,0),"") -> -3827.223 | ... AO97: =IF(AND($H97<>"",AO$67<>""),IF(AND(AO$67>=$H97,AO$67<$H97+$D$28),SUMIFS($L$95:$AO$95,$L$67:$AO$67,$H97)/$D$28,0),"") -> 0
H98: =IF(H97<>"",IF(H97+1<YEAR($E$4)+$E$5,H97+1,""),"") -> 2024 | L98: =IF(AND($H98<>"",L$67<>""),IF(AND(L$67>=$H98,L$67<$H98+$D$28),SUMIFS($L$95:$AO$95,$L$67:$AO$67,$H98)/$D$28,0),"") -> 0 | M98: =IF(AND($H98<>"",M$67<>""),IF(AND(M$67>=$H98,M$67<$H98+$D$28),SUMIFS($L$95:$AO$95,$L$67:$AO$67,$H98)/$D$28,0),"") -> 0 | N98: =IF(AND($H98<>"",N$67<>""),IF(AND(N$67>=$H98,N$67<$H98+$D$28),SUMIFS($L$95:$AO$95,$L$67:$AO$67,$H98)/$D$28,0),"") -> -4718.599 | O98: =IF(AND($H98<>"",O$67<>""),IF(AND(O$67>=$H98,O$67<$H98+$D$28),SUMIFS($L$95:$AO$95,$L$67:$AO$67,$H98)/$D$28,0),"") -> -4718.599 | P98: =IF(AND($H98<>"",P$67<>""),IF(AND(P$67>=$H98,P$67<$H98+$D$28),SUMIFS($L$95:$AO$95,$L$67:$AO$67,$H98)/$D$28,0),"") -> -4718.599 | Q98: =IF(AND($H98<>"",Q$67<>""),IF(AND(Q$67>=$H98,Q$67<$H98+$D$28),SUMIFS($L$95:$AO$95,$L$67:$AO$67,$H98)/$D$28,0),"") -> -4718.599 | R98: =IF(AND($H98<>"",R$67<>""),IF(AND(R$67>=$H98,R$67<$H98+$D$28),SUMIFS($L$95:$AO$95,$L$67:$AO$67,$H98)/$D$28,0),"") -> -4718.599 | S98: =IF(AND($H98<>"",S$67<>""),IF(AND(S$67>=$H98,S$67<$H98+$D$28),SUMIFS($L$95:$AO$95,$L$67:$AO$67,$H98)/$D$28,0),"") -> -4718.599 | ... AO98: =IF(AND($H98<>"",AO$67<>""),IF(AND(AO$67>=$H98,AO$67<$H98+$D$28),SUMIFS($L$95:$AO$95,$L$67:$AO$67,$H98)/$D$28,0),"") -> 0
H99: =IF(H98<>"",IF(H98+1<YEAR($E$4)+$E$5,H98+1,""),"") -> 2025 | L99: =IF(AND($H99<>"",L$67<>""),IF(AND(L$67>=$H99,L$67<$H99+$D$28),SUMIFS($L$95:$AO$95,$L$67:$AO$67,$H99)/$D$28,0),"") -> 0 | M99: =IF(AND($H99<>"",M$67<>""),IF(AND(M$67>=$H99,M$67<$H99+$D$28),SUMIFS($L$95:$AO$95,$L$67:$AO$67,$H99)/$D$28,0),"") -> 0 | N99: =IF(AND($H99<>"",N$67<>""),IF(AND(N$67>=$H99,N$67<$H99+$D$28),SUMIFS($L$95:$AO$95,$L$67:$AO$67,$H99)/$D$28,0),"") -> 0 | O99: =IF(AND($H99<>"",O$67<>""),IF(AND(O$67>=$H99,O$67<$H99+$D$28),SUMIFS($L$95:$AO$95,$L$67:$AO$67,$H99)/$D$28,0),"") -> -798.57009 | P99: =IF(AND($H99<>"",P$67<>""),IF(AND(P$67>=$H99,P$67<$H99+$D$28),SUMIFS($L$95:$AO$95,$L$67:$AO$67,$H99)/$D$28,0),"") -> -798.57009 | Q99: =IF(AND($H99<>"",Q$67<>""),IF(AND(Q$67>=$H99,Q$67<$H99+$D$28),SUMIFS($L$95:$AO$95,$L$67:$AO$67,$H99)/$D$28,0),"") -> -798.57009 | R99: =IF(AND($H99<>"",R$67<>""),IF(AND(R$67>=$H99,R$67<$H99+$D$28),SUMIFS($L$95:$AO$95,$L$67:$AO$67,$H99)/$D$28,0),"") -> -798.57009 | S99: =IF(AND($H99<>"",S$67<>""),IF(AND(S$67>=$H99,S$67<$H99+$D$28),SUMIFS($L$95:$AO$95,$L$67:$AO$67,$H99)/$D$28,0),"") -> -798.57009 | ... AO99: =IF(AND($H99<>"",AO$67<>""),IF(AND(AO$67>=$H99,AO$67<$H99+$D$28),SUMIFS($L$95:$AO$95,$L$67:$AO$67,$H99)/$D$28,0),"") -> 0
H100: =IF(H99<>"",IF(H99+1<YEAR($E$4)+$E$5,H99+1,""),"") -> 2026 | L100: =IF(AND($H100<>"",L$67<>""),IF(AND(L$67>=$H100,L$67<$H100+$D$28),SUMIFS($L$95:$AO$95,$L$67:$AO$67,$H100)/$D$28,0),"") -> 0 | M100: =IF(AND($H100<>"",M$67<>""),IF(AND(M$67>=$H100,M$67<$H100+$D$28),SUMIFS($L$95:$AO$95,$L$67:$AO$67,$H100)/$D$28,0),"") -> 0 | N100: =IF(AND($H100<>"",N$67<>""),IF(AND(N$67>=$H100,N$67<$H100+$D$28),SUMIFS($L$95:$AO$95,$L$67:$AO$67,$H100)/$D$28,0),"") -> 0 | O100: =IF(AND($H100<>"",O$67<>""),IF(AND(O$67>=$H100,O$67<$H100+$D$28),SUMIFS($L$95:$AO$95,$L$67:$AO$67,$H100)/$D$28,0),"") -> 0 | P100: =IF(AND($H100<>"",P$67<>""),IF(AND(P$67>=$H100,P$67<$H100+$D$28),SUMIFS($L$95:$AO$95,$L$67:$AO$67,$H100)/$D$28,0),"") -> -816.13785 | Q100: =IF(AND($H100<>"",Q$67<>""),IF(AND(Q$67>=$H100,Q$67<$H100+$D$28),SUMIFS($L$95:$AO$95,$L$67:$AO$67,$H100)/$D$28,0),"") -> -816.13785 | R100: =IF(AND($H100<>"",R$67<>""),IF(AND(R$67>=$H100,R$67<$H100+$D$28),SUMIFS($L$95:$AO$95,$L$67:$AO$67,$H100)/$D$28,0),"") -> -816.13785 | S100: =IF(AND($H100<>"",S$67<>""),IF(AND(S$67>=$H100,S$67<$H100+$D$28),SUMIFS($L$95:$AO$95,$L$67:$AO$67,$H100)/$D$28,0),"") -> -816.13785 | ... AO100: =IF(AND($H100<>"",AO$67<>""),IF(AND(AO$67>=$H100,AO$67<$H100+$D$28),SUMIFS($L$95:$AO$95,$L$67:$AO$67,$H100)/$D$28,0),"") -> 0
H101: =IF(H100<>"",IF(H100+1<YEAR($E$4)+$E$5,H100+1,""),"") -> 2027 | L101: =IF(AND($H101<>"",L$67<>""),IF(AND(L$67>=$H101,L$67<$H101+$D$28),SUMIFS($L$95:$AO$95,$L$67:$AO$67,$H101)/$D$28,0),"") -> 0 | M101: =IF(AND($H101<>"",M$67<>""),IF(AND(M$67>=$H101,M$67<$H101+$D$28),SUMIFS($L$95:$AO$95,$L$67:$AO$67,$H101)/$D$28,0),"") -> 0 | N101: =IF(AND($H101<>"",N$67<>""),IF(AND(N$67>=$H101,N$67<$H101+$D$28),SUMIFS($L$95:$AO$95,$L$67:$AO$67,$H101)/$D$28,0),"") -> 0 | O101: =IF(AND($H101<>"",O$67<>""),IF(AND(O$67>=$H101,O$67<$H101+$D$28),SUMIFS($L$95:$AO$95,$L$67:$AO$67,$H101)/$D$28,0),"") -> 0 | P101: =IF(AND($H101<>"",P$67<>""),IF(AND(P$67>=$H101,P$67<$H101+$D$28),SUMIFS($L$95:$AO$95,$L$67:$AO$67,$H101)/$D$28,0),"") -> 0 | Q101: =IF(AND($H101<>"",Q$67<>""),IF(AND(Q$67>=$H101,Q$67<$H101+$D$28),SUMIFS($L$95:$AO$95,$L$67:$AO$67,$H101)/$D$28,0),"") -> -838.61565 | R101: =IF(AND($H101<>"",R$67<>""),IF(AND(R$67>=$H101,R$67<$H101+$D$28),SUMIFS($L$95:$AO$95,$L$67:$AO$67,$H101)/$D$28,0),"") -> -838.61565 | S101: =IF(AND($H101<>"",S$67<>""),IF(AND(S$67>=$H101,S$67<$H101+$D$28),SUMIFS($L$95:$AO$95,$L$67:$AO$67,$H101)/$D$28,0),"") -> -838.61565 | ... AO101: =IF(AND($H101<>"",AO$67<>""),IF(AND(AO$67>=$H101,AO$67<$H101+$D$28),SUMIFS($L$95:$AO$95,$L$67:$AO$67,$H101)/$D$28,0),"") -> 0
H102: =IF(H101<>"",IF(H101+1<YEAR($E$4)+$E$5,H101+1,""),"") -> 2028 | L102: =IF(AND($H102<>"",L$67<>""),IF(AND(L$67>=$H102,L$67<$H102+$D$28),SUMIFS($L$95:$AO$95,$L$67:$AO$67,$H102)/$D$28,0),"") -> 0 | M102: =IF(AND($H102<>"",M$67<>""),IF(AND(M$67>=$H102,M$67<$H102+$D$28),SUMIFS($L$95:$AO$95,$L$67:$AO$67,$H102)/$D$28,0),"") -> 0 | N102: =IF(AND($H102<>"",N$67<>""),IF(AND(N$67>=$H102,N$67<$H102+$D$28),SUMIFS($L$95:$AO$95,$L$67:$AO$67,$H102)/$D$28,0),"") -> 0 | O102: =IF(AND($H102<>"",O$67<>""),IF(AND(O$67>=$H102,O$67<$H102+$D$28),SUMIFS($L$95:$AO$95,$L$67:$AO$67,$H102)/$D$28,0),"") -> 0 | P102: =IF(AND($H102<>"",P$67<>""),IF(AND(P$67>=$H102,P$67<$H102+$D$28),SUMIFS($L$95:$AO$95,$L$67:$AO$67,$H102)/$D$28,0),"") -> 0 | Q102: =IF(AND($H102<>"",Q$67<>""),IF(AND(Q$67>=$H102,Q$67<$H102+$D$28),SUMIFS($L$95:$AO$95,$L$67:$AO$67,$H102)/$D$28,0),"") -> 0 | R102: =IF(AND($H102<>"",R$67<>""),IF(AND(R$67>=$H102,R$67<$H102+$D$28),SUMIFS($L$95:$AO$95,$L$67:$AO$67,$H102)/$D$28,0),"") -> -861.71252 | S102: =IF(AND($H102<>"",S$67<>""),IF(AND(S$67>=$H102,S$67<$H102+$D$28),SUMIFS($L$95:$AO$95,$L$67:$AO$67,$H102)/$D$28,0),"") -> -861.71252 | ... AO102: =IF(AND($H102<>"",AO$67<>""),IF(AND(AO$67>=$H102,AO$67<$H102+$D$28),SUMIFS($L$95:$AO$95,$L$67:$AO$67,$H102)/$D$28,0),"") -> 0
H103: =IF(H102<>"",IF(H102+1<YEAR($E$4)+$E$5,H102+1,""),"") -> 2029 | L103: =IF(AND($H103<>"",L$67<>""),IF(AND(L$67>=$H103,L$67<$H103+$D$28),SUMIFS($L$95:$AO$95,$L$67:$AO$67,$H103)/$D$28,0),"") -> 0 | M103: =IF(AND($H103<>"",M$67<>""),IF(AND(M$67>=$H103,M$67<$H103+$D$28),SUMIFS($L$95:$AO$95,$L$67:$AO$67,$H103)/$D$28,0),"") -> 0 | N103: =IF(AND($H103<>"",N$67<>""),IF(AND(N$67>=$H103,N$67<$H103+$D$28),SUMIFS($L$95:$AO$95,$L$67:$AO$67,$H103)/$D$28,0),"") -> 0 | O103: =IF(AND($H103<>"",O$67<>""),IF(AND(O$67>=$H103,O$67<$H103+$D$28),SUMIFS($L$95:$AO$95,$L$67:$AO$67,$H103)/$D$28,0),"") -> 0 | P103: =IF(AND($H103<>"",P$67<>""),IF(AND(P$67>=$H103,P$67<$H103+$D$28),SUMIFS($L$95:$AO$95,$L$67:$AO$67,$H103)/$D$28,0),"") -> 0 | Q103: =IF(AND($H103<>"",Q$67<>""),IF(AND(Q$67>=$H103,Q$67<$H103+$D$28),SUMIFS($L$95:$AO$95,$L$67:$AO$67,$H103)/$D$28,0),"") -> 0 | R103: =IF(AND($H103<>"",R$67<>""),IF(AND(R$67>=$H103,R$67<$H103+$D$28),SUMIFS($L$95:$AO$95,$L$67:$AO$67,$H103)/$D$28,0),"") -> 0 | S103: =IF(AND($H103<>"",S$67<>""),IF(AND(S$67>=$H103,S$67<$H103+$D$28),SUMIFS($L$95:$AO$95,$L$67:$AO$67,$H103)/$D$28,0),"") -> -885.44552 | ... AO103: =IF(AND($H103<>"",AO$67<>""),IF(AND(AO$67>=$H103,AO$67<$H103+$D$28),SUMIFS($L$95:$AO$95,$L$67:$AO$67,$H103)/$D$28,0),"") -> 0
H104: =IF(H103<>"",IF(H103+1<YEAR($E$4)+$E$5,H103+1,""),"") -> 2030 | L104: =IF(AND($H104<>"",L$67<>""),IF(AND(L$67>=$H104,L$67<$H104+$D$28),SUMIFS($L$95:$AO$95,$L$67:$AO$67,$H104)/$D$28,0),"") -> 0 | M104: =IF(AND($H104<>"",M$67<>""),IF(AND(M$67>=$H104,M$67<$H104+$D$28),SUMIFS($L$95:$AO$95,$L$67:$AO$67,$H104)/$D$28,0),"") -> 0 | N104: =IF(AND($H104<>"",N$67<>""),IF(AND(N$67>=$H104,N$67<$H104+$D$28),SUMIFS($L$95:$AO$95,$L$67:$AO$67,$H104)/$D$28,0),"") -> 0 | O104: =IF(AND($H104<>"",O$67<>""),IF(AND(O$67>=$H104,O$67<$H104+$D$28),SUMIFS($L$95:$AO$95,$L$67:$AO$67,$H104)/$D$28,0),"") -> 0 | P104: =IF(AND($H104<>"",P$67<>""),IF(AND(P$67>=$H104,P$67<$H104+$D$28),SUMIFS($L$95:$AO$95,$L$67:$AO$67,$H104)/$D$28,0),"") -> 0 | Q104: =IF(AND($H104<>"",Q$67<>""),IF(AND(Q$67>=$H104,Q$67<$H104+$D$28),SUMIFS($L$95:$AO$95,$L$67:$AO$67,$H104)/$D$28,0),"") -> 0 | R104: =IF(AND($H104<>"",R$67<>""),IF(AND(R$67>=$H104,R$67<$H104+$D$28),SUMIFS($L$95:$AO$95,$L$67:$AO$67,$H104)/$D$28,0),"") -> 0 | S104: =IF(AND($H104<>"",S$67<>""),IF(AND(S$67>=$H104,S$67<$H104+$D$28),SUMIFS($L$95:$AO$95,$L$67:$AO$67,$H104)/$D$28,0),"") -> 0 | ... AO104: =IF(AND($H104<>"",AO$67<>""),IF(AND(AO$67>=$H104,AO$67<$H104+$D$28),SUMIFS($L$95:$AO$95,$L$67:$AO$67,$H104)/$D$28,0),"") -> 0
H105: =IF(H104<>"",IF(H104+1<YEAR($E$4)+$E$5,H104+1,""),"") -> 2031 | L105: =IF(AND($H105<>"",L$67<>""),IF(AND(L$67>=$H105,L$67<$H105+$D$28),SUMIFS($L$95:$AO$95,$L$67:$AO$67,$H105)/$D$28,0),"") -> 0 | M105: =IF(AND($H105<>"",M$67<>""),IF(AND(M$67>=$H105,M$67<$H105+$D$28),SUMIFS($L$95:$AO$95,$L$67:$AO$67,$H105)/$D$28,0),"") -> 0 | N105: =IF(AND($H105<>"",N$67<>""),IF(AND(N$67>=$H105,N$67<$H105+$D$28),SUMIFS($L$95:$AO$95,$L$67:$AO$67,$H105)/$D$28,0),"") -> 0 | O105: =IF(AND($H105<>"",O$67<>""),IF(AND(O$67>=$H105,O$67<$H105+$D$28),SUMIFS($L$95:$AO$95,$L$67:$AO$67,$H105)/$D$28,0),"") -> 0 | P105: =IF(AND($H105<>"",P$67<>""),IF(AND(P$67>=$H105,P$67<$H105+$D$28),SUMIFS($L$95:$AO$95,$L$67:$AO$67,$H105)/$D$28,0),"") -> 0 | Q105: =IF(AND($H105<>"",Q$67<>""),IF(AND(Q$67>=$H105,Q$67<$H105+$D$28),SUMIFS($L$95:$AO$95,$L$67:$AO$67,$H105)/$D$28,0),"") -> 0 | R105: =IF(AND($H105<>"",R$67<>""),IF(AND(R$67>=$H105,R$67<$H105+$D$28),SUMIFS($L$95:$AO$95,$L$67:$AO$67,$H105)/$D$28,0),"") -> 0 | S105: =IF(AND($H105<>"",S$67<>""),IF(AND(S$67>=$H105,S$67<$H105+$D$28),SUMIFS($L$95:$AO$95,$L$67:$AO$67,$H105)/$D$28,0),"") -> 0 | ... AO105: =IF(AND($H105<>"",AO$67<>""),IF(AND(AO$67>=$H105,AO$67<$H105+$D$28),SUMIFS($L$95:$AO$95,$L$67:$AO$67,$H105)/$D$28,0),"") -> 0
H106: =IF(H105<>"",IF(H105+1<YEAR($E$4)+$E$5,H105+1,""),"") -> 2032 | L106: =IF(AND($H106<>"",L$67<>""),IF(AND(L$67>=$H106,L$67<$H106+$D$28),SUMIFS($L$95:$AO$95,$L$67:$AO$67,$H106)/$D$28,0),"") -> 0 | M106: =IF(AND($H106<>"",M$67<>""),IF(AND(M$67>=$H106,M$67<$H106+$D$28),SUMIFS($L$95:$AO$95,$L$67:$AO$67,$H106)/$D$28,0),"") -> 0 | N106: =IF(AND($H106<>"",N$67<>""),IF(AND(N$67>=$H106,N$67<$H106+$D$28),SUMIFS($L$95:$AO$95,$L$67:$AO$67,$H106)/$D$28,0),"") -> 0 | O106: =IF(AND($H106<>"",O$67<>""),IF(AND(O$67>=$H106,O$67<$H106+$D$28),SUMIFS($L$95:$AO$95,$L$67:$AO$67,$H106)/$D$28,0),"") -> 0 | P106: =IF(AND($H106<>"",P$67<>""),IF(AND(P$67>=$H106,P$67<$H106+$D$28),SUMIFS($L$95:$AO$95,$L$67:$AO$67,$H106)/$D$28,0),"") -> 0 | Q106: =IF(AND($H106<>"",Q$67<>""),IF(AND(Q$67>=$H106,Q$67<$H106+$D$28),SUMIFS($L$95:$AO$95,$L$67:$AO$67,$H106)/$D$28,0),"") -> 0 | R106: =IF(AND($H106<>"",R$67<>""),IF(AND(R$67>=$H106,R$67<$H106+$D$28),SUMIFS($L$95:$AO$95,$L$67:$AO$67,$H106)/$D$28,0),"") -> 0 | S106: =IF(AND($H106<>"",S$67<>""),IF(AND(S$67>=$H106,S$67<$H106+$D$28),SUMIFS($L$95:$AO$95,$L$67:$AO$67,$H106)/$D$28,0),"") -> 0 | ... AO106: =IF(AND($H106<>"",AO$67<>""),IF(AND(AO$67>=$H106,AO$67<$H106+$D$28),SUMIFS($L$95:$AO$95,$L$67:$AO$67,$H106)/$D$28,0),"") -> 0
H107: =IF(H106<>"",IF(H106+1<YEAR($E$4)+$E$5,H106+1,""),"") -> 2033 | L107: =IF(AND($H107<>"",L$67<>""),IF(AND(L$67>=$H107,L$67<$H107+$D$28),SUMIFS($L$95:$AO$95,$L$67:$AO$67,$H107)/$D$28,0),"") -> 0 | M107: =IF(AND($H107<>"",M$67<>""),IF(AND(M$67>=$H107,M$67<$H107+$D$28),SUMIFS($L$95:$AO$95,$L$67:$AO$67,$H107)/$D$28,0),"") -> 0 | N107: =IF(AND($H107<>"",N$67<>""),IF(AND(N$67>=$H107,N$67<$H107+$D$28),SUMIFS($L$95:$AO$95,$L$67:$AO$67,$H107)/$D$28,0),"") -> 0 | O107: =IF(AND($H107<>"",O$67<>""),IF(AND(O$67>=$H107,O$67<$H107+$D$28),SUMIFS($L$95:$AO$95,$L$67:$AO$67,$H107)/$D$28,0),"") -> 0 | P107: =IF(AND($H107<>"",P$67<>""),IF(AND(P$67>=$H107,P$67<$H107+$D$28),SUMIFS($L$95:$AO$95,$L$67:$AO$67,$H107)/$D$28,0),"") -> 0 | Q107: =IF(AND($H107<>"",Q$67<>""),IF(AND(Q$67>=$H107,Q$67<$H107+$D$28),SUMIFS($L$95:$AO$95,$L$67:$AO$67,$H107)/$D$28,0),"") -> 0 | R107: =IF(AND($H107<>"",R$67<>""),IF(AND(R$67>=$H107,R$67<$H107+$D$28),SUMIFS($L$95:$AO$95,$L$67:$AO$67,$H107)/$D$28,0),"") -> 0 | S107: =IF(AND($H107<>"",S$67<>""),IF(AND(S$67>=$H107,S$67<$H107+$D$28),SUMIFS($L$95:$AO$95,$L$67:$AO$67,$H107)/$D$28,0),"") -> 0 | ... AO107: =IF(AND($H107<>"",AO$67<>""),IF(AND(AO$67>=$H107,AO$67<$H107+$D$28),SUMIFS($L$95:$AO$95,$L$67:$AO$67,$H107)/$D$28,0),"") -> 0
H108: =IF(H107<>"",IF(H107+1<YEAR($E$4)+$E$5,H107+1,""),"") -> 2034 | L108: =IF(AND($H108<>"",L$67<>""),IF(AND(L$67>=$H108,L$67<$H108+$D$28),SUMIFS($L$95:$AO$95,$L$67:$AO$67,$H108)/$D$28,0),"") -> 0 | M108: =IF(AND($H108<>"",M$67<>""),IF(AND(M$67>=$H108,M$67<$H108+$D$28),SUMIFS($L$95:$AO$95,$L$67:$AO$67,$H108)/$D$28,0),"") -> 0 | N108: =IF(AND($H108<>"",N$67<>""),IF(AND(N$67>=$H108,N$67<$H108+$D$28),SUMIFS($L$95:$AO$95,$L$67:$AO$67,$H108)/$D$28,0),"") -> 0 | O108: =IF(AND($H108<>"",O$67<>""),IF(AND(O$67>=$H108,O$67<$H108+$D$28),SUMIFS($L$95:$AO$95,$L$67:$AO$67,$H108)/$D$28,0),"") -> 0 | P108: =IF(AND($H108<>"",P$67<>""),IF(AND(P$67>=$H108,P$67<$H108+$D$28),SUMIFS($L$95:$AO$95,$L$67:$AO$67,$H108)/$D$28,0),"") -> 0 | Q108: =IF(AND($H108<>"",Q$67<>""),IF(AND(Q$67>=$H108,Q$67<$H108+$D$28),SUMIFS($L$95:$AO$95,$L$67:$AO$67,$H108)/$D$28,0),"") -> 0 | R108: =IF(AND($H108<>"",R$67<>""),IF(AND(R$67>=$H108,R$67<$H108+$D$28),SUMIFS($L$95:$AO$95,$L$67:$AO$67,$H108)/$D$28,0),"") -> 0 | S108: =IF(AND($H108<>"",S$67<>""),IF(AND(S$67>=$H108,S$67<$H108+$D$28),SUMIFS($L$95:$AO$95,$L$67:$AO$67,$H108)/$D$28,0),"") -> 0 | ... AO108: =IF(AND($H108<>"",AO$67<>""),IF(AND(AO$67>=$H108,AO$67<$H108+$D$28),SUMIFS($L$95:$AO$95,$L$67:$AO$67,$H108)/$D$28,0),"") -> 0
... H125: =IF(H124<>"",IF(H124+1<YEAR($E$4)+$E$5,H124+1,""),"") | L125: =IF(AND($H125<>"",L$67<>""),IF(AND(L$67>=$H125,L$67<$H125+$D$28),SUMIFS($L$95:$AO$95,$L$67:$AO$67,$H125)/$D$28,0),"") | M125: =IF(AND($H125<>"",M$67<>""),IF(AND(M$67>=$H125,M$67<$H125+$D$28),SUMIFS($L$95:$AO$95,$L$67:$AO$67,$H125)/$D$28,0),"") | N125: =IF(AND($H125<>"",N$67<>""),IF(AND(N$67>=$H125,N$67<$H125+$D$28),SUMIFS($L$95:$AO$95,$L$67:$AO$67,$H125)/$D$28,0),"") | O125: =IF(AND($H125<>"",O$67<>""),IF(AND(O$67>=$H125,O$67<$H125+$D$28),SUMIFS($L$95:$AO$95,$L$67:$AO$67,$H125)/$D$28,0),"") | P125: =IF(AND($H125<>"",P$67<>""),IF(AND(P$67>=$H125,P$67<$H125+$D$28),SUMIFS($L$95:$AO$95,$L$67:$AO$67,$H125)/$D$28,0),"") | Q125: =IF(AND($H125<>"",Q$67<>""),IF(AND(Q$67>=$H125,Q$67<$H125+$D$28),SUMIFS($L$95:$AO$95,$L$67:$AO$67,$H125)/$D$28,0),"") | R125: =IF(AND($H125<>"",R$67<>""),IF(AND(R$67>=$H125,R$67<$H125+$D$28),SUMIFS($L$95:$AO$95,$L$67:$AO$67,$H125)/$D$28,0),"") | S125: =IF(AND($H125<>"",S$67<>""),IF(AND(S$67>=$H125,S$67<$H125+$D$28),SUMIFS($L$95:$AO$95,$L$67:$AO$67,$H125)/$D$28,0),"") | ... AO125: =IF(AND($H125<>"",AO$67<>""),IF(AND(AO$67>=$H125,AO$67<$H125+$D$28),SUMIFS($L$95:$AO$95,$L$67:$AO$67,$H125)/$D$28,0),"")
J126: Ristrutturazione | K126: - | L126: =IF(AND(TRUE,L$67<>""),SUMIFS(Flussi!$F:$F,Flussi!$B:$B,L$67,Flussi!$D:$D,$J126,Flussi!$E:$E,$K126,Flussi!$A:$A,$D$2),"") -> -4882 | M126: =IF(AND(TRUE,M$67<>""),SUMIFS(Flussi!$F:$F,Flussi!$B:$B,M$67,Flussi!$D:$D,$J126,Flussi!$E:$E,$K126,Flussi!$A:$A,$D$2),"") -> -21629.17 | N126: =IF(AND(TRUE,N$67<>""),SUMIFS(Flussi!$F:$F,Flussi!$B:$B,N$67,Flussi!$D:$D,$J126,Flussi!$E:$E,$K126,Flussi!$A:$A,$D$2),"") -> -3135 | O126: =IF(AND(TRUE,O$67<>""),SUMIFS(Flussi!$F:$F,Flussi!$B:$B,O$67,Flussi!$D:$D,$J126,Flussi!$E:$E,$K126,Flussi!$A:$A,$D$2),"") -> 0 | P126: =IF(AND(TRUE,P$67<>""),SUMIFS(Flussi!$F:$F,Flussi!$B:$B,P$67,Flussi!$D:$D,$J126,Flussi!$E:$E,$K126,Flussi!$A:$A,$D$2),"") -> -4500 | Q126: =IF(AND(TRUE,Q$67<>""),SUMIFS(Flussi!$F:$F,Flussi!$B:$B,Q$67,Flussi!$D:$D,$J126,Flussi!$E:$E,$K126,Flussi!$A:$A,$D$2),"") -> -1500 | R126: =IF(AND(TRUE,R$67<>""),SUMIFS(Flussi!$F:$F,Flussi!$B:$B,R$67,Flussi!$D:$D,$J126,Flussi!$E:$E,$K126,Flussi!$A:$A,$D$2),"") -> 0 | S126: =IF(AND(TRUE,S$67<>""),SUMIFS(Flussi!$F:$F,Flussi!$B:$B,S$67,Flussi!$D:$D,$J126,Flussi!$E:$E,$K126,Flussi!$A:$A,$D$2),"") -> 0 | ... AO126: =IF(AND(TRUE,AO$67<>""),SUMIFS(Flussi!$F:$F,Flussi!$B:$B,AO$67,Flussi!$D:$D,$J126,Flussi!$E:$E,$K126,Flussi!$A:$A,$D$2),"") -> 0
H127: =YEAR($E$4) -> 2022 | L127: =IF(AND($H127<>"",L$67<>""),IF(AND(L$67>=$H127,L$67<$H127+$D$28),SUMIFS($L$126:$AO$126,$L$67:$AO$67,$H127)/$D$28,0),"") -> -488.2 | M127: =IF(AND($H127<>"",M$67<>""),IF(AND(M$67>=$H127,M$67<$H127+$D$28),SUMIFS($L$126:$AO$126,$L$67:$AO$67,$H127)/$D$28,0),"") -> -488.2 | N127: =IF(AND($H127<>"",N$67<>""),IF(AND(N$67>=$H127,N$67<$H127+$D$28),SUMIFS($L$126:$AO$126,$L$67:$AO$67,$H127)/$D$28,0),"") -> -488.2 | O127: =IF(AND($H127<>"",O$67<>""),IF(AND(O$67>=$H127,O$67<$H127+$D$28),SUMIFS($L$126:$AO$126,$L$67:$AO$67,$H127)/$D$28,0),"") -> -488.2 | P127: =IF(AND($H127<>"",P$67<>""),IF(AND(P$67>=$H127,P$67<$H127+$D$28),SUMIFS($L$126:$AO$126,$L$67:$AO$67,$H127)/$D$28,0),"") -> -488.2 | Q127: =IF(AND($H127<>"",Q$67<>""),IF(AND(Q$67>=$H127,Q$67<$H127+$D$28),SUMIFS($L$126:$AO$126,$L$67:$AO$67,$H127)/$D$28,0),"") -> -488.2 | R127: =IF(AND($H127<>"",R$67<>""),IF(AND(R$67>=$H127,R$67<$H127+$D$28),SUMIFS($L$126:$AO$126,$L$67:$AO$67,$H127)/$D$28,0),"") -> -488.2 | S127: =IF(AND($H127<>"",S$67<>""),IF(AND(S$67>=$H127,S$67<$H127+$D$28),SUMIFS($L$126:$AO$126,$L$67:$AO$67,$H127)/$D$28,0),"") -> -488.2 | ... AO127: =IF(AND($H127<>"",AO$67<>""),IF(AND(AO$67>=$H127,AO$67<$H127+$D$28),SUMIFS($L$126:$AO$126,$L$67:$AO$67,$H127)/$D$28,0),"") -> 0
...

Sheet Liberazione
B1: Dati generali
B2: Asset | D2: Liberazione
B3: Acquisto | C3: Valore immobile | D3: =-215000 -> -215000 | E3: 45036 | F3: =EDATE(E3,($E$5)*12)-1 -> 55262
B4: Data acquisto | E4: 45036 | F4: =EDATE(E4,($E$5)*12)-1 -> 55262 | I4: IRR | J4: =$L$295 -> 0.054560219
B5: Anni investimento | E5: 28 | I5: NPV | J5: =MAX(293:293) -> 26054.394
B6: Acquisto da? | E6: Privato/Imprese
B7: Prima casa? | E7: NO
B8: Rendita catastale | C8: - | D8: =568.1+47.41+13.74 -> 629.25 | E8: =$E$4 -> 45036 | F8: =EDATE(E8,$E$5*12)-1 -> 55262
B9: Rivalutazione | C9: - | D9: 0 | E9: =E4 -> 45036 | F9: 45291
B10: Rivalutazione | C10: - | D10: 0.008 | E10: =F9+1 -> 45292 | F10: =F4 -> 55262
B12: Ricavi
B13: Affitto | C13: Alloggio | D13: =(900*12*(1-21%)+1100) -> 9632 | E13: 45036 | F13: 45809
B14: Affitto | C14: Alloggio | D14: =(900*12*(1-21%)+1700) -> 10232 | E14: 45839 | F14: 55262
B15: Affitto | C15: Box | D15: =25*12+120*12*0.57-67-16 -> 1037.8 | E15: 45036 | F15: 55262
B16: Vendita | C16: Alloggio | D16: 240000 | E16: 46356 | F16: 46356
B17: Vendita | C17: Box | D17: 0 | E17: 46356 | F17: 46356
B19: Costi
B20: Avviamento | C20: - | D20: 0 | E20: =$E$4 -> 45036 | F20: =EDATE(E20,$E$5*12)-1 -> 55262
B21: Condominio | C21: Ordinario | D21: =-1700 -> -1700 | E21: =$E$4 -> 45036 | F21: =EDATE(E21,$E$5*12)-1 -> 55262
B22: Condominio | C22: Straordinario | D22: -2500 | E22: 46023 | F22: 46388
B23: Assicurazione | C23: - | D23: =(-39.21+23.7)*12 -> -186.12 | E23: =$E$4 -> 45036 | F23: 46053
B24: Utenze | C24: Gas | D24: 0 | E24: =$E$4 -> 45036 | F24: =EDATE(E24,$E$5*12)-1 -> 55262
B25: Utenze | C25: Luce | D25: 0 | E25: =$E$4 -> 45036 | F25: =EDATE(E25,$E$5*12)-1 -> 55262
B26: Utenze | C26: Internet | D26: 0 | E26: =$E$4 -> 45036 | F26: =EDATE(E26,$E$5*12)-1 -> 55262
B27: Manutenzione ordinaria | C27: - | D27: 0 | E27: =$E$4 -> 45036 | F27: =EDATE(E27,$E$5*12)-1 -> 55262
B28: Manutenzione straordinaria | C28: - | D28: -500 | E28: =$E$4 -> 45036 | F28: =EDATE(E28,$E$5*12)-1 -> 55262
B30: Ammortamenti
B31: Anni | D31: 10
B33: Oneri finanziari - Mutuo
B35: Tasse
B36: Imposte | C36: Registro | D36: =-IF($E$7="SI",MAX(2%*$D$8*105%*120,1000),MAX(9%*$D$8*105%*120,1000)) -> -7135.695 | E36: =$E$4 -> 45036 | F36: =EDATE(E36,$E$5*12)-1 -> 55262
B37: Imposte | C37: Ipotecaria | D37: =-IF($E$6="Privato/Imprese",50,200) -> -50 | E37: =$E$4 -> 45036 | F37: =EDATE(E37,$E$5*12)-1 -> 55262
B38: Imposte | C38: Catastale | D38: =-IF($E$6="Privato/Imprese",50,200) -> -50 | E38: =$E$4 -> 45036 | F38: =EDATE(E38,$E$5*12)-1 -> 55262
B39: Imposte | C39: IMU | D39: =IF($E$7="522,91SI",0,$D$8*1.05*160*1.06%) -> 1120.5684 | E39: =$E$4 -> 45036 | F39: =EDATE(E39,$E$5*12)-1 -> 55262
B40: Imposte | C40: TARI | D40: -80 | E40: =$E$4 -> 45036 | F40: =EDATE(E40,$E$5*12)-1 -> 55262
B42: Detrazioni
B43: Mutuo | C43: Cap detrazione | D43: =4000*$D$34/296000 -> 0 | E43: Ripartizione mutuo
B44: Mutuo | C44: % detrazione | D44: 0.19
B45: Intermediazione | C45: Cap detrazione | D45: 1000
B46: Intermediazione | C46: % detrazione | D46: 0.19
B47: Ristrutturazione | C47: Cap detrazione | D47: 96000
B48: Ristrutturazione | C48: % detrazione | D48: 0.5
B49: Arredamento | C49: Cap detrazione | D49: 8000
B50: Arredamento | C50: % detrazione | D50: 0.5
B51: Offset detrazioni | D51: 1
I64: Profit & Loss
I66: Tipo | J66: Servizio | K66: Voce | L66: =YEAR($E$4) -> 2023 | M66: =IF(L66<>"",IF(L66+1<=YEAR($E$4)+$E$5+$D$51,L66+1,""),"") -> 2024 | N66: =IF(M66<>"",IF(M66+1<=YEAR($E$4)+$E$5+$D$51,M66+1,""),"") -> 2025 | O66: =IF(N66<>"",IF(N66+1<=YEAR($E$4)+$E$5+$D$51,N66+1,""),"") -> 2026 | P66: =IF(O66<>"",IF(O66+1<=YEAR($E$4)+$E$5+$D$51,O66+1,""),"") -> 2027 | Q66: =IF(P66<>"",IF(P66+1<=YEAR($E$4)+$E$5+$D$51,P66+1,""),"") -> 2028 | R66: =IF(Q66<>"",IF(Q66+1<=YEAR($E$4)+$E$5+$D$51,Q66+1,""),"") -> 2029 | S66: =IF(R66<>"",IF(R66+1<=YEAR($E$4)+$E$5+$D$51,R66+1,""),"") -> 2030 | T66: =IF(S66<>"",IF(S66+1<=YEAR($E$4)+$E$5+$D$51,S66+1,""),"") -> 2031 | ... AO66: =IF(AN66<>"",IF(AN66+1<=YEAR($E$4)+$E$5+$D$51,AN66+1,""),"") -> 2052
J68: Affitto | K68: Alloggio | L68: =IF(AND(TRUE,L$66<>""),SUMIFS(Flussi!$F:$F,Flussi!$B:$B,L$66,Flussi!$D:$D,$J68,Flussi!$E:$E,$K68,Flussi!$A:$A,$D$2),"") -> 1806 | M68: =IF(AND(TRUE,M$66<>""),SUMIFS(Flussi!$F:$F,Flussi!$B:$B,M$66,Flussi!$D:$D,$J68,Flussi!$E:$E,$K68,Flussi!$A:$A,$D$2),"") -> 9632 | N68: =IF(AND(TRUE,N$66<>""),SUMIFS(Flussi!$F:$F,Flussi!$B:$B,N$66,Flussi!$D:$D,$J68,Flussi!$E:$E,$K68,Flussi!$A:$A,$D$2),"") -> 9632 | O68: =IF(AND(TRUE,O$66<>""),SUMIFS(Flussi!$F:$F,Flussi!$B:$B,O$66,Flussi!$D:$D,$J68,Flussi!$E:$E,$K68,Flussi!$A:$A,$D$2),"") -> 6382.5 | P68: =IF(AND(TRUE,P$66<>""),SUMIFS(Flussi!$F:$F,Flussi!$B:$B,P$66,Flussi!$D:$D,$J68,Flussi!$E:$E,$K68,Flussi!$A:$A,$D$2),"") -> 0 | Q68: =IF(AND(TRUE,Q$66<>""),SUMIFS(Flussi!$F:$F,Flussi!$B:$B,Q$66,Flussi!$D:$D,$J68,Flussi!$E:$E,$K68,Flussi!$A:$A,$D$2),"") -> 0 | R68: =IF(AND(TRUE,R$66<>""),SUMIFS(Flussi!$F:$F,Flussi!$B:$B,R$66,Flussi!$D:$D,$J68,Flussi!$E:$E,$K68,Flussi!$A:$A,$D$2),"") -> 0 | S68: =IF(AND(TRUE,S$66<>""),SUMIFS(Flussi!$F:$F,Flussi!$B:$B,S$66,Flussi!$D:$D,$J68,Flussi!$E:$E,$K68,Flussi!$A:$A,$D$2),"") -> 0 | ... AO68: =IF(AND(TRUE,AO$66<>""),SUMIFS(Flussi!$F:$F,Flussi!$B:$B,AO$66,Flussi!$D:$D,$J68,Flussi!$E:$E,$K68,Flussi!$A:$A,$D$2),"") -> 0
J69: Affitto | K69: Box | L69: =IF(AND(TRUE,L$66<>""),SUMIFS(Flussi!$F:$F,Flussi!$B:$B,L$66,Flussi!$D:$D,$J69,Flussi!$E:$E,$K69,Flussi!$A:$A,$D$2),"") -> 0 | M69: =IF(AND(TRUE,M$66<>""),SUMIFS(Flussi!$F:$F,Flussi!$B:$B,M$66,Flussi!$D:$D,$J69,Flussi!$E:$E,$K69,Flussi!$A:$A,$D$2),"") -> 849.4 | N69: =IF(AND(TRUE,N$66<>""),SUMIFS(Flussi!$F:$F,Flussi!$B:$B,N$66,Flussi!$D:$D,$J69,Flussi!$E:$E,$K69,Flussi!$A:$A,$D$2),"") -> 1037.8 | O69: =IF(AND(TRUE,O$66<>""),SUMIFS(Flussi!$F:$F,Flussi!$B:$B,O$66,Flussi!$D:$D,$J69,Flussi!$E:$E,$K69,Flussi!$A:$A,$D$2),"") -> 653.8 | P69: =IF(AND(TRUE,P$66<>""),SUMIFS(Flussi!$F:$F,Flussi!$B:$B,P$66,Flussi!$D:$D,$J69,Flussi!$E:$E,$K69,Flussi!$A:$A,$D$2),"") -> 0 | Q69: =IF(AND(TRUE,Q$66<>""),SUMIFS(Flussi!$F:$F,Flussi!$B:$B,Q$66,Flussi!$D:$D,$J69,Flussi!$E:$E,$K69,Flussi!$A:$A,$D$2),"") -> 0 | R69: =IF(AND(TRUE,R$66<>""),SUMIFS(Flussi!$F:$F,Flussi!$B:$B,R$66,Flussi!$D:$D,$J69,Flussi!$E:$E,$K69,Flussi!$A:$A,$D$2),"") -> 0 | S69: =IF(AND(TRUE,S$66<>""),SUMIFS(Flussi!$F:$F,Flussi!$B:$B,S$66,Flussi!$D:$D,$J69,Flussi!$E:$E,$K69,Flussi!$A:$A,$D$2),"") -> 0 | ... AO69: =IF(AND(TRUE,AO$66<>""),SUMIFS(Flussi!$F:$F,Flussi!$B:$B,AO$66,Flussi!$D:$D,$J69,Flussi!$E:$E,$K69,Flussi!$A:$A,$D$2),"") -> 0
J70: Vendita | K70: Alloggio | L70: =IF(AND(TRUE,L$66<>""),SUMIFS(Flussi!$F:$F,Flussi!$B:$B,L$66,Flussi!$D:$D,$J70,Flussi!$E:$E,$K70,Flussi!$A:$A,$D$2),"") -> 0 | M70: =IF(AND(TRUE,M$66<>""),SUMIFS(Flussi!$F:$F,Flussi!$B:$B,M$66,Flussi!$D:$D,$J70,Flussi!$E:$E,$K70,Flussi!$A:$A,$D$2),"") -> 0 | N70: =IF(AND(TRUE,N$66<>""),SUMIFS(Flussi!$F:$F,Flussi!$B:$B,N$66,Flussi!$D:$D,$J70,Flussi!$E:$E,$K70,Flussi!$A:$A,$D$2),"") -> 0 | O70: =IF(AND(TRUE,O$66<>""),SUMIFS(Flussi!$F:$F,Flussi!$B:$B,O$66,Flussi!$D:$D,$J70,Flussi!$E:$E,$K70,Flussi!$A:$A,$D$2),"") -> 237072 | P70: =IF(AND(TRUE,P$66<>""),SUMIFS(Flussi!$F:$F,Flussi!$B:$B,P$66,Flussi!$D:$D,$J70,Flussi!$E:$E,$K70,Flussi!$A:$A,$D$2),"") -> 0 | Q70: =IF(AND(TRUE,Q$66<>""),SUMIFS(Flussi!$F:$F,Flussi!$B:$B,Q$66,Flussi!$D:$D,$J70,Flussi!$E:$E,$K70,Flussi!$A:$A,$D$2),"") -> 0 | R70: =IF(AND(TRUE,R$66<>""),SUMIFS(Flussi!$F:$F,Flussi!$B:$B,R$66,Flussi!$D:$D,$J70,Flussi!$E:$E,$K70,Flussi!$A:$A,$D$2),"") -> 0 | S70: =IF(AND(TRUE,S$66<>""),SUMIFS(Flussi!$F:$F,Flussi!$B:$B,S$66,Flussi!$D:$D,$J70,Flussi!$E:$E,$K70,Flussi!$A:$A,$D$2),"") -> 0 | ... AO70: =IF(AND(TRUE,AO$66<>""),SUMIFS(Flussi!$F:$F,Flussi!$B:$B,AO$66,Flussi!$D:$D,$J70,Flussi!$E:$E,$K70,Flussi!$A:$A,$D$2),"") -> 0
J71: Vendita | K71: Box | L71: =IF(AND(TRUE,L$66<>""),SUMIFS(Flussi!$F:$F,Flussi!$B:$B,L$66,Flussi!$D:$D,$J71,Flussi!$E:$E,$K71,Flussi!$A:$A,$D$2),"") -> 0 | M71: =IF(AND(TRUE,M$66<>""),SUMIFS(Flussi!$F:$F,Flussi!$B:$B,M$66,Flussi!$D:$D,$J71,Flussi!$E:$E,$K71,Flussi!$A:$A,$D$2),"") -> 0 | N71: =IF(AND(TRUE,N$66<>""),SUMIFS(Flussi!$F:$F,Flussi!$B:$B,N$66,Flussi!$D:$D,$J71,Flussi!$E:$E,$K71,Flussi!$A:$A,$D$2),"") -> 0 | O71: =IF(AND(TRUE,O$66<>""),SUMIFS(Flussi!$F:$F,Flussi!$B:$B,O$66,Flussi!$D:$D,$J71,Flussi!$E:$E,$K71,Flussi!$A:$A,$D$2),"") -> 0 | P71: =IF(AND(TRUE,P$66<>""),SUMIFS(Flussi!$F:$F,Flussi!$B:$B,P$66,Flussi!$D:$D,$J71,Flussi!$E:$E,$K71,Flussi!$A:$A,$D$2),"") -> 0 | Q71: =IF(AND(TRUE,Q$66<>""),SUMIFS(Flussi!$F:$F,Flussi!$B:$B,Q$66,Flussi!$D:$D,$J71,Flussi!$E:$E,$K71,Flussi!$A:$A,$D$2),"") -> 0 | R71: =IF(AND(TRUE,R$66<>""),SUMIFS(Flussi!$F:$F,Flussi!$B:$B,R$66,Flussi!$D:$D,$J71,Flussi!$E:$E,$K71,Flussi!$A:$A,$D$2),"") -> 0 | S71: =IF(AND(TRUE,S$66<>""),SUMIFS(Flussi!$F:$F,Flussi!$B:$B,S$66,Flussi!$D:$D,$J71,Flussi!$E:$E,$K71,Flussi!$A:$A,$D$2),"") -> 0 | ... AO71: =IF(AND(TRUE,AO$66<>""),SUMIFS(Flussi!$F:$F,Flussi!$B:$B,AO$66,Flussi!$D:$D,$J71,Flussi!$E:$E,$K71,Flussi!$A:$A,$D$2),"") -> 0
I72: Ricavi | K72: P&L | L72: =IF(AND(TRUE,L$66<>""),SUM(L68:L71),"") -> 1806 | M72: =IF(AND(TRUE,M$66<>""),SUM(M68:M71),"") -> 10481.4 | N72: =IF(AND(TRUE,N$66<>""),SUM(N68:N71),"") -> 10669.8 | O72: =IF(AND(TRUE,O$66<>""),SUM(O68:O71),"") -> 244108.3 | P72: =IF(AND(TRUE,P$66<>""),SUM(P68:P71),"") -> 0 | Q72: =IF(AND(TRUE,Q$66<>""),SUM(Q68:Q71),"") -> 0 | R72: =IF(AND(TRUE,R$66<>""),SUM(R68:R71),"") -> 0 | S72: =IF(AND(TRUE,S$66<>""),SUM(S68:S71),"") -> 0 | ... AO72: =IF(AND(TRUE,AO$66<>""),SUM(AO68:AO71),"") -> 0
J73: Utenze | K73: Gas | L73: =IF(AND(TRUE,L$66<>""),SUMIFS(Flussi!$F:$F,Flussi!$B:$B,L$66,Flussi!$D:$D,$J73,Flussi!$E:$E,$K73,Flussi!$A:$A,$D$2),"") -> -59 | M73: =IF(AND(TRUE,M$66<>""),SUMIFS(Flussi!$F:$F,Flussi!$B:$B,M$66,Flussi!$D:$D,$J73,Flussi!$E:$E,$K73,Flussi!$A:$A,$D$2),"") -> -33.169839 | N73: =IF(AND(TRUE,N$66<>""),SUMIFS(Flussi!$F:$F,Flussi!$B:$B,N$66,Flussi!$D:$D,$J73,Flussi!$E:$E,$K73,Flussi!$A:$A,$D$2),"") -> 0 | O73: =IF(AND(TRUE,O$66<>""),SUMIFS(Flussi!$F:$F,Flussi!$B:$B,O$66,Flussi!$D:$D,$J73,Flussi!$E:$E,$K73,Flussi!$A:$A,$D$2),"") -> -188.61 | P73: =IF(AND(TRUE,P$66<>""),SUMIFS(Flussi!$F:$F,Flussi!$B:$B,P$66,Flussi!$D:$D,$J73,Flussi!$E:$E,$K73,Flussi!$A:$A,$D$2),"") -> 0 | Q73: =IF(AND(TRUE,Q$66<>""),SUMIFS(Flussi!$F:$F,Flussi!$B:$B,Q$66,Flussi!$D:$D,$J73,Flussi!$E:$E,$K73,Flussi!$A:$A,$D$2),"") -> 0 | R73: =IF(AND(TRUE,R$66<>""),SUMIFS(Flussi!$F:$F,Flussi!$B:$B,R$66,Flussi!$D:$D,$J73,Flussi!$E:$E,$K73,Flussi!$A:$A,$D$2),"") -> 0 | S73: =IF(AND(TRUE,S$66<>""),SUMIFS(Flussi!$F:$F,Flussi!$B:$B,S$66,Flussi!$D:$D,$J73,Flussi!$E:$E,$K73,Flussi!$A:$A,$D$2),"") -> 0 | ... AO73: =IF(AND(TRUE,AO$66<>""),SUMIFS(Flussi!$F:$F,Flussi!$B:$B,AO$66,Flussi!$D:$D,$J73,Flussi!$E:$E,$K73,Flussi!$A:$A,$D$2),"") -> 0
J74: Utenze | K74: Luce | L74: =IF(AND(TRUE,L$66<>""),SUMIFS(Flussi!$F:$F,Flussi!$B:$B,L$66,Flussi!$D:$D,$J74,Flussi!$E:$E,$K74,Flussi!$A:$A,$D$2),"") -> -145 | M74: =IF(AND(TRUE,M$66<>""),SUMIFS(Flussi!$F:$F,Flussi!$B:$B,M$66,Flussi!$D:$D,$J74,Flussi!$E:$E,$K74,Flussi!$A:$A,$D$2),"") -> -9.6948485 | N74: =IF(AND(TRUE,N$66<>""),SUMIFS(Flussi!$F:$F,Flussi!$B:$B,N$66,Flussi!$D:$D,$J74,Flussi!$E:$E,$K74,Flussi!$A:$A,$D$2),"") -> 0 | O74: =IF(AND(TRUE,O$66<>""),SUMIFS(Flussi!$F:$F,Flussi!$B:$B,O$66,Flussi!$D:$D,$J74,Flussi!$E:$E,$K74,Flussi!$A:$A,$D$2),"") -> -100 | P74: =IF(AND(TRUE,P$66<>""),SUMIFS(Flussi!$F:$F,Flussi!$B:$B,P$66,Flussi!$D:$D,$J74,Flussi!$E:$E,$K74,Flussi!$A:$A,$D$2),"") -> 0 | Q74: =IF(AND(TRUE,Q$66<>""),SUMIFS(Flussi!$F:$F,Flussi!$B:$B,Q$66,Flussi!$D:$D,$J74,Flussi!$E:$E,$K74,Flussi!$A:$A,$D$2),"") -> 0 | R74: =IF(AND(TRUE,R$66<>""),SUMIFS(Flussi!$F:$F,Flussi!$B:$B,R$66,Flussi!$D:$D,$J74,Flussi!$E:$E,$K74,Flussi!$A:$A,$D$2),"") -> 0 | S74: =IF(AND(TRUE,S$66<>""),SUMIFS(Flussi!$F:$F,Flussi!$B:$B,S$66,Flussi!$D:$D,$J74,Flussi!$E:$E,$K74,Flussi!$A:$A,$D$2),"") -> 0 | ... AO74: =IF(AND(TRUE,AO$66<>""),SUMIFS(Flussi!$F:$F,Flussi!$B:$B,AO$66,Flussi!$D:$D,$J74,Flussi!$E:$E,$K74,Flussi!$A:$A,$D$2),"") -> 0
J75: Utenze | K75: Internet | L75: =IF(AND(TRUE,L$66<>""),SUMIFS(Flussi!$F:$F,Flussi!$B:$B,L$66,Flussi!$D:$D,$J75,Flussi!$E:$E,$K75,Flussi!$A:$A,$D$2),"") -> 0 | M75: =IF(AND(TRUE,M$66<>""),SUMIFS(Flussi!$F:$F,Flussi!$B:$B,M$66,Flussi!$D:$D,$J75,Flussi!$E:$E,$K75,Flussi!$A:$A,$D$2),"") -> 0 | N75: =IF(AND(TRUE,N$66<>""),SUMIFS(Flussi!$F:$F,Flussi!$B:$B,N$66,Flussi!$D:$D,$J75,Flussi!$E:$E,$K75,Flussi!$A:$A,$D$2),"") -> 0 | O75: =IF(AND(TRUE,O$66<>""),SUMIFS(Flussi!$F:$F,Flussi!$B:$B,O$66,Flussi!$D:$D,$J75,Flussi!$E:$E,$K75,Flussi!$A:$A,$D$2),"") -> 0 | P75: =IF(AND(TRUE,P$66<>""),SUMIFS(Flussi!$F:$F,Flussi!$B:$B,P$66,Flussi!$D:$D,$J75,Flussi!$E:$E,$K75,Flussi!$A:$A,$D$2),"") -> 0 | Q75: =IF(AND(TRUE,Q$66<>""),SUMIFS(Flussi!$F:$F,Flussi!$B:$B,Q$66,Flussi!$D:$D,$J75,Flussi!$E:$E,$K75,Flussi!$A:$A,$D$2),"") -> 0 | R75: =IF(AND(TRUE,R$66<>""),SUMIFS(Flussi!$F:$F,Flussi!$B:$B,R$66,Flussi!$D:$D,$J75,Flussi!$E:$E,$K75,Flussi!$A:$A,$D$2),"") -> 0 | S75: =IF(AND(TRUE,S$66<>""),SUMIFS(Flussi!$F:$F,Flussi!$B:$B,S$66,Flussi!$D:$D,$J75,Flussi!$E:$E,$K75,Flussi!$A:$A,$D$2),"") -> 0 | ... AO75: =IF(AND(TRUE,AO$66<>""),SUMIFS(Flussi!$F:$F,Flussi!$B:$B,AO$66,Flussi!$D:$D,$J75,Flussi!$E:$E,$K75,Flussi!$A:$A,$D$2),"") -> 0
J76: Avviamento | K76: Intermediazione | L76: =IF(AND(TRUE,L$66<>""),SUMIFS(Flussi!$F:$F,Flussi!$B:$B,L$66,Flussi!$D:$D,$J76,Flussi!$E:$E,$K76,Flussi!$A:$A,$D$2),"") -> 0 | M76: =IF(AND(TRUE,M$66<>""),SUMIFS(Flussi!$F:$F,Flussi!$B:$B,M$66,Flussi!$D:$D,$J76,Flussi!$E:$E,$K76,Flussi!$A:$A,$D$2),"") -> 0 | N76: =IF(AND(TRUE,N$66<>""),SUMIFS(Flussi!$F:$F,Flussi!$B:$B,N$66,Flussi!$D:$D,$J76,Flussi!$E:$E,$K76,Flussi!$A:$A,$D$2),"") -> 0 | O76: =IF(AND(TRUE,O$66<>""),SUMIFS(Flussi!$F:$F,Flussi!$B:$B,O$66,Flussi!$D:$D,$J76,Flussi!$E:$E,$K76,Flussi!$A:$A,$D$2),"") -> 0 | P76: =IF(AND(TRUE,P$66<>""),SUMIFS(Flussi!$F:$F,Flussi!$B:$B,P$66,Flussi!$D:$D,$J76,Flussi!$E:$E,$K76,Flussi!$A:$A,$D$2),"") -> 0 | Q76: =IF(AND(TRUE,Q$66<>""),SUMIFS(Flussi!$F:$F,Flussi!$B:$B,Q$66,Flussi!$D:$D,$J76,Flussi!$E:$E,$K76,Flussi!$A:$A,$D$2),"") -> 0 | R76: =IF(AND(TRUE,R$66<>""),SUMIFS(Flussi!$F:$F,Flussi!$B:$B,R$66,Flussi!$D:$D,$J76,Flussi!$E:$E,$K76,Flussi!$A:$A,$D$2),"") -> 0 | S76: =IF(AND(TRUE,S$66<>""),SUMIFS(Flussi!$F:$F,Flussi!$B:$B,S$66,Flussi!$D:$D,$J76,Flussi!$E:$E,$K76,Flussi!$A:$A,$D$2),"") -> 0 | ... AO76: =IF(AND(TRUE,AO$66<>""),SUMIFS(Flussi!$F:$F,Flussi!$B:$B,AO$66,Flussi!$D:$D,$J76,Flussi!$E:$E,$K76,Flussi!$A:$A,$D$2),"") -> 0
J77: Avviamento | K77: - | L77: =IF(AND(TRUE,L$66<>""),SUMIFS(Flussi!$F:$F,Flussi!$B:$B,L$66,Flussi!$D:$D,$J77,Flussi!$E:$E,$K77,Flussi!$A:$A,$D$2),"") -> -1650 | M77: =IF(AND(TRUE,M$66<>""),SUMIFS(Flussi!$F:$F,Flussi!$B:$B,M$66,Flussi!$D:$D,$J77,Flussi!$E:$E,$K77,Flussi!$A:$A,$D$2),"") -> 0 | N77: =IF(AND(TRUE,N$66<>""),SUMIFS(Flussi!$F:$F,Flussi!$B:$B,N$66,Flussi!$D:$D,$J77,Flussi!$E:$E,$K77,Flussi!$A:$A,$D$2),"") -> 0 | O77: =IF(AND(TRUE,O$66<>""),SUMIFS(Flussi!$F:$F,Flussi!$B:$B,O$66,Flussi!$D:$D,$J77,Flussi!$E:$E,$K77,Flussi!$A:$A,$D$2),"") -> 0 | P77: =IF(AND(TRUE,P$66<>""),SUMIFS(Flussi!$F:$F,Flussi!$B:$B,P$66,Flussi!$D:$D,$J77,Flussi!$E:$E,$K77,Flussi!$A:$A,$D$2),"") -> 0 | Q77: =IF(AND(TRUE,Q$66<>""),SUMIFS(Flussi!$F:$F,Flussi!$B:$B,Q$66,Flussi!$D:$D,$J77,Flussi!$E:$E,$K77,Flussi!$A:$A,$D$2),"") -> 0 | R77: =IF(AND(TRUE,R$66<>""),SUMIFS(Flussi!$F:$F,Flussi!$B:$B,R$66,Flussi!$D:$D,$J77,Flussi!$E:$E,$K77,Flussi!$A:$A,$D$2),"") -> 0 | S77: =IF(AND(TRUE,S$66<>""),SUMIFS(Flussi!$F:$F,Flussi!$B:$B,S$66,Flussi!$D:$D,$J77,Flussi!$E:$E,$K77,Flussi!$A:$A,$D$2),"") -> 0 | ... AO77: =IF(AND(TRUE,AO$66<>""),SUMIFS(Flussi!$F:$F,Flussi!$B:$B,AO$66,Flussi!$D:$D,$J77,Flussi!$E:$E,$K77,Flussi!$A:$A,$D$2),"") -> 0
J78: Condominio | K78: Ordinario | L78: =IF(AND(TRUE,L$66<>""),SUMIFS(Flussi!$F:$F,Flussi!$B:$B,L$66,Flussi!$D:$D,$J78,Flussi!$E:$E,$K78,Flussi!$A:$A,$D$2),"") -> -1493.06 | M78: =IF(AND(TRUE,M$66<>""),SUMIFS(Flussi!$F:$F,Flussi!$B:$B,M$66,Flussi!$D:$D,$J78,Flussi!$E:$E,$K78,Flussi!$A:$A,$D$2),"") -> -1408.95 | N78: =IF(AND(TRUE,N$66<>""),SUMIFS(Flussi!$F:$F,Flussi!$B:$B,N$66,Flussi!$D:$D,$J78,Flussi!$E:$E,$K78,Flussi!$A:$A,$D$2),"") -> -2522.22 | O78: =IF(AND(TRUE,O$66<>""),SUMIFS(Flussi!$F:$F,Flussi!$B:$B,O$66,Flussi!$D:$D,$J78,Flussi!$E:$E,$K78,Flussi!$A:$A,$D$2),"") -> -2168 | P78: =IF(AND(TRUE,P$66<>""),SUMIFS(Flussi!$F:$F,Flussi!$B:$B,P$66,Flussi!$D:$D,$J78,Flussi!$E:$E,$K78,Flussi!$A:$A,$D$2),"") -> 0 | Q78: =IF(AND(TRUE,Q$66<>""),SUMIFS(Flussi!$F:$F,Flussi!$B:$B,Q$66,Flussi!$D:$D,$J78,Flussi!$E:$E,$K78,Flussi!$A:$A,$D$2),"") -> 0 | R78: =IF(AND(TRUE,R$66<>""),SUMIFS(Flussi!$F:$F,Flussi!$B:$B,R$66,Flussi!$D:$D,$J78,Flussi!$E:$E,$K78,Flussi!$A:$A,$D$2),"") -> 0 | S78: =IF(AND(TRUE,S$66<>""),SUMIFS(Flussi!$F:$F,Flussi!$B:$B,S$66,Flussi!$D:$D,$J78,Flussi!$E:$E,$K78,Flussi!$A:$A,$D$2),"") -> 0 | ... AO78: =IF(AND(TRUE,AO$66<>""),SUMIFS(Flussi!$F:$F,Flussi!$B:$B,AO$66,Flussi!$D:$D,$J78,Flussi!$E:$E,$K78,Flussi!$A:$A,$D$2),"") -> 0
J79: Condominio | K79: Straordinario | L79: =IF(AND(TRUE,L$66<>""),SUMIFS(Flussi!$F:$F,Flussi!$B:$B,L$66,Flussi!$D:$D,$J79,Flussi!$E:$E,$K79,Flussi!$A:$A,$D$2),"") -> 0 | M79: =IF(AND(TRUE,M$66<>""),SUMIFS(Flussi!$F:$F,Flussi!$B:$B,M$66,Flussi!$D:$D,$J79,Flussi!$E:$E,$K79,Flussi!$A:$A,$D$2),"") -> 0 | N79: =IF(AND(TRUE,N$66<>""),SUMIFS(Flussi!$F:$F,Flussi!$B:$B,N$66,Flussi!$D:$D,$J79,Flussi!$E:$E,$K79,Flussi!$A:$A,$D$2),"") -> 0 | O79: =IF(AND(TRUE,O$66<>""),SUMIFS(Flussi!$F:$F,Flussi!$B:$B,O$66,Flussi!$D:$D,$J79,Flussi!$E:$E,$K79,Flussi!$A:$A,$D$2),"") -> 0 | P79: =IF(AND(TRUE,P$66<>""),SUMIFS(Flussi!$F:$F,Flussi!$B:$B,P$66,Flussi!$D:$D,$J79,Flussi!$E:$E,$K79,Flussi!$A:$A,$D$2),"") -> 0 | Q79: =IF(AND(TRUE,Q$66<>""),SUMIFS(Flussi!$F:$F,Flussi!$B:$B,Q$66,Flussi!$D:$D,$J79,Flussi!$E:$E,$K79,Flussi!$A:$A,$D$2),"") -> 0 | R79: =IF(AND(TRUE,R$66<>""),SUMIFS(Flussi!$F:$F,Flussi!$B:$B,R$66,Flussi!$D:$D,$J79,Flussi!$E:$E,$K79,Flussi!$A:$A,$D$2),"") -> 0 | S79: =IF(AND(TRUE,S$66<>""),SUMIFS(Flussi!$F:$F,Flussi!$B:$B,S$66,Flussi!$D:$D,$J79,Flussi!$E:$E,$K79,Flussi!$A:$A,$D$2),"") -> 0 | ... AO79: =IF(AND(TRUE,AO$66<>""),SUMIFS(Flussi!$F:$F,Flussi!$B:$B,AO$66,Flussi!$D:$D,$J79,Flussi!$E:$E,$K79,Flussi!$A:$A,$D$2),"") -> 0
J80: Assicurazione | K80: - | L80: =IF(AND(TRUE,L$66<>""),SUMIFS(Flussi!$F:$F,Flussi!$B:$B,L$66,Flussi!$D:$D,$J80,Flussi!$E:$E,$K80,Flussi!$A:$A,$D$2),"") -> -46.53 | M80: =IF(AND(TRUE,M$66<>""),SUMIFS(Flussi!$F:$F,Flussi!$B:$B,M$66,Flussi!$D:$D,$J80,Flussi!$E:$E,$K80,Flussi!$A:$A,$D$2),"") -> -186.12 | N80: =IF(AND(TRUE,N$66<>""),SUMIFS(Flussi!$F:$F,Flussi!$B:$B,N$66,Flussi!$D:$D,$J80,Flussi!$E:$E,$K80,Flussi!$A:$A,$D$2),"") -> -186.12 | O80: =IF(AND(TRUE,O$66<>""),SUMIFS(Flussi!$F:$F,Flussi!$B:$B,O$66,Flussi!$D:$D,$J80,Flussi!$E:$E,$K80,Flussi!$A:$A,$D$2),"") -> -15.51 | P80: =IF(AND(TRUE,P$66<>""),SUMIFS(Flussi!$F:$F,Flussi!$B:$B,P$66,Flussi!$D:$D,$J80,Flussi!$E:$E,$K80,Flussi!$A:$A,$D$2),"") -> 0 | Q80: =IF(AND(TRUE,Q$66<>""),SUMIFS(Flussi!$F:$F,Flussi!$B:$B,Q$66,Flussi!$D:$D,$J80,Flussi!$E:$E,$K80,Flussi!$A:$A,$D$2),"") -> 0 | R80: =IF(AND(TRUE,R$66<>""),SUMIFS(Flussi!$F:$F,Flussi!$B:$B,R$66,Flussi!$D:$D,$J80,Flussi!$E:$E,$K80,Flussi!$A:$A,$D$2),"") -> 0 | S80: =IF(AND(TRUE,S$66<>""),SUMIFS(Flussi!$F:$F,Flussi!$B:$B,S$66,Flussi!$D:$D,$J80,Flussi!$E:$E,$K80,Flussi!$A:$A,$D$2),"") -> 0 | ... AO80: =IF(AND(TRUE,AO$66<>""),SUMIFS(Flussi!$F:$F,Flussi!$B:$B,AO$66,Flussi!$D:$D,$J80,Flussi!$E:$E,$K80,Flussi!$A:$A,$D$2),"") -> 0
J81: Manutenzione ordinaria | K81: - | L81: =IF(AND(TRUE,L$66<>""),SUMIFS(Flussi!$F:$F,Flussi!$B:$B,L$66,Flussi!$D:$D,$J81,Flussi!$E:$E,$K81,Flussi!$A:$A,$D$2),"") -> -209 | M81: =IF(AND(TRUE,M$66<>""),SUMIFS(Flussi!$F:$F,Flussi!$B:$B,M$66,Flussi!$D:$D,$J81,Flussi!$E:$E,$K81,Flussi!$A:$A,$D$2),"") -> 0 | N81: =IF(AND(TRUE,N$66<>""),SUMIFS(Flussi!$F:$F,Flussi!$B:$B,N$66,Flussi!$D:$D,$J81,Flussi!$E:$E,$K81,Flussi!$A:$A,$D$2),"") -> 0 | O81: =IF(AND(TRUE,O$66<>""),SUMIFS(Flussi!$F:$F,Flussi!$B:$B,O$66,Flussi!$D:$D,$J81,Flussi!$E:$E,$K81,Flussi!$A:$A,$D$2),"") -> -170 | P81: =IF(AND(TRUE,P$66<>""),SUMIFS(Flussi!$F:$F,Flussi!$B:$B,P$66,Flussi!$D:$D,$J81,Flussi!$E:$E,$K81,Flussi!$A:$A,$D$2),"") -> 0 | Q81: =IF(AND(TRUE,Q$66<>""),SUMIFS(Flussi!$F:$F,Flussi!$B:$B,Q$66,Flussi!$D:$D,$J81,Flussi!$E:$E,$K81,Flussi!$A:$A,$D$2),"") -> 0 | R81: =IF(AND(TRUE,R$66<>""),SUMIFS(Flussi!$F:$F,Flussi!$B:$B,R$66,Flussi!$D:$D,$J81,Flussi!$E:$E,$K81,Flussi!$A:$A,$D$2),"") -> 0 | S81: =IF(AND(TRUE,S$66<>""),SUMIFS(Flussi!$F:$F,Flussi!$B:$B,S$66,Flussi!$D:$D,$J81,Flussi!$E:$E,$K81,Flussi!$A:$A,$D$2),"") -> 0 | ... AO81: =IF(AND(TRUE,AO$66<>""),SUMIFS(Flussi!$F:$F,Flussi!$B:$B,AO$66,Flussi!$D:$D,$J81,Flussi!$E:$E,$K81,Flussi!$A:$A,$D$2),"") -> 0
J82: Manutenzione straordinaria | K82: - | L82: =IF(AND(TRUE,L$66<>""),SUMIFS(Flussi!$F:$F,Flussi!$B:$B,L$66,Flussi!$D:$D,$J82,Flussi!$E:$E,$K82,Flussi!$A:$A,$D$2),"") -> -130 | M82: =IF(AND(TRUE,M$66<>""),SUMIFS(Flussi!$F:$F,Flussi!$B:$B,M$66,Flussi!$D:$D,$J82,Flussi!$E:$E,$K82,Flussi!$A:$A,$D$2),"") -> -743.89 | N82: =IF(AND(TRUE,N$66<>""),SUMIFS(Flussi!$F:$F,Flussi!$B:$B,N$66,Flussi!$D:$D,$J82,Flussi!$E:$E,$K82,Flussi!$A:$A,$D$2),"") -> 234 | O82: =IF(AND(TRUE,O$66<>""),SUMIFS(Flussi!$F:$F,Flussi!$B:$B,O$66,Flussi!$D:$D,$J82,Flussi!$E:$E,$K82,Flussi!$A:$A,$D$2),"") -> 0 | P82: =IF(AND(TRUE,P$66<>""),SUMIFS(Flussi!$F:$F,Flussi!$B:$B,P$66,Flussi!$D:$D,$J82,Flussi!$E:$E,$K82,Flussi!$A:$A,$D$2),"") -> 0 | Q82: =IF(AND(TRUE,Q$66<>""),SUMIFS(Flussi!$F:$F,Flussi!$B:$B,Q$66,Flussi!$D:$D,$J82,Flussi!$E:$E,$K82,Flussi!$A:$A,$D$2),"") -> 0 | R82: =IF(AND(TRUE,R$66<>""),SUMIFS(Flussi!$F:$F,Flussi!$B:$B,R$66,Flussi!$D:$D,$J82,Flussi!$E:$E,$K82,Flussi!$A:$A,$D$2),"") -> 0 | S82: =IF(AND(TRUE,S$66<>""),SUMIFS(Flussi!$F:$F,Flussi!$B:$B,S$66,Flussi!$D:$D,$J82,Flussi!$E:$E,$K82,Flussi!$A:$A,$D$2),"") -> 0 | ... AO82: =IF(AND(TRUE,AO$66<>""),SUMIFS(Flussi!$F:$F,Flussi!$B:$B,AO$66,Flussi!$D:$D,$J82,Flussi!$E:$E,$K82,Flussi!$A:$A,$D$2),"") -> 0
I83: Costi | K83: P&L | L83: =IF(AND(TRUE,L$66<>""),SUM(L73:L82),"") -> -3732.59 | M83: =IF(AND(TRUE,M$66<>""),SUM(M73:M82),"") -> -2381.8247 | N83: =IF(AND(TRUE,N$66<>""),SUM(N73:N82),"") -> -2474.34 | O83: =IF(AND(TRUE,O$66<>""),SUM(O73:O82),"") -> -2642.12 | P83: =IF(AND(TRUE,P$66<>""),SUM(P73:P82),"") -> 0 | Q83: =IF(AND(TRUE,Q$66<>""),SUM(Q73:Q82),"") -> 0 | R83: =IF(AND(TRUE,R$66<>""),SUM(R73:R82),"") -> 0 | S83: =IF(AND(TRUE,S$66<>""),SUM(S73:S82),"") -> 0 | ... AO83: =IF(AND(TRUE,AO$66<>""),SUM(AO73:AO82),"") -> 0
I84: EBIDTA | K84: P&L | L84: =IF(AND(TRUE,L$66<>""),L72+L83,"") -> -1926.59 | M84: =IF(AND(TRUE,M$66<>""),M72+M83,"") -> 8099.5753 | N84: =IF(AND(TRUE,N$66<>""),N72+N83,"") -> 8195.46 | O84: =IF(AND(TRUE,O$66<>""),O72+O83,"") -> 241466.18 | P84: =IF(AND(TRUE,P$66<>""),P72+P83,"") -> 0 | Q84: =IF(AND(TRUE,Q$66<>""),Q72+Q83,"") -> 0 | R84: =IF(AND(TRUE,R$66<>""),R72+R83,"") -> 0 | S84: =IF(AND(TRUE,S$66<>""),S72+S83,"") -> 0 | ... AO84: =IF(AND(TRUE,AO$66<>""),AO72+AO83,"") -> 0
J86: Acquisto | K86: Valore immobile | L86: =IF(AND(TRUE,L$66<>""),SUMIFS(Flussi!$F:$F,Flussi!$B:$B,L$66,Flussi!$D:$D,$J86,Flussi!$E:$E,$K86,Flussi!$A:$A,$D$2),"") -> -215000 | M86: =IF(AND(TRUE,M$66<>""),SUMIFS(Flussi!$F:$F,Flussi!$B:$B,M$66,Flussi!$D:$D,$J86,Flussi!$E:$E,$K86,Flussi!$A:$A,$D$2),"") -> 0 | N86: =IF(AND(TRUE,N$66<>""),SUMIFS(Flussi!$F:$F,Flussi!$B:$B,N$66,Flussi!$D:$D,$J86,Flussi!$E:$E,$K86,Flussi!$A:$A,$D$2),"") -> 0 | O86: =IF(AND(TRUE,O$66<>""),SUMIFS(Flussi!$F:$F,Flussi!$B:$B,O$66,Flussi!$D:$D,$J86,Flussi!$E:$E,$K86,Flussi!$A:$A,$D$2),"") -> 0 | P86: =IF(AND(TRUE,P$66<>""),SUMIFS(Flussi!$F:$F,Flussi!$B:$B,P$66,Flussi!$D:$D,$J86,Flussi!$E:$E,$K86,Flussi!$A:$A,$D$2),"") -> 0 | Q86: =IF(AND(TRUE,Q$66<>""),SUMIFS(Flussi!$F:$F,Flussi!$B:$B,Q$66,Flussi!$D:$D,$J86,Flussi!$E:$E,$K86,Flussi!$A:$A,$D$2),"") -> 0 | R86: =IF(AND(TRUE,R$66<>""),SUMIFS(Flussi!$F:$F,Flussi!$B:$B,R$66,Flussi!$D:$D,$J86,Flussi!$E:$E,$K86,Flussi!$A:$A,$D$2),"") -> 0 | S86: =IF(AND(TRUE,S$66<>""),SUMIFS(Flussi!$F:$F,Flussi!$B:$B,S$66,Flussi!$D:$D,$J86,Flussi!$E:$E,$K86,Flussi!$A:$A,$D$2),"") -> 0 | ... AO86: =IF(AND(TRUE,AO$66<>""),SUMIFS(Flussi!$F:$F,Flussi!$B:$B,AO$66,Flussi!$D:$D,$J86,Flussi!$E:$E,$K86,Flussi!$A:$A,$D$2),"") -> 0
J87: Mutuo | K87: Importo | L87: =IF(AND(TRUE,L$66<>""),SUMIFS(Flussi!$F:$F,Flussi!$B:$B,L$66,Flussi!$D:$D,$J87,Flussi!$E:$E,$K87,Flussi!$A:$A,$D$2),"") -> 0 | M87: =IF(AND(TRUE,M$66<>""),SUMIFS(Flussi!$F:$F,Flussi!$B:$B,M$66,Flussi!$D:$D,$J87,Flussi!$E:$E,$K87,Flussi!$A:$A,$D$2),"") -> 0 | N87: =IF(AND(TRUE,N$66<>""),SUMIFS(Flussi!$F:$F,Flussi!$B:$B,N$66,Flussi!$D:$D,$J87,Flussi!$E:$E,$K87,Flussi!$A:$A,$D$2),"") -> 0 | O87: =IF(AND(TRUE,O$66<>""),SUMIFS(Flussi!$F:$F,Flussi!$B:$B,O$66,Flussi!$D:$D,$J87,Flussi!$E:$E,$K87,Flussi!$A:$A,$D$2),"") -> 0 | P87: =IF(AND(TRUE,P$66<>""),SUMIFS(Flussi!$F:$F,Flussi!$B:$B,P$66,Flussi!$D:$D,$J87,Flussi!$E:$E,$K87,Flussi!$A:$A,$D$2),"") -> 0 | Q87: =IF(AND(TRUE,Q$66<>""),SUMIFS(Flussi!$F:$F,Flussi!$B:$B,Q$66,Flussi!$D:$D,$J87,Flussi!$E:$E,$K87,Flussi!$A:$A,$D$2),"") -> 0 | R87: =IF(AND(TRUE,R$66<>""),SUMIFS(Flussi!$F:$F,Flussi!$B:$B,R$66,Flussi!$D:$D,$J87,Flussi!$E:$E,$K87,Flussi!$A:$A,$D$2),"") -> 0 | S87: =IF(AND(TRUE,S$66<>""),SUMIFS(Flussi!$F:$F,Flussi!$B:$B,S$66,Flussi!$D:$D,$J87,Flussi!$E:$E,$K87,Flussi!$A:$A,$D$2),"") -> 0 | ... AO87: =IF(AND(TRUE,AO$66<>""),SUMIFS(Flussi!$F:$F,Flussi!$B:$B,AO$66,Flussi!$D:$D,$J87,Flussi!$E:$E,$K87,Flussi!$A:$A,$D$2),"") -> 0
J88: Mutuo | K88: Quota capitale | L88: 0 | M88: 0 | N88: 0 | O88: 0 | P88: 0 | Q88: 0 | R88: 0 | S88: 0 | T88: 0 | U88: 0 | V88: 0 | W88: 0 | X88: 0 | Y88: 0 | Z88: 0 | AA88: 0 | AB88: 0 | AC88: 0 | AD88: 0 | AE88: 0 | AF88: 0 | AG88: 0 | AH88: 0 | AI88: 0 | AJ88: 0 | AK88: 0 | AL88: 0 | AM88: 0 | AN88: 0 | AO88: 0
J89: Mutuo | K89: Rimborso anticipato | L89: 0 | M89: 0 | N89: 0 | O89: 0 | P89: 0 | Q89: 0 | R89: 0 | S89: 0 | T89: 0 | U89: 0 | V89: 0 | W89: 0 | X89: 0 | Y89: 0 | Z89: 0 | AA89: 0 | AB89: 0 | AC89: 0 | AD89: 0 | AE89: 0 | AF89: 0 | AG89: 0 | AH89: 0 | AI89: 0 | AJ89: 0 | AK89: 0 | AL89: 0 | AM89: 0 | AN89: 0 | AO89: 0
I90: Equity | J90: Equity | K90: P&L | L90: =IF(AND(TRUE,L$66<>""),SUM(L86:L89),"") -> -215000 | M90: =IF(AND(TRUE,M$66<>""),SUM(M86:M89),"") -> 0 | N90: =IF(AND(TRUE,N$66<>""),SUM(N86:N89),"") -> 0 | O90: =IF(AND(TRUE,O$66<>""),SUM(O86:O89),"") -> 0 | P90: =IF(AND(TRUE,P$66<>""),SUM(P86:P89),"") -> 0 | Q90: =IF(AND(TRUE,Q$66<>""),SUM(Q86:Q89),"") -> 0 | R90: =IF(AND(TRUE,R$66<>""),SUM(R86:R89),"") -> 0 | S90: =IF(AND(TRUE,S$66<>""),SUM(S86:S89),"") -> 0 | ... AO90: =IF(AND(TRUE,AO$66<>""),SUM(AO86:AO89),"") -> 0
H91: =YEAR($E$4) -> 2023 | L91: =IF(AND($H91<>"",L$66<>""),IF(AND(L$66>=$H91,L$66<$H91+$D$31),SUMIFS($L$90:$AK$90,$L$66:$AK$66,$H91)/$D$31,0),"") -> -21500 | M91: =IF(AND($H91<>"",M$66<>""),IF(AND(M$66>=$H91,M$66<$H91+$D$31),SUMIFS($L$90:$AK$90,$L$66:$AK$66,$H91)/$D$31,0),"") -> -21500 | N91: =IF(AND($H91<>"",N$66<>""),IF(AND(N$66>=$H91,N$66<$H91+$D$31),SUMIFS($L$90:$AK$90,$L$66:$AK$66,$H91)/$D$31,0),"") -> -21500 | O91: =IF(AND($H91<>"",O$66<>""),IF(AND(O$66>=$H91,O$66<$H91+$D$31),SUMIFS($L$90:$AK$90,$L$66:$AK$66,$H91)/$D$31,0),"") -> -21500 | P91: =IF(AND($H91<>"",P$66<>""),IF(AND(P$66>=$H91,P$66<$H91+$D$31),SUMIFS($L$90:$AK$90,$L$66:$AK$66,$H91)/$D$31,0),"") -> -21500 | Q91: =IF(AND($H91<>"",Q$66<>""),IF(AND(Q$66>=$H91,Q$66<$H91+$D$31),SUMIFS($L$90:$AK$90,$L$66:$AK$66,$H91)/$D$31,0),"") -> -21500 | R91: =IF(AND($H91<>"",R$66<>""),IF(AND(R$66>=$H91,R$66<$H91+$D$31),SUMIFS($L$90:$AK$90,$L$66:$AK$66,$H91)/$D$31,0),"") -> -21500 | S91: =IF(AND($H91<>"",S$66<>""),IF(AND(S$66>=$H91,S$66<$H91+$D$31),SUMIFS($L$90:$AK$90,$L$66:$AK$66,$H91)/$D$31,0),"") -> -21500 | ... AO91: =IF(AND($H91<>"",AO$66<>""),IF(AND(AO$66>=$H91,AO$66<$H91+$D$31),SUMIFS($L$90:$AK$90,$L$66:$AK$66,$H91)/$D$31,0),"") -> 0
H92: =IF(H91<>"",IF(H91+1<YEAR($E$4)+$E$5,H91+1,""),"") -> 2024 | L92: =IF(AND($H92<>"",L$66<>""),IF(AND(L$66>=$H92,L$66<$H92+$D$31),SUMIFS($L$90:$AK$90,$L$66:$AK$66,$H92)/$D$31,0),"") -> 0 | M92: =IF(AND($H92<>"",M$66<>""),IF(AND(M$66>=$H92,M$66<$H92+$D$31),SUMIFS($L$90:$AK$90,$L$66:$AK$66,$H92)/$D$31,0),"") -> 0 | N92: =IF(AND($H92<>"",N$66<>""),IF(AND(N$66>=$H92,N$66<$H92+$D$31),SUMIFS($L$90:$AK$90,$L$66:$AK$66,$H92)/$D$31,0),"") -> 0 | O92: =IF(AND($H92<>"",O$66<>""),IF(AND(O$66>=$H92,O$66<$H92+$D$31),SUMIFS($L$90:$AK$90,$L$66:$AK$66,$H92)/$D$31,0),"") -> 0 | P92: =IF(AND($H92<>"",P$66<>""),IF(AND(P$66>=$H92,P$66<$H92+$D$31),SUMIFS($L$90:$AK$90,$L$66:$AK$66,$H92)/$D$31,0),"") -> 0 | Q92: =IF(AND($H92<>"",Q$66<>""),IF(AND(Q$66>=$H92,Q$66<$H92+$D$31),SUMIFS($L$90:$AK$90,$L$66:$AK$66,$H92)/$D$31,0),"") -> 0 | R92: =IF(AND($H92<>"",R$66<>""),IF(AND(R$66>=$H92,R$66<$H92+$D$31),SUMIFS($L$90:$AK$90,$L$66:$AK$66,$H92)/$D$31,0),"") -> 0 | S92: =IF(AND($H92<>"",S$66<>""),IF(AND(S$66>=$H92,S$66<$H92+$D$31),SUMIFS($L$90:$AK$90,$L$66:$AK$66,$H92)/$D$31,0),"") -> 0 | ... AO92: =IF(AND($H92<>"",AO$66<>""),IF(AND(AO$66>=$H92,AO$66<$H92+$D$31),SUMIFS($L$90:$AK$90,$L$66:$AK$66,$H92)/$D$31,0),"") -> 0
H93: =IF(H92<>"",IF(H92+1<YEAR($E$4)+$E$5,H92+1,""),"") -> 2025 | L93: =IF(AND($H93<>"",L$66<>""),IF(AND(L$66>=$H93,L$66<$H93+$D$31),SUMIFS($L$90:$AK$90,$L$66:$AK$66,$H93)/$D$31,0),"") -> 0 | M93: =IF(AND($H93<>"",M$66<>""),IF(AND(M$66>=$H93,M$66<$H93+$D$31),SUMIFS($L$90:$AK$90,$L$66:$AK$66,$H93)/$D$31,0),"") -> 0 | N93: =IF(AND($H93<>"",N$66<>""),IF(AND(N$66>=$H93,N$66<$H93+$D$31),SUMIFS($L$90:$AK$90,$L$66:$AK$66,$H93)/$D$31,0),"") -> 0 | O93: =IF(AND($H93<>"",O$66<>""),IF(AND(O$66>=$H93,O$66<$H93+$D$31),SUMIFS($L$90:$AK$90,$L$66:$AK$66,$H93)/$D$31,0),"") -> 0 | P93: =IF(AND($H93<>"",P$66<>""),IF(AND(P$66>=$H93,P$66<$H93+$D$31),SUMIFS($L$90:$AK$90,$L$66:$AK$66,$H93)/$D$31,0),"") -> 0 | Q93: =IF(AND($H93<>"",Q$66<>""),IF(AND(Q$66>=$H93,Q$66<$H93+$D$31),SUMIFS($L$90:$AK$90,$L$66:$AK$66,$H93)/$D$31,0),"") -> 0 | R93: =IF(AND($H93<>"",R$66<>""),IF(AND(R$66>=$H93,R$66<$H93+$D$31),SUMIFS($L$90:$AK$90,$L$66:$AK$66,$H93)/$D$31,0),"") -> 0 | S93: =IF(AND($H93<>"",S$66<>""),IF(AND(S$66>=$H93,S$66<$H93+$D$31),SUMIFS($L$90:$AK$90,$L$66:$AK$66,$H93)/$D$31,0),"") -> 0 | ... AO93: =IF(AND($H93<>"",AO$66<>""),IF(AND(AO$66>=$H93,AO$66<$H93+$D$31),SUMIFS($L$90:$AK$90,$L$66:$AK$66,$H93)/$D$31,0),"") -> 0
H94: =IF(H93<>"",IF(H93+1<YEAR($E$4)+$E$5,H93+1,""),"") -> 2026 | L94: =IF(AND($H94<>"",L$66<>""),IF(AND(L$66>=$H94,L$66<$H94+$D$31),SUMIFS($L$90:$AK$90,$L$66:$AK$66,$H94)/$D$31,0),"") -> 0 | M94: =IF(AND($H94<>"",M$66<>""),IF(AND(M$66>=$H94,M$66<$H94+$D$31),SUMIFS($L$90:$AK$90,$L$66:$AK$66,$H94)/$D$31,0),"") -> 0 | N94: =IF(AND($H94<>"",N$66<>""),IF(AND(N$66>=$H94,N$66<$H94+$D$31),SUMIFS($L$90:$AK$90,$L$66:$AK$66,$H94)/$D$31,0),"") -> 0 | O94: =IF(AND($H94<>"",O$66<>""),IF(AND(O$66>=$H94,O$66<$H94+$D$31),SUMIFS($L$90:$AK$90,$L$66:$AK$66,$H94)/$D$31,0),"") -> 0 | P94: =IF(AND($H94<>"",P$66<>""),IF(AND(P$66>=$H94,P$66<$H94+$D$31),SUMIFS($L$90:$AK$90,$L$66:$AK$66,$H94)/$D$31,0),"") -> 0 | Q94: =IF(AND($H94<>"",Q$66<>""),IF(AND(Q$66>=$H94,Q$66<$H94+$D$31),SUMIFS($L$90:$AK$90,$L$66:$AK$66,$H94)/$D$31,0),"") -> 0 | R94: =IF(AND($H94<>"",R$66<>""),IF(AND(R$66>=$H94,R$66<$H94+$D$31),SUMIFS($L$90:$AK$90,$L$66:$AK$66,$H94)/$D$31,0),"") -> 0 | S94: =IF(AND($H94<>"",S$66<>""),IF(AND(S$66>=$H94,S$66<$H94+$D$31),SUMIFS($L$90:$AK$90,$L$66:$AK$66,$H94)/$D$31,0),"") -> 0 | ... AO94: =IF(AND($H94<>"",AO$66<>""),IF(AND(AO$66>=$H94,AO$66<$H94+$D$31),SUMIFS($L$90:$AK$90,$L$66:$AK$66,$H94)/$D$31,0),"") -> 0
H95: =IF(H94<>"",IF(H94+1<YEAR($E$4)+$E$5,H94+1,""),"") -> 2027 | L95: =IF(AND($H95<>"",L$66<>""),IF(AND(L$66>=$H95,L$66<$H95+$D$31),SUMIFS($L$90:$AK$90,$L$66:$AK$66,$H95)/$D$31,0),"") -> 0 | M95: =IF(AND($H95<>"",M$66<>""),IF(AND(M$66>=$H95,M$66<$H95+$D$31),SUMIFS($L$90:$AK$90,$L$66:$AK$66,$H95)/$D$31,0),"") -> 0 | N95: =IF(AND($H95<>"",N$66<>""),IF(AND(N$66>=$H95,N$66<$H95+$D$31),SUMIFS($L$90:$AK$90,$L$66:$AK$66,$H95)/$D$31,0),"") -> 0 | O95: =IF(AND($H95<>"",O$66<>""),IF(AND(O$66>=$H95,O$66<$H95+$D$31),SUMIFS($L$90:$AK$90,$L$66:$AK$66,$H95)/$D$31,0),"") -> 0 | P95: =IF(AND($H95<>"",P$66<>""),IF(AND(P$66>=$H95,P$66<$H95+$D$31),SUMIFS($L$90:$AK$90,$L$66:$AK$66,$H95)/$D$31,0),"") -> 0 | Q95: =IF(AND($H95<>"",Q$66<>""),IF(AND(Q$66>=$H95,Q$66<$H95+$D$31),SUMIFS($L$90:$AK$90,$L$66:$AK$66,$H95)/$D$31,0),"") -> 0 | R95: =IF(AND($H95<>"",R$66<>""),IF(AND(R$66>=$H95,R$66<$H95+$D$31),SUMIFS($L$90:$AK$90,$L$66:$AK$66,$H95)/$D$31,0),"") -> 0 | S95: =IF(AND($H95<>"",S$66<>""),IF(AND(S$66>=$H95,S$66<$H95+$D$31),SUMIFS($L$90:$AK$90,$L$66:$AK$66,$H95)/$D$31,0),"") -> 0 | ... AO95: =IF(AND($H95<>"",AO$66<>""),IF(AND(AO$66>=$H95,AO$66<$H95+$D$31),SUMIFS($L$90:$AK$90,$L$66:$AK$66,$H95)/$D$31,0),"") -> 0
H96: =IF(H95<>"",IF(H95+1<YEAR($E$4)+$E$5,H95+1,""),"") -> 2028 | L96: =IF(AND($H96<>"",L$66<>""),IF(AND(L$66>=$H96,L$66<$H96+$D$31),SUMIFS($L$90:$AK$90,$L$66:$AK$66,$H96)/$D$31,0),"") -> 0 | M96: =IF(AND($H96<>"",M$66<>""),IF(AND(M$66>=$H96,M$66<$H96+$D$31),SUMIFS($L$90:$AK$90,$L$66:$AK$66,$H96)/$D$31,0),"") -> 0 | N96: =IF(AND($H96<>"",N$66<>""),IF(AND(N$66>=$H96,N$66<$H96+$D$31),SUMIFS($L$90:$AK$90,$L$66:$AK$66,$H96)/$D$31,0),"") -> 0 | O96: =IF(AND($H96<>"",O$66<>""),IF(AND(O$66>=$H96,O$66<$H96+$D$31),SUMIFS($L$90:$AK$90,$L$66:$AK$66,$H96)/$D$31,0),"") -> 0 | P96: =IF(AND($H96<>"",P$66<>""),IF(AND(P$66>=$H96,P$66<$H96+$D$31),SUMIFS($L$90:$AK$90,$L$66:$AK$66,$H96)/$D$31,0),"") -> 0 | Q96: =IF(AND($H96<>"",Q$66<>""),IF(AND(Q$66>=$H96,Q$66<$H96+$D$31),SUMIFS($L$90:$AK$90,$L$66:$AK$66,$H96)/$D$31,0),"") -> 0 | R96: =IF(AND($H96<>"",R$66<>""),IF(AND(R$66>=$H96,R$66<$H96+$D$31),SUMIFS($L$90:$AK$90,$L$66:$AK$66,$H96)/$D$31,0),"") -> 0 | S96: =IF(AND($H96<>"",S$66<>""),IF(AND(S$66>=$H96,S$66<$H96+$D$31),SUMIFS($L$90:$AK$90,$L$66:$AK$66,$H96)/$D$31,0),"") -> 0 | ... AO96: =IF(AND($H96<>"",AO$66<>""),IF(AND(AO$66>=$H96,AO$66<$H96+$D$31),SUMIFS($L$90:$AK$90,$L$66:$AK$66,$H96)/$D$31,0),"") -> 0
H97: =IF(H96<>"",IF(H96+1<YEAR($E$4)+$E$5,H96+1,""),"") -> 2029 | L97: =IF(AND($H97<>"",L$66<>""),IF(AND(L$66>=$H97,L$66<$H97+$D$31),SUMIFS($L$90:$AK$90,$L$66:$AK$66,$H97)/$D$31,0),"") -> 0 | M97: =IF(AND($H97<>"",M$66<>""),IF(AND(M$66>=$H97,M$66<$H97+$D$31),SUMIFS($L$90:$AK$90,$L$66:$AK$66,$H97)/$D$31,0),"") -> 0 | N97: =IF(AND($H97<>"",N$66<>""),IF(AND(N$66>=$H97,N$66<$H97+$D$31),SUMIFS($L$90:$AK$90,$L$66:$AK$66,$H97)/$D$31,0),"") -> 0 | O97: =IF(AND($H97<>"",O$66<>""),IF(AND(O$66>=$H97,O$66<$H97+$D$31),SUMIFS($L$90:$AK$90,$L$66:$AK$66,$H97)/$D$31,0),"") -> 0 | P97: =IF(AND($H97<>"",P$66<>""),IF(AND(P$66>=$H97,P$66<$H97+$D$31),SUMIFS($L$90:$AK$90,$L$66:$AK$66,$H97)/$D$31,0),"") -> 0 | Q97: =IF(AND($H97<>"",Q$66<>""),IF(AND(Q$66>=$H97,Q$66<$H97+$D$31),SUMIFS($L$90:$AK$90,$L$66:$AK$66,$H97)/$D$31,0),"") -> 0 | R97: =IF(AND($H97<>"",R$66<>""),IF(AND(R$66>=$H97,R$66<$H97+$D$31),SUMIFS($L$90:$AK$90,$L$66:$AK$66,$H97)/$D$31,0),"") -> 0 | S97: =IF(AND($H97<>"",S$66<>""),IF(AND(S$66>=$H97,S$66<$H97+$D$31),SUMIFS($L$90:$AK$90,$L$66:$AK$66,$H97)/$D$31,0),"") -> 0 | ... AO97: =IF(AND($H97<>"",AO$66<>""),IF(AND(AO$66>=$H97,AO$66<$H97+$D$31),SUMIFS($L$90:$AK$90,$L$66:$AK$66,$H97)/$D$31,0),"") -> 0
H98: =IF(H97<>"",IF(H97+1<YEAR($E$4)+$E$5,H97+1,""),"") -> 2030 | L98: =IF(AND($H98<>"",L$66<>""),IF(AND(L$66>=$H98,L$66<$H98+$D$31),SUMIFS($L$90:$AK$90,$L$66:$AK$66,$H98)/$D$31,0),"") -> 0 | M98: =IF(AND($H98<>"",M$66<>""),IF(AND(M$66>=$H98,M$66<$H98+$D$31),SUMIFS($L$90:$AK$90,$L$66:$AK$66,$H98)/$D$31,0),"") -> 0 | N98: =IF(AND($H98<>"",N$66<>""),IF(AND(N$66>=$H98,N$66<$H98+$D$31),SUMIFS($L$90:$AK$90,$L$66:$AK$66,$H98)/$D$31,0),"") -> 0 | O98: =IF(AND($H98<>"",O$66<>""),IF(AND(O$66>=$H98,O$66<$H98+$D$31),SUMIFS($L$90:$AK$90,$L$66:$AK$66,$H98)/$D$31,0),"") -> 0 | P98: =IF(AND($H98<>"",P$66<>""),IF(AND(P$66>=$H98,P$66<$H98+$D$31),SUMIFS($L$90:$AK$90,$L$66:$AK$66,$H98)/$D$31,0),"") -> 0 | Q98: =IF(AND($H98<>"",Q$66<>""),IF(AND(Q$66>=$H98,Q$66<$H98+$D$31),SUMIFS($L$90:$AK$90,$L$66:$AK$66,$H98)/$D$31,0),"") -> 0 | R98: =IF(AND($H98<>"",R$66<>""),IF(AND(R$66>=$H98,R$66<$H98+$D$31),SUMIFS($L$90:$AK$90,$L$66:$AK$66,$H98)/$D$31,0),"") -> 0 | S98: =IF(AND($H98<>"",S$66<>""),IF(AND(S$66>=$H98,S$66<$H98+$D$31),SUMIFS($L$90:$AK$90,$L$66:$AK$66,$H98)/$D$31,0),"") -> 0 | ... AO98: =IF(AND($H98<>"",AO$66<>""),IF(AND(AO$66>=$H98,AO$66<$H98+$D$31),SUMIFS($L$90:$AK$90,$L$66:$AK$66,$H98)/$D$31,0),"") -> 0
H99: =IF(H98<>"",IF(H98+1<YEAR($E$4)+$E$5,H98+1,""),"") -> 2031 | L99: =IF(AND($H99<>"",L$66<>""),IF(AND(L$66>=$H99,L$66<$H99+$D$31),SUMIFS($L$90:$AK$90,$L$66:$AK$66,$H99)/$D$31,0),"") -> 0 | M99: =IF(AND($H99<>"",M$66<>""),IF(AND(M$66>=$H99,M$66<$H99+$D$31),SUMIFS($L$90:$AK$90,$L$66:$AK$66,$H99)/$D$31,0),"") -> 0 | N99: =IF(AND($H99<>"",N$66<>""),IF(AND(N$66>=$H99,N$66<$H99+$D$31),SUMIFS($L$90:$AK$90,$L$66:$AK$66,$H99)/$D$31,0),"") -> 0 | O99: =IF(AND($H99<>"",O$66<>""),IF(AND(O$66>=$H99,O$66<$H99+$D$31),SUMIFS($L$90:$AK$90,$L$66:$AK$66,$H99)/$D$31,0),"") -> 0 | P99: =IF(AND($H99<>"",P$66<>""),IF(AND(P$66>=$H99,P$66<$H99+$D$31),SUMIFS($L$90:$AK$90,$L$66:$AK$66,$H99)/$D$31,0),"") -> 0 | Q99: =IF(AND($H99<>"",Q$66<>""),IF(AND(Q$66>=$H99,Q$66<$H99+$D$31),SUMIFS($L$90:$AK$90,$L$66:$AK$66,$H99)/$D$31,0),"") -> 0 | R99: =IF(AND($H99<>"",R$66<>""),IF(AND(R$66>=$H99,R$66<$H99+$D$31),SUMIFS($L$90:$AK$90,$L$66:$AK$66,$H99)/$D$31,0),"") -> 0 | S99: =IF(AND($H99<>"",S$66<>""),IF(AND(S$66>=$H99,S$66<$H99+$D$31),SUMIFS($L$90:$AK$90,$L$66:$AK$66,$H99)/$D$31,0),"") -> 0 | ... AO99: =IF(AND($H99<>"",AO$66<>""),IF(AND(AO$66>=$H99,AO$66<$H99+$D$31),SUMIFS($L$90:$AK$90,$L$66:$AK$66,$H99)/$D$31,0),"") -> 0
H100: =IF(H99<>"",IF(H99+1<YEAR($E$4)+$E$5,H99+1,""),"") -> 2032 | L100: =IF(AND($H100<>"",L$66<>""),IF(AND(L$66>=$H100,L$66<$H100+$D$31),SUMIFS($L$90:$AK$90,$L$66:$AK$66,$H100)/$D$31,0),"") -> 0 | M100: =IF(AND($H100<>"",M$66<>""),IF(AND(M$66>=$H100,M$66<$H100+$D$31),SUMIFS($L$90:$AK$90,$L$66:$AK$66,$H100)/$D$31,0),"") -> 0 | N100: =IF(AND($H100<>"",N$66<>""),IF(AND(N$66>=$H100,N$66<$H100+$D$31),SUMIFS($L$90:$AK$90,$L$66:$AK$66,$H100)/$D$31,0),"") -> 0 | O100: =IF(AND($H100<>"",O$66<>""),IF(AND(O$66>=$H100,O$66<$H100+$D$31),SUMIFS($L$90:$AK$90,$L$66:$AK$66,$H100)/$D$31,0),"") -> 0 | P100: =IF(AND($H100<>"",P$66<>""),IF(AND(P$66>=$H100,P$66<$H100+$D$31),SUMIFS($L$90:$AK$90,$L$66:$AK$66,$H100)/$D$31,0),"") -> 0 | Q100: =IF(AND($H100<>"",Q$66<>""),IF(AND(Q$66>=$H100,Q$66<$H100+$D$31),SUMIFS($L$90:$AK$90,$L$66:$AK$66,$H100)/$D$31,0),"") -> 0 | R100: =IF(AND($H100<>"",R$66<>""),IF(AND(R$66>=$H100,R$66<$H100+$D$31),SUMIFS($L$90:$AK$90,$L$66:$AK$66,$H100)/$D$31,0),"") -> 0 | S100: =IF(AND($H100<>"",S$66<>""),IF(AND(S$66>=$H100,S$66<$H100+$D$31),SUMIFS($L$90:$AK$90,$L$66:$AK$66,$H100)/$D$31,0),"") -> 0 | ... AO100: =IF(AND($H100<>"",AO$66<>""),IF(AND(AO$66>=$H100,AO$66<$H100+$D$31),SUMIFS($L$90:$AK$90,$L$66:$AK$66,$H100)/$D$31,0),"") -> 0
H101: =IF(H100<>"",IF(H100+1<YEAR($E$4)+$E$5,H100+1,""),"") -> 2033 | L101: =IF(AND($H101<>"",L$66<>""),IF(AND(L$66>=$H101,L$66<$H101+$D$31),SUMIFS($L$90:$AK$90,$L$66:$AK$66,$H101)/$D$31,0),"") -> 0 | M101: =IF(AND($H101<>"",M$66<>""),IF(AND(M$66>=$H101,M$66<$H101+$D$31),SUMIFS($L$90:$AK$90,$L$66:$AK$66,$H101)/$D$31,0),"") -> 0 | N101: =IF(AND($H101<>"",N$66<>""),IF(AND(N$66>=$H101,N$66<$H101+$D$31),SUMIFS($L$90:$AK$90,$L$66:$AK$66,$H101)/$D$31,0),"") -> 0 | O101: =IF(AND($H101<>"",O$66<>""),IF(AND(O$66>=$H101,O$66<$H101+$D$31),SUMIFS($L$90:$AK$90,$L$66:$AK$66,$H101)/$D$31,0),"") -> 0 | P101: =IF(AND($H101<>"",P$66<>""),IF(AND(P$66>=$H101,P$66<$H101+$D$31),SUMIFS($L$90:$AK$90,$L$66:$AK$66,$H101)/$D$31,0),"") -> 0 | Q101: =IF(AND($H101<>"",Q$66<>""),IF(AND(Q$66>=$H101,Q$66<$H101+$D$31),SUMIFS($L$90:$AK$90,$L$66:$AK$66,$H101)/$D$31,0),"") -> 0 | R101: =IF(AND($H101<>"",R$66<>""),IF(AND(R$66>=$H101,R$66<$H101+$D$31),SUMIFS($L$90:$AK$90,$L$66:$AK$66,$H101)/$D$31,0),"") -> 0 | S101: =IF(AND($H101<>"",S$66<>""),IF(AND(S$66>=$H101,S$66<$H101+$D$31),SUMIFS($L$90:$AK$90,$L$66:$AK$66,$H101)/$D$31,0),"") -> 0 | ... AO101: =IF(AND($H101<>"",AO$66<>""),IF(AND(AO$66>=$H101,AO$66<$H101+$D$31),SUMIFS($L$90:$AK$90,$L$66:$AK$66,$H101)/$D$31,0),"") -> 0
H102: =IF(H101<>"",IF(H101+1<YEAR($E$4)+$E$5,H101+1,""),"") -> 2034 | L102: =IF(AND($H102<>"",L$66<>""),IF(AND(L$66>=$H102,L$66<$H102+$D$31),SUMIFS($L$90:$AK$90,$L$66:$AK$66,$H102)/$D$31,0),"") -> 0 | M102: =IF(AND($H102<>"",M$66<>""),IF(AND(M$66>=$H102,M$66<$H102+$D$31),SUMIFS($L$90:$AK$90,$L$66:$AK$66,$H102)/$D$31,0),"") -> 0 | N102: =IF(AND($H102<>"",N$66<>""),IF(AND(N$66>=$H102,N$66<$H102+$D$31),SUMIFS($L$90:$AK$90,$L$66:$AK$66,$H102)/$D$31,0),"") -> 0 | O102: =IF(AND($H102<>"",O$66<>""),IF(AND(O$66>=$H102,O$66<$H102+$D$31),SUMIFS($L$90:$AK$90,$L$66:$AK$66,$H102)/$D$31,0),"") -> 0 | P102: =IF(AND($H102<>"",P$66<>""),IF(AND(P$66>=$H102,P$66<$H102+$D$31),SUMIFS($L$90:$AK$90,$L$66:$AK$66,$H102)/$D$31,0),"") -> 0 | Q102: =IF(AND($H102<>"",Q$66<>""),IF(AND(Q$66>=$H102,Q$66<$H102+$D$31),SUMIFS($L$90:$AK$90,$L$66:$AK$66,$H102)/$D$31,0),"") -> 0 | R102: =IF(AND($H102<>"",R$66<>""),IF(AND(R$66>=$H102,R$66<$H102+$D$31),SUMIFS($L$90:$AK$90,$L$66:$AK$66,$H102)/$D$31,0),"") -> 0 | S102: =IF(AND($H102<>"",S$66<>""),IF(AND(S$66>=$H102,S$66<$H102+$D$31),SUMIFS($L$90:$AK$90,$L$66:$AK$66,$H102)/$D$31,0),"") -> 0 | ... AO102: =IF(AND($H102<>"",AO$66<>""),IF(AND(AO$66>=$H102,AO$66<$H102+$D$31),SUMIFS($L$90:$AK$90,$L$66:$AK$66,$H102)/$D$31,0),"") -> 0
H103: =IF(H102<>"",IF(H102+1<YEAR($E$4)+$E$5,H102+1,""),"") -> 2035 | L103: =IF(AND($H103<>"",L$66<>""),IF(AND(L$66>=$H103,L$66<$H103+$D$31),SUMIFS($L$90:$AK$90,$L$66:$AK$66,$H103)/$D$31,0),"") -> 0 | M103: =IF(AND($H103<>"",M$66<>""),IF(AND(M$66>=$H103,M$66<$H103+$D$31),SUMIFS($L$90:$AK$90,$L$66:$AK$66,$H103)/$D$31,0),"") -> 0 | N103: =IF(AND($H103<>"",N$66<>""),IF(AND(N$66>=$H103,N$66<$H103+$D$31),SUMIFS($L$90:$AK$90,$L$66:$AK$66,$H103)/$D$31,0),"") -> 0 | O103: =IF(AND($H103<>"",O$66<>""),IF(AND(O$66>=$H103,O$66<$H103+$D$31),SUMIFS($L$90:$AK$90,$L$66:$AK$66,$H103)/$D$31,0),"") -> 0 | P103: =IF(AND($H103<>"",P$66<>""),IF(AND(P$66>=$H103,P$66<$H103+$D$31),SUMIFS($L$90:$AK$90,$L$66:$AK$66,$H103)/$D$31,0),"") -> 0 | Q103: =IF(AND($H103<>"",Q$66<>""),IF(AND(Q$66>=$H103,Q$66<$H103+$D$31),SUMIFS($L$90:$AK$90,$L$66:$AK$66,$H103)/$D$31,0),"") -> 0 | R103: =IF(AND($H103<>"",R$66<>""),IF(AND(R$66>=$H103,R$66<$H103+$D$31),SUMIFS($L$90:$AK$90,$L$66:$AK$66,$H103)/$D$31,0),"") -> 0 | S103: =IF(AND($H103<>"",S$66<>""),IF(AND(S$66>=$H103,S$66<$H103+$D$31),SUMIFS($L$90:$AK$90,$L$66:$AK$66,$H103)/$D$31,0),"") -> 0 | ... AO103: =IF(AND($H103<>"",AO$66<>""),IF(AND(AO$66>=$H103,AO$66<$H103+$D$31),SUMIFS($L$90:$AK$90,$L$66:$AK$66,$H103)/$D$31,0),"") -> 0
... H120: =IF(H119<>"",IF(H119+1<YEAR($E$4)+$E$5,H119+1,""),"") | L120: =IF(AND($H120<>"",L$66<>""),IF(AND(L$66>=$H120,L$66<$H120+$D$31),SUMIFS($L$90:$AK$90,$L$66:$AK$66,$H120)/$D$31,0),"") | M120: =IF(AND($H120<>"",M$66<>""),IF(AND(M$66>=$H120,M$66<$H120+$D$31),SUMIFS($L$90:$AK$90,$L$66:$AK$66,$H120)/$D$31,0),"") | N120: =IF(AND($H120<>"",N$66<>""),IF(AND(N$66>=$H120,N$66<$H120+$D$31),SUMIFS($L$90:$AK$90,$L$66:$AK$66,$H120)/$D$31,0),"") | O120: =IF(AND($H120<>"",O$66<>""),IF(AND(O$66>=$H120,O$66<$H120+$D$31),SUMIFS($L$90:$AK$90,$L$66:$AK$66,$H120)/$D$31,0),"") | P120: =IF(AND($H120<>"",P$66<>""),IF(AND(P$66>=$H120,P$66<$H120+$D$31),SUMIFS($L$90:$AK$90,$L$66:$AK$66,$H120)/$D$31,0),"") | Q120: =IF(AND($H120<>"",Q$66<>""),IF(AND(Q$66>=$H120,Q$66<$H120+$D$31),SUMIFS($L$90:$AK$90,$L$66:$AK$66,$H120)/$D$31,0),"") | R120: =IF(AND($H120<>"",R$66<>""),IF(AND(R$66>=$H120,R$66<$H120+$D$31),SUMIFS($L$90:$AK$90,$L$66:$AK$66,$H120)/$D$31,0),"") | S120: =IF(AND($H120<>"",S$66<>""),IF(AND(S$66>=$H120,S$66<$H120+$D$31),SUMIFS($L$90:$AK$90,$L$66:$AK$66,$H120)/$D$31,0),"") | ... AO120: =IF(AND($H120<>"",AO$66<>""),IF(AND(AO$66>=$H120,AO$66<$H120+$D$31),SUMIFS($L$90:$AK$90,$L$66:$AK$66,$H120)/$D$31,0),"")
J121: Ristrutturazione | K121: - | L121: =IF(AND(TRUE,L$66<>""),SUMIFS(Flussi!$F:$F,Flussi!$B:$B,L$66,Flussi!$D:$D,$J121,Flussi!$E:$E,$K121,Flussi!$A:$A,$D$2),"") -> 0 | M121: =IF(AND(TRUE,M$66<>""),SUMIFS(Flussi!$F:$F,Flussi!$B:$B,M$66,Flussi!$D:$D,$J121,Flussi!$E:$E,$K121,Flussi!$A:$A,$D$2),"") -> 0 | N121: =IF(AND(TRUE,N$66<>""),SUMIFS(Flussi!$F:$F,Flussi!$B:$B,N$66,Flussi!$D:$D,$J121,Flussi!$E:$E,$K121,Flussi!$A:$A,$D$2),"") -> 0 | O121: =IF(AND(TRUE,O$66<>""),SUMIFS(Flussi!$F:$F,Flussi!$B:$B,O$66,Flussi!$D:$D,$J121,Flussi!$E:$E,$K121,Flussi!$A:$A,$D$2),"") -> 0 | P121: =IF(AND(TRUE,P$66<>""),SUMIFS(Flussi!$F:$F,Flussi!$B:$B,P$66,Flussi!$D:$D,$J121,Flussi!$E:$E,$K121,Flussi!$A:$A,$D$2),"") -> 0 | Q121: =IF(AND(TRUE,Q$66<>""),SUMIFS(Flussi!$F:$F,Flussi!$B:$B,Q$66,Flussi!$D:$D,$J121,Flussi!$E:$E,$K121,Flussi!$A:$A,$D$2),"") -> 0 | R121: =IF(AND(TRUE,R$66<>""),SUMIFS(Flussi!$F:$F,Flussi!$B:$B,R$66,Flussi!$D:$D,$J121,Flussi!$E:$E,$K121,Flussi!$A:$A,$D$2),"") -> 0 | S121: =IF(AND(TRUE,S$66<>""),SUMIFS(Flussi!$F:$F,Flussi!$B:$B,S$66,Flussi!$D:$D,$J121,Flussi!$E:$E,$K121,Flussi!$A:$A,$D$2),"") -> 0 | ... AO121: =IF(AND(TRUE,AO$66<>""),SUMIFS(Flussi!$F:$F,Flussi!$B:$B,AO$66,Flussi!$D:$D,$J121,Flussi!$E:$E,$K121,Flussi!$A:$A,$D$2),"") -> 0
H122: =YEAR($E$4) -> 2023 | L122: =IF(AND($H122<>"",L$66<>""),IF(AND(L$66>=$H122,L$66<$H122+$D$31),SUMIFS($L$121:$AK$121,$L$66:$AK$66,$H122)/$D$31,0),"") -> 0 | M122: =IF(AND($H122<>"",M$66<>""),IF(AND(M$66>=$H122,M$66<$H122+$D$31),SUMIFS($L$121:$AK$121,$L$66:$AK$66,$H122)/$D$31,0),"") -> 0 | N122: =IF(AND($H122<>"",N$66<>""),IF(AND(N$66>=$H122,N$66<$H122+$D$31),SUMIFS($L$121:$AK$121,$L$66:$AK$66,$H122)/$D$31,0),"") -> 0 | O122: =IF(AND($H122<>"",O$66<>""),IF(AND(O$66>=$H122,O$66<$H122+$D$31),SUMIFS($L$121:$AK$121,$L$66:$AK$66,$H122)/$D$31,0),"") -> 0 | P122: =IF(AND($H122<>"",P$66<>""),IF(AND(P$66>=$H122,P$66<$H122+$D$31),SUMIFS($L$121:$AK$121,$L$66:$AK$66,$H122)/$D$31,0),"") -> 0 | Q122: =IF(AND($H122<>"",Q$66<>""),IF(AND(Q$66>=$H122,Q$66<$H122+$D$31),SUMIFS($L$121:$AK$121,$L$66:$AK$66,$H122)/$D$31,0),"") -> 0 | R122: =IF(AND($H122<>"",R$66<>""),IF(AND(R$66>=$H122,R$66<$H122+$D$31),SUMIFS($L$121:$AK$121,$L$66:$AK$66,$H122)/$D$31,0),"") -> 0 | S122: =IF(AND($H122<>"",S$66<>""),IF(AND(S$66>=$H122,S$66<$H122+$D$31),SUMIFS($L$121:$AK$121,$L$66:$AK$66,$H122)/$D$31,0),"") -> 0 | ... AO122: =IF(AND($H122<>"",AO$66<>""),IF(AND(AO$66>=$H122,AO$66<$H122+$D$31),SUMIFS($L$121:$AK$121,$L$66:$AK$66,$H122)/$D$31,0),"") -> 0
H123: =IF(H122<>"",IF(H122+1<YEAR($E$4)+$E$5,H122+1,""),"") -> 2024 | L123: =IF(AND($H123<>"",L$66<>""),IF(AND(L$66>=$H123,L$66<$H123+$D$31),SUMIFS($L$121:$AK$121,$L$66:$AK$66,$H123)/$D$31,0),"") -> 0 | M123: =IF(AND($H123<>"",M$66<>""),IF(AND(M$66>=$H123,M$66<$H123+$D$31),SUMIFS($L$121:$AK$121,$L$66:$AK$66,$H123)/$D$31,0),"") -> 0 | N123: =IF(AND($H123<>"",N$66<>""),IF(AND(N$66>=$H123,N$66<$H123+$D$31),SUMIFS($L$121:$AK$121,$L$66:$AK$66,$H123)/$D$31,0),"") -> 0 | O123: =IF(AND($H123<>"",O$66<>""),IF(AND(O$66>=$H123,O$66<$H123+$D$31),SUMIFS($L$121:$AK$121,$L$66:$AK$66,$H123)/$D$31,0),"") -> 0 | P123: =IF(AND($H123<>"",P$66<>""),IF(AND(P$66>=$H123,P$66<$H123+$D$31),SUMIFS($L$121:$AK$121,$L$66:$AK$66,$H123)/$D$31,0),"") -> 0 | Q123: =IF(AND($H123<>"",Q$66<>""),IF(AND(Q$66>=$H123,Q$66<$H123+$D$31),SUMIFS($L$121:$AK$121,$L$66:$AK$66,$H123)/$D$31,0),"") -> 0 | R123: =IF(AND($H123<>"",R$66<>""),IF(AND(R$66>=$H123,R$66<$H123+$D$31),SUMIFS($L$121:$AK$121,$L$66:$AK$66,$H123)/$D$31,0),"") -> 0 | S123: =IF(AND($H123<>"",S$66<>""),IF(AND(S$66>=$H123,S$66<$H123+$D$31),SUMIFS($L$121:$AK$121,$L$66:$AK$66,$H123)/$D$31,0),"") -> 0 | ... AO123: =IF(AND($H123<>"",AO$66<>""),IF(AND(AO$66>=$H123,AO$66<$H123+$D$31),SUMIFS($L$121:$AK$121,$L$66:$AK$66,$H123)/$D$31,0),"") -> 0
H124: =IF(H123<>"",IF(H123+1<YEAR($E$4)+$E$5,H123+1,""),"") -> 2025 | L124: =IF(AND($H124<>"",L$66<>""),IF(AND(L$66>=$H124,L$66<$H124+$D$31),SUMIFS($L$121:$AK$121,$L$66:$AK$66,$H124)/$D$31,0),"") -> 0 | M124: =IF(AND($H124<>"",M$66<>""),IF(AND(M$66>=$H124,M$66<$H124+$D$31),SUMIFS($L$121:$AK$121,$L$66:$AK$66,$H124)/$D$31,0),"") -> 0 | N124: =IF(AND($H124<>"",N$66<>""),IF(AND(N$66>=$H124,N$66<$H124+$D$31),SUMIFS($L$121:$AK$121,$L$66:$AK$66,$H124)/$D$31,0),"") -> 0 | O124: =IF(AND($H124<>"",O$66<>""),IF(AND(O$66>=$H124,O$66<$H124+$D$31),SUMIFS($L$121:$AK$121,$L$66:$AK$66,$H124)/$D$31,0),"") -> 0 | P124: =IF(AND($H124<>"",P$66<>""),IF(AND(P$66>=$H124,P$66<$H124+$D$31),SUMIFS($L$121:$AK$121,$L$66:$AK$66,$H124)/$D$31,0),"") -> 0 | Q124: =IF(AND($H124<>"",Q$66<>""),IF(AND(Q$66>=$H124,Q$66<$H124+$D$31),SUMIFS($L$121:$AK$121,$L$66:$AK$66,$H124)/$D$31,0),"") -> 0 | R124: =IF(AND($H124<>"",R$66<>""),IF(AND(R$66>=$H124,R$66<$H124+$D$31),SUMIFS($L$121:$AK$121,$L$66:$AK$66,$H124)/$D$31,0),"") -> 0 | S124: =IF(AND($H124<>"",S$66<>""),IF(AND(S$66>=$H124,S$66<$H124+$D$31),SUMIFS($L$121:$AK$121,$L$66:$AK$66,$H124)/$D$31,0),"") -> 0 | ... AO124: =IF(AND($H124<>"",AO$66<>""),IF(AND(AO$66>=$H124,AO$66<$H124+$D$31),SUMIFS($L$121:$AK$121,$L$66:$AK$66,$H124)/$D$31,0),"") -> 0
H125: =IF(H124<>"",IF(H124+1<YEAR($E$4)+$E$5,H124+1,""),"") -> 2026 | L125: =IF(AND($H125<>"",L$66<>""),IF(AND(L$66>=$H125,L$66<$H125+$D$31),SUMIFS($L$121:$AK$121,$L$66:$AK$66,$H125)/$D$31,0),"") -> 0 | M125: =IF(AND($H125<>"",M$66<>""),IF(AND(M$66>=$H125,M$66<$H125+$D$31),SUMIFS($L$121:$AK$121,$L$66:$AK$66,$H125)/$D$31,0),"") -> 0 | N125: =IF(AND($H125<>"",N$66<>""),IF(AND(N$66>=$H125,N$66<$H125+$D$31),SUMIFS($L$121:$AK$121,$L$66:$AK$66,$H125)/$D$31,0),"") -> 0 | O125: =IF(AND($H125<>"",O$66<>""),IF(AND(O$66>=$H125,O$66<$H125+$D$31),SUMIFS($L$121:$AK$121,$L$66:$AK$66,$H125)/$D$31,0),"") -> 0 | P125: =IF(AND($H125<>"",P$66<>""),IF(AND(P$66>=$H125,P$66<$H125+$D$31),SUMIFS($L$121:$AK$121,$L$66:$AK$66,$H125)/$D$31,0),"") -> 0 | Q125: =IF(AND($H125<>"",Q$66<>""),IF(AND(Q$66>=$H125,Q$66<$H125+$D$31),SUMIFS($L$121:$AK$121,$L$66:$AK$66,$H125)/$D$31,0),"") -> 0 | R125: =IF(AND($H125<>"",R$66<>""),IF(AND(R$66>=$H125,R$66<$H125+$D$31),SUMIFS($L$121:$AK$121,$L$66:$AK$66,$H125)/$D$31,0),"") -> 0 | S125: =IF(AND($H125<>"",S$66<>""),IF(AND(S$66>=$H125,S$66<$H125+$D$31),SUMIFS($L$121:$AK$121,$L$66:$AK$66,$H125)/$D$31,0),"") -> 0 | ... AO125: =IF(AND($H125<>"",AO$66<>""),IF(AND(AO$66>=$H125,AO$66<$H125+$D$31),SUMIFS($L$121:$AK$121,$L$66:$AK$66,$H125)/$D$31,0),"") -> 0
H126: =IF(H125<>"",IF(H125+1<YEAR($E$4)+$E$5,H125+1,""),"") -> 2027 | L126: =IF(AND($H126<>"",L$66<>""),IF(AND(L$66>=$H126,L$66<$H126+$D$31),SUMIFS($L$121:$AK$121,$L$66:$AK$66,$H126)/$D$31,0),"") -> 0 | M126: =IF(AND($H126<>"",M$66<>""),IF(AND(M$66>=$H126,M$66<$H126+$D$31),SUMIFS($L$121:$AK$121,$L$66:$AK$66,$H126)/$D$31,0),"") -> 0 | N126: =IF(AND($H126<>"",N$66<>""),IF(AND(N$66>=$H126,N$66<$H126+$D$31),SUMIFS($L$121:$AK$121,$L$66:$AK$66,$H126)/$D$31,0),"") -> 0 | O126: =IF(AND($H126<>"",O$66<>""),IF(AND(O$66>=$H126,O$66<$H126+$D$31),SUMIFS($L$121:$AK$121,$L$66:$AK$66,$H126)/$D$31,0),"") -> 0 | P126: =IF(AND($H126<>"",P$66<>""),IF(AND(P$66>=$H126,P$66<$H126+$D$31),SUMIFS($L$121:$AK$121,$L$66:$AK$66,$H126)/$D$31,0),"") -> 0 | Q126: =IF(AND($H126<>"",Q$66<>""),IF(AND(Q$66>=$H126,Q$66<$H126+$D$31),SUMIFS($L$121:$AK$121,$L$66:$AK$66,$H126)/$D$31,0),"") -> 0 | R126: =IF(AND($H126<>"",R$66<>""),IF(AND(R$66>=$H126,R$66<$H126+$D$31),SUMIFS($L$121:$AK$121,$L$66:$AK$66,$H126)/$D$31,0),"") -> 0 | S126: =IF(AND($H126<>"",S$66<>""),IF(AND(S$66>=$H126,S$66<$H126+$D$31),SUMIFS($L$121:$AK$121,$L$66:$AK$66,$H126)/$D$31,0),"") -> 0 | ... AO126: =IF(AND($H126<>"",AO$66<>""),IF(AND(AO$66>=$H126,AO$66<$H126+$D$31),SUMIFS($L$121:$AK$121,$L$66:$AK$66,$H126)/$D$31,0),"") -> 0
H127: =IF(H126<>"",IF(H126+1<YEAR($E$4)+$E$5,H126+1,""),"") -> 2028 | L127: =IF(AND($H127<>"",L$66<>""),IF(AND(L$66>=$H127,L$66<$H127+$D$31),SUMIFS($L$121:$AK$121,$L$66:$AK$66,$H127)/$D$31,0),"") -> 0 | M127: =IF(AND($H127<>"",M$66<>""),IF(AND(M$66>=$H127,M$66<$H127+$D$31),SUMIFS($L$121:$AK$121,$L$66:$AK$66,$H127)/$D$31,0),"") -> 0 | N127: =IF(AND($H127<>"",N$66<>""),IF(AND(N$66>=$H127,N$66<$H127+$D$31),SUMIFS($L$121:$AK$121,$L$66:$AK$66,$H127)/$D$31,0),"") -> 0 | O127: =IF(AND($H127<>"",O$66<>""),IF(AND(O$66>=$H127,O$66<$H127+$D$31),SUMIFS($L$121:$AK$121,$L$66:$AK$66,$H127)/$D$31,0),"") -> 0 | P127: =IF(AND($H127<>"",P$66<>""),IF(AND(P$66>=$H127,P$66<$H127+$D$31),SUMIFS($L$121:$AK$121,$L$66:$AK$66,$H127)/$D$31,0),"") -> 0 | Q127: =IF(AND($H127<>"",Q$66<>""),IF(AND(Q$66>=$H127,Q$66<$H127+$D$31),SUMIFS($L$121:$AK$121,$L$66:$AK$66,$H127)/$D$31,0),"") -> 0 | R127: =IF(AND($H127<>"",R$66<>""),IF(AND(R$66>=$H127,R$66<$H127+$D$31),SUMIFS($L$121:$AK$121,$L$66:$AK$66,$H127)/$D$31,0),"") -> 0 | S127: =IF(AND($H127<>"",S$66<>""),IF(AND(S$66>=$H127,S$66<$H127+$D$31),SUMIFS($L$121:$AK$121,$L$66:$AK$66,$H127)/$D$31,0),"") -> 0 | ... AO127: =IF(AND($H127<>"",AO$66<>""),IF(AND(AO$66>=$H127,AO$66<$H127+$D$31),SUMIFS($L$121:$AK$121,$L$66:$AK$66,$H127)/$D$31,0),"") -> 0
H128: =IF(H127<>"",IF(H127+1<YEAR($E$4)+$E$5,H127+1,""),"") -> 2029 | L128: =IF(AND($H128<>"",L$66<>""),IF(AND(L$66>=$H128,L$66<$H128+$D$31),SUMIFS($L$121:$AK$121,$L$66:$AK$66,$H128)/$D$31,0),"") -> 0 | M128: =IF(AND($H128<>"",M$66<>""),IF(AND(M$66>=$H128,M$66<$H128+$D$31),SUMIFS($L$121:$AK$121,$L$66:$AK$66,$H128)/$D$31,0),"") -> 0 | N128: =IF(AND($H128<>"",N$66<>""),IF(AND(N$66>=$H128,N$66<$H128+$D$31),SUMIFS($L$121:$AK$121,$L$66:$AK$66,$H128)/$D$31,0),"") -> 0 | O128: =IF(AND($H128<>"",O$66<>""),IF(AND(O$66>=$H128,O$66<$H128+$D$31),SUMIFS($L$121:$AK$121,$L$66:$AK$66,$H128)/$D$31,0),"") -> 0 | P128: =IF(AND($H128<>"",P$66<>""),IF(AND(P$66>=$H128,P$66<$H128+$D$31),SUMIFS($L$121:$AK$121,$L$66:$AK$66,$H128)/$D$31,0),"") -> 0 | Q128: =IF(AND($H128<>"",Q$66<>""),IF(AND(Q$66>=$H128,Q$66<$H128+$D$31),SUMIFS($L$121:$AK$121,$L$66:$AK$66,$H128)/$D$31,0),"") -> 0 | R128: =IF(AND($H128<>"",R$66<>""),IF(AND(R$66>=$H128,R$66<$H128+$D$31),SUMIFS($L$121:$AK$121,$L$66:$AK$66,$H128)/$D$31,0),"") -> 0 | S128: =IF(AND($H128<>"",S$66<>""),IF(AND(S$66>=$H128,S$66<$H128+$D$31),SUMIFS($L$121:$AK$121,$L$66:$AK$66,$H128)/$D$31,0),"") -> 0 | ... AO128: =IF(AND($H128<>"",AO$66<>""),IF(AND(AO$66>=$H128,AO$66<$H128+$D$31),SUMIFS($L$121:$AK$121,$L$66:$AK$66,$H128)/$D$31,0),"") -> 0
H129: =IF(H128<>"",IF(H128+1<YEAR($E$4)+$E$5,H128+1,""),"") -> 2030 | L129: =IF(AND($H129<>"",L$66<>""),IF(AND(L$66>=$H129,L$66<$H129+$D$31),SUMIFS($L$121:$AK$121,$L$66:$AK$66,$H129)/$D$31,0),"") -> 0 | M129: =IF(AND($H129<>"",M$66<>""),IF(AND(M$66>=$H129,M$66<$H129+$D$31),SUMIFS($L$121:$AK$121,$L$66:$AK$66,$H129)/$D$31,0),"") -> 0 | N129: =IF(AND($H129<>"",N$66<>""),IF(AND(N$66>=$H129,N$66<$H129+$D$31),SUMIFS($L$121:$AK$121,$L$66:$AK$66,$H129)/$D$31,0),"") -> 0 | O129: =IF(AND($H129<>"",O$66<>""),IF(AND(O$66>=$H129,O$66<$H129+$D$31),SUMIFS($L$121:$AK$121,$L$66:$AK$66,$H129)/$D$31,0),"") -> 0 | P129: =IF(AND($H129<>"",P$66<>""),IF(AND(P$66>=$H129,P$66<$H129+$D$31),SUMIFS($L$121:$AK$121,$L$66:$AK$66,$H129)/$D$31,0),"") -> 0 | Q129: =IF(AND($H129<>"",Q$66<>""),IF(AND(Q$66>=$H129,Q$66<$H129+$D$31),SUMIFS($L$121:$AK$121,$L$66:$AK$66,$H129)/$D$31,0),"") -> 0 | R129: =IF(AND($H129<>"",R$66<>""),IF(AND(R$66>=$H129,R$66<$H129+$D$31),SUMIFS($L$121:$AK$121,$L$66:$AK$66,$H129)/$D$31,0),"") -> 0 | S129: =IF(AND($H129<>"",S$66<>""),IF(AND(S$66>=$H129,S$66<$H129+$D$31),SUMIFS($L$121:$AK$121,$L$66:$AK$66,$H129)/$D$31,0),"") -> 0 | ... AO129: =IF(AND($H129<>"",AO$66<>""),IF(AND(AO$66>=$H129,AO$66<$H129+$D$31),SUMIFS($L$121:$AK$121,$L$66:$AK$66,$H129)/$D$31,0),"") -> 0
H130: =IF(H129<>"",IF(H129+1<YEAR($E$4)+$E$5,H129+1,""),"") -> 2031 | L130: =IF(AND($H130<>"",L$66<>""),IF(AND(L$66>=$H130,L$66<$H130+$D$31),SUMIFS($L$121:$AK$121,$L$66:$AK$66,$H130)/$D$31,0),"") -> 0 | M130: =IF(AND($H130<>"",M$66<>""),IF(AND(M$66>=$H130,M$66<$H130+$D$31),SUMIFS($L$121:$AK$121,$L$66:$AK$66,$H130)/$D$31,0),"") -> 0 | N130: =IF(AND($H130<>"",N$66<>""),IF(AND(N$66>=$H130,N$66<$H130+$D$31),SUMIFS($L$121:$AK$121,$L$66:$AK$66,$H130)/$D$31,0),"") -> 0 | O130: =IF(AND($H130<>"",O$66<>""),IF(AND(O$66>=$H130,O$66<$H130+$D$31),SUMIFS($L$121:$AK$121,$L$66:$AK$66,$H130)/$D$31,0),"") -> 0 | P130: =IF(AND($H130<>"",P$66<>""),IF(AND(P$66>=$H130,P$66<$H130+$D$31),SUMIFS($L$121:$AK$121,$L$66:$AK$66,$H130)/$D$31,0),"") -> 0 | Q130: =IF(AND($H130<>"",Q$66<>""),IF(AND(Q$66>=$H130,Q$66<$H130+$D$31),SUMIFS($L$121:$AK$121,$L$66:$AK$66,$H130)/$D$31,0),"") -> 0 | R130: =IF(AND($H130<>"",R$66<>""),IF(AND(R$66>=$H130,R$66<$H130+$D$31),SUMIFS($L$121:$AK$121,$L$66:$AK$66,$H130)/$D$31,0),"") -> 0 | S130: =IF(AND($H130<>"",S$66<>""),IF(AND(S$66>=$H130,S$66<$H130+$D$31),SUMIFS($L$121:$AK$121,$L$66:$AK$66,$H130)/$D$31,0),"") -> 0 | ... AO130: =IF(AND($H130<>"",AO$66<>""),IF(AND(AO$66>=$H130,AO$66<$H130+$D$31),SUMIFS($L$121:$AK$121,$L$66:$AK$66,$H130)/$D$31,0),"") -> 0
H131: =IF(H130<>"",IF(H130+1<YEAR($E$4)+$E$5,H130+1,""),"") -> 2032 | L131: =IF(AND($H131<>"",L$66<>""),IF(AND(L$66>=$H131,L$66<$H131+$D$31),SUMIFS($L$121:$AK$121,$L$66:$AK$66,$H131)/$D$31,0),"") -> 0 | M131: =IF(AND($H131<>"",M$66<>""),IF(AND(M$66>=$H131,M$66<$H131+$D$31),SUMIFS($L$121:$AK$121,$L$66:$AK$66,$H131)/$D$31,0),"") -> 0 | N131: =IF(AND($H131<>"",N$66<>""),IF(AND(N$66>=$H131,N$66<$H131+$D$31),SUMIFS($L$121:$AK$121,$L$66:$AK$66,$H131)/$D$31,0),"") -> 0 | O131: =IF(AND($H131<>"",O$66<>""),IF(AND(O$66>=$H131,O$66<$H131+$D$31),SUMIFS($L$121:$AK$121,$L$66:$AK$66,$H131)/$D$31,0),"") -> 0 | P131: =IF(AND($H131<>"",P$66<>""),IF(AND(P$66>=$H131,P$66<$H131+$D$31),SUMIFS($L$121:$AK$121,$L$66:$AK$66,$H131)/$D$31,0),"") -> 0 | Q131: =IF(AND($H131<>"",Q$66<>""),IF(AND(Q$66>=$H131,Q$66<$H131+$D$31),SUMIFS($L$121:$AK$121,$L$66:$AK$66,$H131)/$D$31,0),"") -> 0 | R131: =IF(AND($H131<>"",R$66<>""),IF(AND(R$66>=$H131,R$66<$H131+$D$31),SUMIFS($L$121:$AK$121,$L$66:$AK$66,$H131)/$D$31,0),"") -> 0 | S131: =IF(AND($H131<>"",S$66<>""),IF(AND(S$66>=$H131,S$66<$H131+$D$31),SUMIFS($L$121:$AK$121,$L$66:$AK$66,$H131)/$D$31,0),"") -> 0 | ... AO131: =IF(AND($H131<>"",AO$66<>""),IF(AND(AO$66>=$H131,AO$66<$H131+$D$31),SUMIFS($L$121:$AK$121,$L$66:$AK$66,$H131)/$D$31,0),"") -> 0
H132: =IF(H131<>"",IF(H131+1<YEAR($E$4)+$E$5,H131+1,""),"") -> 2033 | L132: =IF(AND($H132<>"",L$66<>""),IF(AND(L$66>=$H132,L$66<$H132+$D$31),SUMIFS($L$121:$AK$121,$L$66:$AK$66,$H132)/$D$31,0),"") -> 0 | M132: =IF(AND($H132<>"",M$66<>""),IF(AND(M$66>=$H132,M$66<$H132+$D$31),SUMIFS($L$121:$AK$121,$L$66:$AK$66,$H132)/$D$31,0),"") -> 0 | N132: =IF(AND($H132<>"",N$66<>""),IF(AND(N$66>=$H132,N$66<$H132+$D$31),SUMIFS($L$121:$AK$121,$L$66:$AK$66,$H132)/$D$31,0),"") -> 0 | O132: =IF(AND($H132<>"",O$66<>""),IF(AND(O$66>=$H132,O$66<$H132+$D$31),SUMIFS($L$121:$AK$121,$L$66:$AK$66,$H132)/$D$31,0),"") -> 0 | P132: =IF(AND($H132<>"",P$66<>""),IF(AND(P$66>=$H132,P$66<$H132+$D$31),SUMIFS($L$121:$AK$121,$L$66:$AK$66,$H132)/$D$31,0),"") -> 0 | Q132: =IF(AND($H132<>"",Q$66<>""),IF(AND(Q$66>=$H132,Q$66<$H132+$D$31),SUMIFS($L$121:$AK$121,$L$66:$AK$66,$H132)/$D$31,0),"") -> 0 | R132: =IF(AND($H132<>"",R$66<>""),IF(AND(R$66>=$H132,R$66<$H132+$D$31),SUMIFS($L$121:$AK$121,$L$66:$AK$66,$H132)/$D$31,0),"") -> 0 | S132: =IF(AND($H132<>"",S$66<>""),IF(AND(S$66>=$H132,S$66<$H132+$D$31),SUMIFS($L$121:$AK$121,$L$66:$AK$66,$H132)/$D$31,0),"") -> 0 | ... AO132: =IF(AND($H132<>"",AO$66<>""),IF(AND(AO$66>=$H132,AO$66<$H132+$D$31),SUMIFS($L$121:$AK$121,$L$66:$AK$66,$H132)/$D$31,0),"") -> 0
H133: =IF(H132<>"",IF(H132+1<YEAR($E$4)+$E$5,H132+1,""),"") -> 2034 | L133: =IF(AND($H133<>"",L$66<>""),IF(AND(L$66>=$H133,L$66<$H133+$D$31),SUMIFS($L$121:$AK$121,$L$66:$AK$66,$H133)/$D$31,0),"") -> 0 | M133: =IF(AND($H133<>"",M$66<>""),IF(AND(M$66>=$H133,M$66<$H133+$D$31),SUMIFS($L$121:$AK$121,$L$66:$AK$66,$H133)/$D$31,0),"") -> 0 | N133: =IF(AND($H133<>"",N$66<>""),IF(AND(N$66>=$H133,N$66<$H133+$D$31),SUMIFS($L$121:$AK$121,$L$66:$AK$66,$H133)/$D$31,0),"") -> 0 | O133: =IF(AND($H133<>"",O$66<>""),IF(AND(O$66>=$H133,O$66<$H133+$D$31),SUMIFS($L$121:$AK$121,$L$66:$AK$66,$H133)/$D$31,0),"") -> 0 | P133: =IF(AND($H133<>"",P$66<>""),IF(AND(P$66>=$H133,P$66<$H133+$D$31),SUMIFS($L$121:$AK$121,$L$66:$AK$66,$H133)/$D$31,0),"") -> 0 | Q133: =IF(AND($H133<>"",Q$66<>""),IF(AND(Q$66>=$H133,Q$66<$H133+$D$31),SUMIFS($L$121:$AK$121,$L$66:$AK$66,$H133)/$D$31,0),"") -> 0 | R133: =IF(AND($H133<>"",R$66<>""),IF(AND(R$66>=$H133,R$66<$H133+$D$31),SUMIFS($L$121:$AK$121,$L$66:$AK$66,$H133)/$D$31,0),"") -> 0 | S133: =IF(AND($H133<>"",S$66<>""),IF(AND(S$66>=$H133,S$66<$H133+$D$31),SUMIFS($L$121:$AK$121,$L$66:$AK$66,$H133)/$D$31,0),"") -> 0 | ... AO133: =IF(AND($H133<>"",AO$66<>""),IF(AND(AO$66>=$H133,AO$66<$H133+$D$31),SUMIFS($L$121:$AK$121,$L$66:$AK$66,$H133)/$D$31,0),"") -> 0
H134: =IF(H133<>"",IF(H133+1<YEAR($E$4)+$E$5,H133+1,""),"") -> 2035 | L134: =IF(AND($H134<>"",L$66<>""),IF(AND(L$66>=$H134,L$66<$H134+$D$31),SUMIFS($L$121:$AK$121,$L$66:$AK$66,$H134)/$D$31,0),"") -> 0 | M134: =IF(AND($H134<>"",M$66<>""),IF(AND(M$66>=$H134,M$66<$H134+$D$31),SUMIFS($L$121:$AK$121,$L$66:$AK$66,$H134)/$D$31,0),"") -> 0 | N134: =IF(AND($H134<>"",N$66<>""),IF(AND(N$66>=$H134,N$66<$H134+$D$31),SUMIFS($L$121:$AK$121,$L$66:$AK$66,$H134)/$D$31,0),"") -> 0 | O134: =IF(AND($H134<>"",O$66<>""),IF(AND(O$66>=$H134,O$66<$H134+$D$31),SUMIFS($L$121:$AK$121,$L$66:$AK$66,$H134)/$D$31,0),"") -> 0 | P134: =IF(AND($H134<>"",P$66<>""),IF(AND(P$66>=$H134,P$66<$H134+$D$31),SUMIFS($L$121:$AK$121,$L$66:$AK$66,$H134)/$D$31,0),"") -> 0 | Q134: =IF(AND($H134<>"",Q$66<>""),IF(AND(Q$66>=$H134,Q$66<$H134+$D$31),SUMIFS($L$121:$AK$121,$L$66:$AK$66,$H134)/$D$31,0),"") -> 0 | R134: =IF(AND($H134<>"",R$66<>""),IF(AND(R$66>=$H134,R$66<$H134+$D$31),SUMIFS($L$121:$AK$121,$L$66:$AK$66,$H134)/$D$31,0),"") -> 0 | S134: =IF(AND($H134<>"",S$66<>""),IF(AND(S$66>=$H134,S$66<$H134+$D$31),SUMIFS($L$121:$AK$121,$L$66:$AK$66,$H134)/$D$31,0),"") -> 0 | ... AO134: =IF(AND($H134<>"",AO$66<>""),IF(AND(AO$66>=$H134,AO$66<$H134+$D$31),SUMIFS($L$121:$AK$121,$L$66:$AK$66,$H134)/$D$31,0),"") -> 0
... H151: =IF(H150<>"",IF(H150+1<YEAR($E$4)+$E$5,H150+1,""),"") | L151: =IF(AND($H151<>"",L$66<>""),IF(AND(L$66>=$H151,L$66<$H151+$D$31),SUMIFS($L$121:$AK$121,$L$66:$AK$66,$H151)/$D$31,0),"") | M151: =IF(AND($H151<>"",M$66<>""),IF(AND(M$66>=$H151,M$66<$H151+$D$31),SUMIFS($L$121:$AK$121,$L$66:$AK$66,$H151)/$D$31,0),"") | N151: =IF(AND($H151<>"",N$66<>""),IF(AND(N$66>=$H151,N$66<$H151+$D$31),SUMIFS($L$121:$AK$121,$L$66:$AK$66,$H151)/$D$31,0),"") | O151: =IF(AND($H151<>"",O$66<>""),IF(AND(O$66>=$H151,O$66<$H151+$D$31),SUMIFS($L$121:$AK$121,$L$66:$AK$66,$H151)/$D$31,0),"") | P151: =IF(AND($H151<>"",P$66<>""),IF(AND(P$66>=$H151,P$66<$H151+$D$31),SUMIFS($L$121:$AK$121,$L$66:$AK$66,$H151)/$D$31,0),"") | Q151: =IF(AND($H151<>"",Q$66<>""),IF(AND(Q$66>=$H151,Q$66<$H151+$D$31),SUMIFS($L$121:$AK$121,$L$66:$AK$66,$H151)/$D$31,0),"") | R151: =IF(AND($H151<>"",R$66<>""),IF(AND(R$66>=$H151,R$66<$H151+$D$31),SUMIFS($L$121:$AK$121,$L$66:$AK$66,$H151)/$D$31,0),"") | S151: =IF(AND($H151<>"",S$66<>""),IF(AND(S$66>=$H151,S$66<$H151+$D$31),SUMIFS($L$121:$AK$121,$L$66:$AK$66,$H151)/$D$31,0),"") | ... AO151: =IF(AND($H151<>"",AO$66<>""),IF(AND(AO$66>=$H151,AO$66<$H151+$D$31),SUMIFS($L$121:$AK$121,$L$66:$AK$66,$H151)/$D$31,0),"")
J152: Arredamento | K152: - | L152: =IF(AND(TRUE,L$66<>""),SUMIFS(Flussi!$F:$F,Flussi!$B:$B,L$66,Flussi!$D:$D,$J152,Flussi!$E:$E,$K152,Flussi!$A:$A,$D$2),"") -> 0 | M152: =IF(AND(TRUE,M$66<>""),SUMIFS(Flussi!$F:$F,Flussi!$B:$B,M$66,Flussi!$D:$D,$J152,Flussi!$E:$E,$K152,Flussi!$A:$A,$D$2),"") -> 0 | N152: =IF(AND(TRUE,N$66<>""),SUMIFS(Flussi!$F:$F,Flussi!$B:$B,N$66,Flussi!$D:$D,$J152,Flussi!$E:$E,$K152,Flussi!$A:$A,$D$2),"") -> 0 | O152: =IF(AND(TRUE,O$66<>""),SUMIFS(Flussi!$F:$F,Flussi!$B:$B,O$66,Flussi!$D:$D,$J152,Flussi!$E:$E,$K152,Flussi!$A:$A,$D$2),"") -> 0 | P152: =IF(AND(TRUE,P$66<>""),SUMIFS(Flussi!$F:$F,Flussi!$B:$B,P$66,Flussi!$D:$D,$J152,Flussi!$E:$E,$K152,Flussi!$A:$A,$D$2),"") -> 0 | Q152: =IF(AND(TRUE,Q$66<>""),SUMIFS(Flussi!$F:$F,Flussi!$B:$B,Q$66,Flussi!$D:$D,$J152,Flussi!$E:$E,$K152,Flussi!$A:$A,$D$2),"") -> 0 | R152: =IF(AND(TRUE,R$66<>""),SUMIFS(Flussi!$F:$F,Flussi!$B:$B,R$66,Flussi!$D:$D,$J152,Flussi!$E:$E,$K152,Flussi!$A:$A,$D$2),"") -> 0 | S152: =IF(AND(TRUE,S$66<>""),SUMIFS(Flussi!$F:$F,Flussi!$B:$B,S$66,Flussi!$D:$D,$J152,Flussi!$E:$E,$K152,Flussi!$A:$A,$D$2),"") -> 0 | ... AO152: =IF(AND(TRUE,AO$66<>""),SUMIFS(Flussi!$F:$F,Flussi!$B:$B,AO$66,Flussi!$D:$D,$J152,Flussi!$E:$E,$K152,Flussi!$A:$A,$D$2),"") -> 0
H153: =YEAR($E$4) -> 2023 | L153: =IF(AND($H153<>"",L$66<>""),IF(AND(L$66>=$H153,L$66<$H153+$D$31),SUMIFS($L$152:$AK$152,$L$66:$AK$66,$H153)/$D$31,0),"") -> 0 | M153: =IF(AND($H153<>"",M$66<>""),IF(AND(M$66>=$H153,M$66<$H153+$D$31),SUMIFS($L$152:$AK$152,$L$66:$AK$66,$H153)/$D$31,0),"") -> 0 | N153: =IF(AND($H153<>"",N$66<>""),IF(AND(N$66>=$H153,N$66<$H153+$D$31),SUMIFS($L$152:$AK$152,$L$66:$AK$66,$H153)/$D$31,0),"") -> 0 | O153: =IF(AND($H153<>"",O$66<>""),IF(AND(O$66>=$H153,O$66<$H153+$D$31),SUMIFS($L$152:$AK$152,$L$66:$AK$66,$H153)/$D$31,0),"") -> 0 | P153: =IF(AND($H153<>"",P$66<>""),IF(AND(P$66>=$H153,P$66<$H153+$D$31),SUMIFS($L$152:$AK$152,$L$66:$AK$66,$H153)/$D$31,0),"") -> 0 | Q153: =IF(AND($H153<>"",Q$66<>""),IF(AND(Q$66>=$H153,Q$66<$H153+$D$31),SUMIFS($L$152:$AK$152,$L$66:$AK$66,$H153)/$D$31,0),"") -> 0 | R153: =IF(AND($H153<>"",R$66<>""),IF(AND(R$66>=$H153,R$66<$H153+$D$31),SUMIFS($L$152:$AK$152,$L$66:$AK$66,$H153)/$D$31,0),"") -> 0 | S153: =IF(AND($H153<>"",S$66<>""),IF(AND(S$66>=$H153,S$66<$H153+$D$31),SUMIFS($L$152:$AK$152,$L$66:$AK$66,$H153)/$D$31,0),"") -> 0 | ... AO153: =IF(AND($H153<>"",AO$66<>""),IF(AND(AO$66>=$H153,AO$66<$H153+$D$31),SUMIFS($L$152:$AK$152,$L$66:$AK$66,$H153)/$D$31,0),"") -> 0
...

Sheet DiazBox
B1: Dati generali
B2: Asset | D2: DiazBox
B3: Acquisto | C3: Valore immobile | D3: -13000 | E3: =E4 -> 45036 | F3: =EDATE($E$4,$E$5*12)-1 -> 46131
B4: Data acquisto | E4: 45036 | F4: 46387 | I4: IRR | J4: =$L$295 -> 0.041383851
B5: Anni investimento | E5: 3 | I5: NPV | J5: =MAX(293:293) -> 1349.8132
B6: Acquisto da? | E6: Privato/Imprese
B7: Prima casa? | E7: NO
B8: Rendita catastale | C8: - | D8: 57.84 | E8: =$E$4 -> 45036 | F8: =EDATE($E$4,$E$5*12)-1 -> 46131
B9: Rivalutazione | C9: - | D9: 0 | E9: =$E$4 -> 45036 | F9: =EDATE($E$4,$E$5*12)-1 -> 46131
B11: Ricavi
B12: Affitto | C12: Box | D12: =30*12+115*12*0.57-99 -> 1047.6 | E12: =$E$4 -> 45036 | F12: =EDATE($E$4,$E$5*12)-1 -> 46131
B13: Vendita | C13: Box | D13: =-(D3+D18+D19)+1500 -> 18092.61 | E13: =EDATE($E$4,$E$5*12)-1 -> 46131 | F13: 46387
B14: Vendita | C14: Intermediazione | D14: 0 | E14: =EDATE($E$4,$E$5*12)-1 -> 46131 | F14: =EDATE($E$4,$E$5*12)-1 -> 46131 | H14: $D$3*(1+D10)^E5
B15: Vendita | C15: Plusvalenza | D15: =-(D13+(D3+D19))*0.26 -> -707.2 | E15: =EDATE($E$4,$E$5*12)-1 -> 46131 | F15: 46387
B17: Costi
B18: Avviamento | C18: Intermediazione | D18: -1220 | E18: =$E$4 -> 45036 | F18: =EDATE($E$4,$E$5*12)-1 -> 46131
B19: Avviamento | C19: Notaio | D19: -2372.61 | E19: =$E$4 -> 45036 | F19: =EDATE($E$4,$E$5*12)-1 -> 46131
B20: Condominio | C20: - | D20: -100 | E20: =$E$4 -> 45036 | F20: =EDATE($E$4,$E$5*12)-1 -> 46131
B21: Assicurazione | C21: - | D21: 0 | E21: =$E$4 -> 45036 | F21: =EDATE($E$4,$E$5*12)-1 -> 46131
B22: Utenze | C22: Gas | D22: 0 | E22: =$E$4 -> 45036 | F22: =EDATE($E$4,$E$5*12)-1 -> 46131
B23: Utenze | C23: Luce | D23: 0 | E23: =$E$4 -> 45036 | F23: =EDATE($E$4,$E$5*12)-1 -> 46131
B24: Manutenzione ordinaria | C24: - | D24: 0 | E24: =$E$4 -> 45036 | F24: =EDATE($E$4,$E$5*12)-1 -> 46131
B25: Manutenzione straordinaria | C25: - | D25: -25 | E25: =$E$4 -> 45036 | F25: =EDATE($E$4,$E$5*12)-1 -> 46131
B27: Ammortamenti
B28: Anni | D28: =SUMIFS(#REF!,#REF!,$B28) -> #REF!
B30: Oneri finanziari
B31: Mutuo | C31: Importo | D31: 0
B32: Mutuo | C32: Periodi | D32: 12
B33: Mutuo | C33: Anni | D33: 20
B34: Mutuo | C34: Decorrenza | D34: 44958
B35: Mutuo | C35: Commissioni | D35: 0
B36: Mutuo | C36: Tasso | D36: 0 | E36: 45658 | F36: 46539
B37: Mutuo | C37: Tasso | D37: 0 | E37: =EDATE(F36,1) -> 46569 | F37: 47270
B38: Mutuo | C38: Tasso | D38: 0 | E38: =EDATE(F37,1) -> 47300 | F38: =EDATE(E38,25*12) -> 56431
B39: Mutuo | C39: Rimborso | D39: 0 | E39: 45658 | F39: 45658
B44: Tasse
B45: Imposte | C45: Registro | D45: =-IF($E$7="SI",MAX(2%*$D$8*105%*120,1000),MAX(9%*$D$8*105%*120,1000)) -> -1000 | E45: =$E$4 -> 45036 | F45: =EDATE(E45,$E$5*12)-1 -> 46131
B46: Imposte | C46: Ipotecaria | D46: =-IF($E$6="Privato/Imprese",50,200) -> -50 | E46: =$E$4 -> 45036 | F46: =EDATE(E46,$E$5*12)-1 -> 46131
B47: Imposte | C47: Catastale | D47: =-IF($E$6="Privato/Imprese",50,200) -> -50 | E47: =$E$4 -> 45036 | F47: =EDATE(E47,$E$5*12)-1 -> 46131
B48: Imposte | C48: IMU | D48: =-IF($E$7="SI",0,$D$8*1.05*160*1.06%) -> -103.00147 | E48: =$E$4 -> 45036 | F48: =EDATE(E48,$E$5*12)-1 -> 46131
B49: Imposte | C49: TARI | D49: -45 | E49: =$E$4 -> 45036 | F49: =EDATE(E49,$E$5*12)-1 -> 46131
B51: Detrazioni
B52: Mutuo | C52: Cap detrazione | D52: =4000*$D$31/294000 -> 0 | E52: Ripartizione mutuo
B53: Mutuo | C53: % detrazione | D53: 0.19
B63: Offset detrazioni | D63: 1
I64: Profit & Loss
I66: Tipo | J66: Servizio | K66: Voce | L66: =YEAR($E$4) -> 2023 | M66: =IF(L66<>"",IF(L66+1<=YEAR($E$4)+$E$5+$D$63,L66+1,""),"") -> 2024 | N66: =IF(M66<>"",IF(M66+1<=YEAR($E$4)+$E$5+$D$63,M66+1,""),"") -> 2025 | O66: =IF(N66<>"",IF(N66+1<=YEAR($E$4)+$E$5+$D$63,N66+1,""),"") -> 2026 | P66: =IF(O66<>"",IF(O66+1<=YEAR($E$4)+$E$5+$D$63,O66+1,""),"") -> 2027 | Q66: =IF(P66<>"",IF(P66+1<=YEAR($E$4)+$E$5+$D$63,P66+1,""),"") | R66: =IF(Q66<>"",IF(Q66+1<=YEAR($E$4)+$E$5+$D$63,Q66+1,""),"") | S66: =IF(R66<>"",IF(R66+1<=YEAR($E$4)+$E$5+$D$63,R66+1,""),"") | T66: =IF(S66<>"",IF(S66+1<=YEAR($E$4)+$E$5+$D$63,S66+1,""),"") | ... AO66: =IF(AN66<>"",IF(AN66+1<=YEAR($E$4)+$E$5+$D$63,AN66+1,""),"")
J68: Affitto | K68: Alloggio | L68: =IF(AND(TRUE,L$66<>""),SUMIFS(Flussi!$F:$F,Flussi!$B:$B,L$66,Flussi!$D:$D,$J68,Flussi!$E:$E,$K68,Flussi!$A:$A,$D$2),"") -> 0 | M68: =IF(AND(TRUE,M$66<>""),SUMIFS(Flussi!$F:$F,Flussi!$B:$B,M$66,Flussi!$D:$D,$J68,Flussi!$E:$E,$K68,Flussi!$A:$A,$D$2),"") -> 0 | N68: =IF(AND(TRUE,N$66<>""),SUMIFS(Flussi!$F:$F,Flussi!$B:$B,N$66,Flussi!$D:$D,$J68,Flussi!$E:$E,$K68,Flussi!$A:$A,$D$2),"") -> 0 | O68: =IF(AND(TRUE,O$66<>""),SUMIFS(Flussi!$F:$F,Flussi!$B:$B,O$66,Flussi!$D:$D,$J68,Flussi!$E:$E,$K68,Flussi!$A:$A,$D$2),"") -> 0 | P68: =IF(AND(TRUE,P$66<>""),SUMIFS(Flussi!$F:$F,Flussi!$B:$B,P$66,Flussi!$D:$D,$J68,Flussi!$E:$E,$K68,Flussi!$A:$A,$D$2),"") -> 0 | Q68: =IF(AND(TRUE,Q$66<>""),SUMIFS(Flussi!$F:$F,Flussi!$B:$B,Q$66,Flussi!$D:$D,$J68,Flussi!$E:$E,$K68,Flussi!$A:$A,$D$2),"") | R68: =IF(AND(TRUE,R$66<>""),SUMIFS(Flussi!$F:$F,Flussi!$B:$B,R$66,Flussi!$D:$D,$J68,Flussi!$E:$E,$K68,Flussi!$A:$A,$D$2),"") | S68: =IF(AND(TRUE,S$66<>""),SUMIFS(Flussi!$F:$F,Flussi!$B:$B,S$66,Flussi!$D:$D,$J68,Flussi!$E:$E,$K68,Flussi!$A:$A,$D$2),"") | ... AO68: =IF(AND(TRUE,AO$66<>""),SUMIFS(Flussi!$F:$F,Flussi!$B:$B,AO$66,Flussi!$D:$D,$J68,Flussi!$E:$E,$K68,Flussi!$A:$A,$D$2),"")
J69: Affitto | K69: Box | L69: =IF(AND(TRUE,L$66<>""),SUMIFS(Flussi!$F:$F,Flussi!$B:$B,L$66,Flussi!$D:$D,$J69,Flussi!$E:$E,$K69,Flussi!$A:$A,$D$2),"") -> 0 | M69: =IF(AND(TRUE,M$66<>""),SUMIFS(Flussi!$F:$F,Flussi!$B:$B,M$66,Flussi!$D:$D,$J69,Flussi!$E:$E,$K69,Flussi!$A:$A,$D$2),"") -> 0 | N69: =IF(AND(TRUE,N$66<>""),SUMIFS(Flussi!$F:$F,Flussi!$B:$B,N$66,Flussi!$D:$D,$J69,Flussi!$E:$E,$K69,Flussi!$A:$A,$D$2),"") -> 893.4 | O69: =IF(AND(TRUE,O$66<>""),SUMIFS(Flussi!$F:$F,Flussi!$B:$B,O$66,Flussi!$D:$D,$J69,Flussi!$E:$E,$K69,Flussi!$A:$A,$D$2),"") -> 287 | P69: =IF(AND(TRUE,P$66<>""),SUMIFS(Flussi!$F:$F,Flussi!$B:$B,P$66,Flussi!$D:$D,$J69,Flussi!$E:$E,$K69,Flussi!$A:$A,$D$2),"") -> 0 | Q69: =IF(AND(TRUE,Q$66<>""),SUMIFS(Flussi!$F:$F,Flussi!$B:$B,Q$66,Flussi!$D:$D,$J69,Flussi!$E:$E,$K69,Flussi!$A:$A,$D$2),"") | R69: =IF(AND(TRUE,R$66<>""),SUMIFS(Flussi!$F:$F,Flussi!$B:$B,R$66,Flussi!$D:$D,$J69,Flussi!$E:$E,$K69,Flussi!$A:$A,$D$2),"") | S69: =IF(AND(TRUE,S$66<>""),SUMIFS(Flussi!$F:$F,Flussi!$B:$B,S$66,Flussi!$D:$D,$J69,Flussi!$E:$E,$K69,Flussi!$A:$A,$D$2),"") | ... AO69: =IF(AND(TRUE,AO$66<>""),SUMIFS(Flussi!$F:$F,Flussi!$B:$B,AO$66,Flussi!$D:$D,$J69,Flussi!$E:$E,$K69,Flussi!$A:$A,$D$2),"")
J70: Vendita | K70: Alloggio | L70: =IF(AND(TRUE,L$66<>""),SUMIFS(Flussi!$F:$F,Flussi!$B:$B,L$66,Flussi!$D:$D,$J70,Flussi!$E:$E,$K70,Flussi!$A:$A,$D$2),"") -> 0 | M70: =IF(AND(TRUE,M$66<>""),SUMIFS(Flussi!$F:$F,Flussi!$B:$B,M$66,Flussi!$D:$D,$J70,Flussi!$E:$E,$K70,Flussi!$A:$A,$D$2),"") -> 0 | N70: =IF(AND(TRUE,N$66<>""),SUMIFS(Flussi!$F:$F,Flussi!$B:$B,N$66,Flussi!$D:$D,$J70,Flussi!$E:$E,$K70,Flussi!$A:$A,$D$2),"") -> 0 | O70: =IF(AND(TRUE,O$66<>""),SUMIFS(Flussi!$F:$F,Flussi!$B:$B,O$66,Flussi!$D:$D,$J70,Flussi!$E:$E,$K70,Flussi!$A:$A,$D$2),"") -> 0 | P70: =IF(AND(TRUE,P$66<>""),SUMIFS(Flussi!$F:$F,Flussi!$B:$B,P$66,Flussi!$D:$D,$J70,Flussi!$E:$E,$K70,Flussi!$A:$A,$D$2),"") -> 0 | Q70: =IF(AND(TRUE,Q$66<>""),SUMIFS(Flussi!$F:$F,Flussi!$B:$B,Q$66,Flussi!$D:$D,$J70,Flussi!$E:$E,$K70,Flussi!$A:$A,$D$2),"") | R70: =IF(AND(TRUE,R$66<>""),SUMIFS(Flussi!$F:$F,Flussi!$B:$B,R$66,Flussi!$D:$D,$J70,Flussi!$E:$E,$K70,Flussi!$A:$A,$D$2),"") | S70: =IF(AND(TRUE,S$66<>""),SUMIFS(Flussi!$F:$F,Flussi!$B:$B,S$66,Flussi!$D:$D,$J70,Flussi!$E:$E,$K70,Flussi!$A:$A,$D$2),"") | ... AO70: =IF(AND(TRUE,AO$66<>""),SUMIFS(Flussi!$F:$F,Flussi!$B:$B,AO$66,Flussi!$D:$D,$J70,Flussi!$E:$E,$K70,Flussi!$A:$A,$D$2),"")
J71: Vendita | K71: Box | L71: =IF(AND(TRUE,L$66<>""),SUMIFS(Flussi!$F:$F,Flussi!$B:$B,L$66,Flussi!$D:$D,$J71,Flussi!$E:$E,$K71,Flussi!$A:$A,$D$2),"") -> 0 | M71: =IF(AND(TRUE,M$66<>""),SUMIFS(Flussi!$F:$F,Flussi!$B:$B,M$66,Flussi!$D:$D,$J71,Flussi!$E:$E,$K71,Flussi!$A:$A,$D$2),"") -> 0 | N71: =IF(AND(TRUE,N$66<>""),SUMIFS(Flussi!$F:$F,Flussi!$B:$B,N$66,Flussi!$D:$D,$J71,Flussi!$E:$E,$K71,Flussi!$A:$A,$D$2),"") -> 0 | O71: =IF(AND(TRUE,O$66<>""),SUMIFS(Flussi!$F:$F,Flussi!$B:$B,O$66,Flussi!$D:$D,$J71,Flussi!$E:$E,$K71,Flussi!$A:$A,$D$2),"") -> 18092.61 | P71: =IF(AND(TRUE,P$66<>""),SUMIFS(Flussi!$F:$F,Flussi!$B:$B,P$66,Flussi!$D:$D,$J71,Flussi!$E:$E,$K71,Flussi!$A:$A,$D$2),"") -> 0 | Q71: =IF(AND(TRUE,Q$66<>""),SUMIFS(Flussi!$F:$F,Flussi!$B:$B,Q$66,Flussi!$D:$D,$J71,Flussi!$E:$E,$K71,Flussi!$A:$A,$D$2),"") | R71: =IF(AND(TRUE,R$66<>""),SUMIFS(Flussi!$F:$F,Flussi!$B:$B,R$66,Flussi!$D:$D,$J71,Flussi!$E:$E,$K71,Flussi!$A:$A,$D$2),"") | S71: =IF(AND(TRUE,S$66<>""),SUMIFS(Flussi!$F:$F,Flussi!$B:$B,S$66,Flussi!$D:$D,$J71,Flussi!$E:$E,$K71,Flussi!$A:$A,$D$2),"") | ... AO71: =IF(AND(TRUE,AO$66<>""),SUMIFS(Flussi!$F:$F,Flussi!$B:$B,AO$66,Flussi!$D:$D,$J71,Flussi!$E:$E,$K71,Flussi!$A:$A,$D$2),"")
J72: Vendita | K72: Intermediazione | L72: =IF(AND(TRUE,L$66<>""),SUMIFS(Flussi!$F:$F,Flussi!$B:$B,L$66,Flussi!$D:$D,$J72,Flussi!$E:$E,$K72,Flussi!$A:$A,$D$2),"") -> 0 | M72: =IF(AND(TRUE,M$66<>""),SUMIFS(Flussi!$F:$F,Flussi!$B:$B,M$66,Flussi!$D:$D,$J72,Flussi!$E:$E,$K72,Flussi!$A:$A,$D$2),"") -> 0 | N72: =IF(AND(TRUE,N$66<>""),SUMIFS(Flussi!$F:$F,Flussi!$B:$B,N$66,Flussi!$D:$D,$J72,Flussi!$E:$E,$K72,Flussi!$A:$A,$D$2),"") -> 0 | O72: =IF(AND(TRUE,O$66<>""),SUMIFS(Flussi!$F:$F,Flussi!$B:$B,O$66,Flussi!$D:$D,$J72,Flussi!$E:$E,$K72,Flussi!$A:$A,$D$2),"") -> 0 | P72: =IF(AND(TRUE,P$66<>""),SUMIFS(Flussi!$F:$F,Flussi!$B:$B,P$66,Flussi!$D:$D,$J72,Flussi!$E:$E,$K72,Flussi!$A:$A,$D$2),"") -> 0 | Q72: =IF(AND(TRUE,Q$66<>""),SUMIFS(Flussi!$F:$F,Flussi!$B:$B,Q$66,Flussi!$D:$D,$J72,Flussi!$E:$E,$K72,Flussi!$A:$A,$D$2),"") | R72: =IF(AND(TRUE,R$66<>""),SUMIFS(Flussi!$F:$F,Flussi!$B:$B,R$66,Flussi!$D:$D,$J72,Flussi!$E:$E,$K72,Flussi!$A:$A,$D$2),"") | S72: =IF(AND(TRUE,S$66<>""),SUMIFS(Flussi!$F:$F,Flussi!$B:$B,S$66,Flussi!$D:$D,$J72,Flussi!$E:$E,$K72,Flussi!$A:$A,$D$2),"") | ... AO72: =IF(AND(TRUE,AO$66<>""),SUMIFS(Flussi!$F:$F,Flussi!$B:$B,AO$66,Flussi!$D:$D,$J72,Flussi!$E:$E,$K72,Flussi!$A:$A,$D$2),"")
I73: Ricavi | K73: P&L | L73: =IF(AND(TRUE,L$66<>""),SUM(L68:L72),"") -> 0 | M73: =IF(AND(TRUE,M$66<>""),SUM(M68:M72),"") -> 0 | N73: =IF(AND(TRUE,N$66<>""),SUM(N68:N72),"") -> 893.4 | O73: =IF(AND(TRUE,O$66<>""),SUM(O68:O72),"") -> 18379.61 | P73: =IF(AND(TRUE,P$66<>""),SUM(P68:P72),"") -> 0 | Q73: =IF(AND(TRUE,Q$66<>""),SUM(Q68:Q72),"") | R73: =IF(AND(TRUE,R$66<>""),SUM(R68:R72),"") | S73: =IF(AND(TRUE,S$66<>""),SUM(S68:S72),"") | ... AO73: =IF(AND(TRUE,AO$66<>""),SUM(AO68:AO72),"")
J74: Utenze | K74: Gas | L74: =IF(AND(TRUE,L$66<>""),SUMIFS(Flussi!$F:$F,Flussi!$B:$B,L$66,Flussi!$D:$D,$J74,Flussi!$E:$E,$K74,Flussi!$A:$A,$D$2),"") -> 0 | M74: =IF(AND(TRUE,M$66<>""),SUMIFS(Flussi!$F:$F,Flussi!$B:$B,M$66,Flussi!$D:$D,$J74,Flussi!$E:$E,$K74,Flussi!$A:$A,$D$2),"") -> 0 | N74: =IF(AND(TRUE,N$66<>""),SUMIFS(Flussi!$F:$F,Flussi!$B:$B,N$66,Flussi!$D:$D,$J74,Flussi!$E:$E,$K74,Flussi!$A:$A,$D$2),"") -> 0 | O74: =IF(AND(TRUE,O$66<>""),SUMIFS(Flussi!$F:$F,Flussi!$B:$B,O$66,Flussi!$D:$D,$J74,Flussi!$E:$E,$K74,Flussi!$A:$A,$D$2),"") -> 0 | P74: =IF(AND(TRUE,P$66<>""),SUMIFS(Flussi!$F:$F,Flussi!$B:$B,P$66,Flussi!$D:$D,$J74,Flussi!$E:$E,$K74,Flussi!$A:$A,$D$2),"") -> 0 | Q74: =IF(AND(TRUE,Q$66<>""),SUMIFS(Flussi!$F:$F,Flussi!$B:$B,Q$66,Flussi!$D:$D,$J74,Flussi!$E:$E,$K74,Flussi!$A:$A,$D$2),"") | R74: =IF(AND(TRUE,R$66<>""),SUMIFS(Flussi!$F:$F,Flussi!$B:$B,R$66,Flussi!$D:$D,$J74,Flussi!$E:$E,$K74,Flussi!$A:$A,$D$2),"") | S74: =IF(AND(TRUE,S$66<>""),SUMIFS(Flussi!$F:$F,Flussi!$B:$B,S$66,Flussi!$D:$D,$J74,Flussi!$E:$E,$K74,Flussi!$A:$A,$D$2),"") | ... AO74: =IF(AND(TRUE,AO$66<>""),SUMIFS(Flussi!$F:$F,Flussi!$B:$B,AO$66,Flussi!$D:$D,$J74,Flussi!$E:$E,$K74,Flussi!$A:$A,$D$2),"")
J75: Utenze | K75: Luce | L75: =IF(AND(TRUE,L$66<>""),SUMIFS(Flussi!$F:$F,Flussi!$B:$B,L$66,Flussi!$D:$D,$J75,Flussi!$E:$E,$K75,Flussi!$A:$A,$D$2),"") -> 0 | M75: =IF(AND(TRUE,M$66<>""),SUMIFS(Flussi!$F:$F,Flussi!$B:$B,M$66,Flussi!$D:$D,$J75,Flussi!$E:$E,$K75,Flussi!$A:$A,$D$2),"") -> 0 | N75: =IF(AND(TRUE,N$66<>""),SUMIFS(Flussi!$F:$F,Flussi!$B:$B,N$66,Flussi!$D:$D,$J75,Flussi!$E:$E,$K75,Flussi!$A:$A,$D$2),"") -> 0 | O75: =IF(AND(TRUE,O$66<>""),SUMIFS(Flussi!$F:$F,Flussi!$B:$B,O$66,Flussi!$D:$D,$J75,Flussi!$E:$E,$K75,Flussi!$A:$A,$D$2),"") -> 0 | P75: =IF(AND(TRUE,P$66<>""),SUMIFS(Flussi!$F:$F,Flussi!$B:$B,P$66,Flussi!$D:$D,$J75,Flussi!$E:$E,$K75,Flussi!$A:$A,$D$2),"") -> 0 | Q75: =IF(AND(TRUE,Q$66<>""),SUMIFS(Flussi!$F:$F,Flussi!$B:$B,Q$66,Flussi!$D:$D,$J75,Flussi!$E:$E,$K75,Flussi!$A:$A,$D$2),"") | R75: =IF(AND(TRUE,R$66<>""),SUMIFS(Flussi!$F:$F,Flussi!$B:$B,R$66,Flussi!$D:$D,$J75,Flussi!$E:$E,$K75,Flussi!$A:$A,$D$2),"") | S75: =IF(AND(TRUE,S$66<>""),SUMIFS(Flussi!$F:$F,Flussi!$B:$B,S$66,Flussi!$D:$D,$J75,Flussi!$E:$E,$K75,Flussi!$A:$A,$D$2),"") | ... AO75: =IF(AND(TRUE,AO$66<>""),SUMIFS(Flussi!$F:$F,Flussi!$B:$B,AO$66,Flussi!$D:$D,$J75,Flussi!$E:$E,$K75,Flussi!$A:$A,$D$2),"")
J76: Utenze | K76: Internet | L76: =IF(AND(TRUE,L$66<>""),SUMIFS(Flussi!$F:$F,Flussi!$B:$B,L$66,Flussi!$D:$D,$J76,Flussi!$E:$E,$K76,Flussi!$A:$A,$D$2),"") -> 0 | M76: =IF(AND(TRUE,M$66<>""),SUMIFS(Flussi!$F:$F,Flussi!$B:$B,M$66,Flussi!$D:$D,$J76,Flussi!$E:$E,$K76,Flussi!$A:$A,$D$2),"") -> 0 | N76: =IF(AND(TRUE,N$66<>""),SUMIFS(Flussi!$F:$F,Flussi!$B:$B,N$66,Flussi!$D:$D,$J76,Flussi!$E:$E,$K76,Flussi!$A:$A,$D$2),"") -> 0 | O76: =IF(AND(TRUE,O$66<>""),SUMIFS(Flussi!$F:$F,Flussi!$B:$B,O$66,Flussi!$D:$D,$J76,Flussi!$E:$E,$K76,Flussi!$A:$A,$D$2),"") -> 0 | P76: =IF(AND(TRUE,P$66<>""),SUMIFS(Flussi!$F:$F,Flussi!$B:$B,P$66,Flussi!$D:$D,$J76,Flussi!$E:$E,$K76,Flussi!$A:$A,$D$2),"") -> 0 | Q76: =IF(AND(TRUE,Q$66<>""),SUMIFS(Flussi!$F:$F,Flussi!$B:$B,Q$66,Flussi!$D:$D,$J76,Flussi!$E:$E,$K76,Flussi!$A:$A,$D$2),"") | R76: =IF(AND(TRUE,R$66<>""),SUMIFS(Flussi!$F:$F,Flussi!$B:$B,R$66,Flussi!$D:$D,$J76,Flussi!$E:$E,$K76,Flussi!$A:$A,$D$2),"") | S76: =IF(AND(TRUE,S$66<>""),SUMIFS(Flussi!$F:$F,Flussi!$B:$B,S$66,Flussi!$D:$D,$J76,Flussi!$E:$E,$K76,Flussi!$A:$A,$D$2),"") | ... AO76: =IF(AND(TRUE,AO$66<>""),SUMIFS(Flussi!$F:$F,Flussi!$B:$B,AO$66,Flussi!$D:$D,$J76,Flussi!$E:$E,$K76,Flussi!$A:$A,$D$2),"")
J77: Avviamento | K77: Intermediazione | L77: =IF(AND(TRUE,L$66<>""),SUMIFS(Flussi!$F:$F,Flussi!$B:$B,L$66,Flussi!$D:$D,$J77,Flussi!$E:$E,$K77,Flussi!$A:$A,$D$2),"") -> -1220 | M77: =IF(AND(TRUE,M$66<>""),SUMIFS(Flussi!$F:$F,Flussi!$B:$B,M$66,Flussi!$D:$D,$J77,Flussi!$E:$E,$K77,Flussi!$A:$A,$D$2),"") -> 0 | N77: =IF(AND(TRUE,N$66<>""),SUMIFS(Flussi!$F:$F,Flussi!$B:$B,N$66,Flussi!$D:$D,$J77,Flussi!$E:$E,$K77,Flussi!$A:$A,$D$2),"") -> 0 | O77: =IF(AND(TRUE,O$66<>""),SUMIFS(Flussi!$F:$F,Flussi!$B:$B,O$66,Flussi!$D:$D,$J77,Flussi!$E:$E,$K77,Flussi!$A:$A,$D$2),"") -> 0 | P77: =IF(AND(TRUE,P$66<>""),SUMIFS(Flussi!$F:$F,Flussi!$B:$B,P$66,Flussi!$D:$D,$J77,Flussi!$E:$E,$K77,Flussi!$A:$A,$D$2),"") -> 0 | Q77: =IF(AND(TRUE,Q$66<>""),SUMIFS(Flussi!$F:$F,Flussi!$B:$B,Q$66,Flussi!$D:$D,$J77,Flussi!$E:$E,$K77,Flussi!$A:$A,$D$2),"") | R77: =IF(AND(TRUE,R$66<>""),SUMIFS(Flussi!$F:$F,Flussi!$B:$B,R$66,Flussi!$D:$D,$J77,Flussi!$E:$E,$K77,Flussi!$A:$A,$D$2),"") | S77: =IF(AND(TRUE,S$66<>""),SUMIFS(Flussi!$F:$F,Flussi!$B:$B,S$66,Flussi!$D:$D,$J77,Flussi!$E:$E,$K77,Flussi!$A:$A,$D$2),"") | ... AO77: =IF(AND(TRUE,AO$66<>""),SUMIFS(Flussi!$F:$F,Flussi!$B:$B,AO$66,Flussi!$D:$D,$J77,Flussi!$E:$E,$K77,Flussi!$A:$A,$D$2),"")
J78: Avviamento | K78: Notaio | L78: =IF(AND(TRUE,L$66<>""),SUMIFS(Flussi!$F:$F,Flussi!$B:$B,L$66,Flussi!$D:$D,$J78,Flussi!$E:$E,$K78,Flussi!$A:$A,$D$2),"") -> -2372.61 | M78: =IF(AND(TRUE,M$66<>""),SUMIFS(Flussi!$F:$F,Flussi!$B:$B,M$66,Flussi!$D:$D,$J78,Flussi!$E:$E,$K78,Flussi!$A:$A,$D$2),"") -> 0 | N78: =IF(AND(TRUE,N$66<>""),SUMIFS(Flussi!$F:$F,Flussi!$B:$B,N$66,Flussi!$D:$D,$J78,Flussi!$E:$E,$K78,Flussi!$A:$A,$D$2),"") -> 0 | O78: =IF(AND(TRUE,O$66<>""),SUMIFS(Flussi!$F:$F,Flussi!$B:$B,O$66,Flussi!$D:$D,$J78,Flussi!$E:$E,$K78,Flussi!$A:$A,$D$2),"") -> 0 | P78: =IF(AND(TRUE,P$66<>""),SUMIFS(Flussi!$F:$F,Flussi!$B:$B,P$66,Flussi!$D:$D,$J78,Flussi!$E:$E,$K78,Flussi!$A:$A,$D$2),"") -> 0 | Q78: =IF(AND(TRUE,Q$66<>""),SUMIFS(Flussi!$F:$F,Flussi!$B:$B,Q$66,Flussi!$D:$D,$J78,Flussi!$E:$E,$K78,Flussi!$A:$A,$D$2),"") | R78: =IF(AND(TRUE,R$66<>""),SUMIFS(Flussi!$F:$F,Flussi!$B:$B,R$66,Flussi!$D:$D,$J78,Flussi!$E:$E,$K78,Flussi!$A:$A,$D$2),"") | S78: =IF(AND(TRUE,S$66<>""),SUMIFS(Flussi!$F:$F,Flussi!$B:$B,S$66,Flussi!$D:$D,$J78,Flussi!$E:$E,$K78,Flussi!$A:$A,$D$2),"") | ... AO78: =IF(AND(TRUE,AO$66<>""),SUMIFS(Flussi!$F:$F,Flussi!$B:$B,AO$66,Flussi!$D:$D,$J78,Flussi!$E:$E,$K78,Flussi!$A:$A,$D$2),"")
J79: Condominio | K79: - | L79: =IF(AND(TRUE,L$66<>""),SUMIFS(Flussi!$F:$F,Flussi!$B:$B,L$66,Flussi!$D:$D,$J79,Flussi!$E:$E,$K79,Flussi!$A:$A,$D$2),"") -> 0 | M79: =IF(AND(TRUE,M$66<>""),SUMIFS(Flussi!$F:$F,Flussi!$B:$B,M$66,Flussi!$D:$D,$J79,Flussi!$E:$E,$K79,Flussi!$A:$A,$D$2),"") -> 0 | N79: =IF(AND(TRUE,N$66<>""),SUMIFS(Flussi!$F:$F,Flussi!$B:$B,N$66,Flussi!$D:$D,$J79,Flussi!$E:$E,$K79,Flussi!$A:$A,$D$2),"") -> -99.95 | O79: =IF(AND(TRUE,O$66<>""),SUMIFS(Flussi!$F:$F,Flussi!$B:$B,O$66,Flussi!$D:$D,$J79,Flussi!$E:$E,$K79,Flussi!$A:$A,$D$2),"") -> -168 | P79: =IF(AND(TRUE,P$66<>""),SUMIFS(Flussi!$F:$F,Flussi!$B:$B,P$66,Flussi!$D:$D,$J79,Flussi!$E:$E,$K79,Flussi!$A:$A,$D$2),"") -> 0 | Q79: =IF(AND(TRUE,Q$66<>""),SUMIFS(Flussi!$F:$F,Flussi!$B:$B,Q$66,Flussi!$D:$D,$J79,Flussi!$E:$E,$K79,Flussi!$A:$A,$D$2),"") | R79: =IF(AND(TRUE,R$66<>""),SUMIFS(Flussi!$F:$F,Flussi!$B:$B,R$66,Flussi!$D:$D,$J79,Flussi!$E:$E,$K79,Flussi!$A:$A,$D$2),"") | S79: =IF(AND(TRUE,S$66<>""),SUMIFS(Flussi!$F:$F,Flussi!$B:$B,S$66,Flussi!$D:$D,$J79,Flussi!$E:$E,$K79,Flussi!$A:$A,$D$2),"") | ... AO79: =IF(AND(TRUE,AO$66<>""),SUMIFS(Flussi!$F:$F,Flussi!$B:$B,AO$66,Flussi!$D:$D,$J79,Flussi!$E:$E,$K79,Flussi!$A:$A,$D$2),"")
